Workbook

Sheet Bank Schedule
C1: Hide | D1: Hide | E1: Hide
C2: Hide | D2: Hide | E2: Hide | I2: Hide | J2: Hide | R2: Hide | S2: Hide | U2: Hide | W2: Hide | AE2: Hide | AF2: Hide | AG2: Hide | AH2: Hide
B3: Surveyor | C3: Client | D3: Property Number | E3: Property | F3: Unit Demise | G3: Unit Type | H3: Net Area | I3: . | J3: Agency Area group | K3: Tenant Name | L3: Start Date | M3: Expiry Date | N3: Vacant Since? | O3: RRs | P3: Break Date | Q3: Rent PA (£) | R3: check 1 | S3: check 2 | T3: 2023 ERV (£) | U3: check 3 | V3: 2024 ERV (£) | W3: check 4 | X3: ERV 2024 £.Sq.ft | Y3: ERV Variation | Z3: EPC | AA3: * | AB3: 2024 Cap Valn. (£) | AC3: 1954 Act Protected | AD3: Remarks | AE3: Agency Quoting Rent £.sq.ft | AF3: Monthly Viewings | AG3: Total Viewings | AH3: Marketing Agent
G5: 5-6 Bywell Place
B7: JM | C7: MEL | D7: 550020 | E7: 5-6 Bywell Place | F7: Whole Building | G7: Office | H7: 2011 | I7: =H7 | J7: 2000 | K7: 111 Skin Limited | L7: 45365 | M7: 47190 | P7: 46459 | Q7: 115500 | R7: =Q7 | S7: =R7 | T7: 100600 | U7: =T7 | V7: 115000 | W7: =V7 | X7: =V7/H7 | Y7: =SUM(V7-T7)/T7 | Z7: C | AB7: 1825000 | AC7: No | AD7: Tenant break on 6 months notice. Break penalty of £28,875 if exercised.
F8: 5/6 Bywell Place | H8: =SUM(H7:H7)
G9: 22 and 23-25 Eastcastle Street
B11: SH | C11: MEL | D11: 550910 | E11: 22 and 23-25 Eastcastle Street | F11: Lower Ground & Ground (22) | G11: Retail | H11: 2333 | I11: =H11 | J11: 2000 | K11: Top Bridal Ltd | L11: 45736 | M11: 47561 | P11: 46831 | Q11: 128000 | R11: =Q11 | T11: 110000 | U11: =T11 | V11: 108100 | W11: =V11 | X11: =V11/H11 | Y11: =SUM(V11-T11)/T11 | Z11: C | AC11: No | AD11: Stepped rent increasing to £130,000 wef 20/03/27. Tenant break on 6 months notice. | AF11: 1 | AG11: 3
B12: SH | C12: MEL | D12: 550910 | E12: 22 and 23-25 Eastcastle Street | F12: Lower Ground & Ground (23-25) | G12: Gallery | H12: 6092 | I12: =H12 | J12: 6000 | K12: Sisters Grimm Ltd | L12: 45712 | M12: 47537 | P12: 46806 | Q12: 325000 | R12: =Q12 | T12: 225000 | U12: =T12 | V12: 226100 | W12: =V12 | X12: =V12/H12 | Y12: =SUM(V12-T12)/T12 | Z12: B | AC12: No | AD12: Tenant break on 6 months notice. 1 month rent free from 24/02/28 if break not excerised. | AG12: 3 | AH12: LEM
B13: SH | C13: MEL | D13: 550910 | E13: 22 and 23-25 Eastcastle Street | F13: First Floor (22) | G13: Office | H13: 1063 | I13: =H13 | J13: 1000 | K13: Peter Alexander UK Ltd | L13: 45551 | M13: 47376 | P13: 46645 | Q13: 61425 | R13: =Q13 | T13: 55700 | U13: =T13 | V13: 61100 | W13: =V13 | X13: =V13/H13 | Y13: =SUM(V13-T13)/T13 | Z13: D | AC13: No | AD13: Tenant break on 3 months notice. Additional 3 months rent free if not exercised. | AH13: LEM
B14: SH | C14: MEL | D14: 550910 | E14: 22 and 23-25 Eastcastle Street | F14: First Floor (23-25) | G14: Office | H14: 2220 | I14: =H14 | J14: 2000 | K14: Cord Technologies Ltd | L14: 45086 | M14: 46181 | Q14: 131400 | R14: =Q14 | T14: 131100 | U14: =T14 | V14: 133200 | W14: =V14 | X14: =V14/H14 | Y14: =SUM(V14-T14)/T14 | Z14: D | AC14: No | AD14: Tenant break passed.
B15: SH | C15: MEL | D15: 550910 | E15: 22 and 23-25 Eastcastle Street | F15: Second Floor (22) | G15: Office | H15: 1124 | I15: =H15 | J15: 1000 | K15: Cord Technologies Ltd | L15: 45614 | M15: 46181 | Q15: 71875 | R15: =Q15 | T15: 60400 | U15: =T15 | V15: 61800 | W15: =V15 | X15: =V15/H15 | Y15: =SUM(V15-T15)/T15 | Z15: B | AC15: No | AD15: Tenant break passed.
B16: SH | C16: MEL | D16: 550910 | E16: 22 and 23-25 Eastcastle Street | F16: Second Floor (23-25) | G16: Office | H16: 2238 | I16: =H16 | J16: 2000 | K16: Vacant | N16: 45636 | Q16: 0 | R16: =Q16 | T16: 134300 | U16: =T16 | V16: 134300 | W16: =V16 | X16: =V16/H16 | Y16: =SUM(V16-T16)/T16 | Z16: D | AC16: No | AD16: LEM marketing. | AF16: 2 | AG16: 2
B17: SH | C17: MEL | D17: 550910 | E17: 22 and 23-25 Eastcastle Street | F17: Third Floor (22) | G17: Office | H17: 400 | I17: =H17 | J17: 500 | K17: Vacant | N17: 45771 | Q17: 0 | R17: =Q17 | T17: 20600 | U17: =T17 | V17: 23000 | W17: =V17 | X17: =V17/H17 | Y17: =SUM(V17-T17)/T17 | Z17: D | AC17: No | AD17: LEM marketing. | AF17: 1 | AG17: 1
B18: SH | C18: MEL | D18: 550910 | E18: 22 and 23-25 Eastcastle Street | F18: Third Floor (23-25) | G18: Office | H18: 1938 | I18: =H18 | J18: 2000 | K18: Vacant | N18: 45217 | Q18: 0 | R18: =Q18 | T18: 109000 | U18: =T18 | V18: 111400 | W18: =V18 | X18: =V18/H18 | Y18: =SUM(V18-T18)/T18 | Z18: D | AC18: No | AD18: LEM marketing. | AE18: 65 | AF18: 2 | AG18: 4
B19: SH | C19: MEL | D19: 550910 | E19: 22 and 23-25 Eastcastle Street | F19: Fourth Floor (22) | G19: Office | H19: 419 | I19: =H19 | J19: 500 | K19: Element Pictures UK Ltd. | L19: 44539 | M19: 46364 | Q19: 23940 | R19: =Q19 | T19: 21000 | U19: =T19 | V19: 24100 | W19: =V19 | X19: =V19/H19 | Y19: =SUM(V19-T19)/T19 | Z19: D | AC19: No | AF19: 1 | AG19: 1
B20: SH | C20: MEL | D20: 550910 | E20: 22 and 23-25 Eastcastle Street | F20: Fourth Floor (23-25) | G20: Office | H20: 972 | I20: =H20 | J20: 1000 | K20: Encore Search (Newburgh Street) Ltd. | L20: 45100 | M20: 46926 | P20: 46195 | Q20: 58560 | R20: =Q20 | T20: 49400 | U20: =T20 | V20: 58300 | W20: =V20 | X20: =V20/H20 | Y20: =SUM(V20-T20)/T20 | Z20: D | AC20: No | AD20: Tenant break on 6 months notice. 3 months rent free if not exercised.
B21: SH | C21: MEL | D21: 550910 | E21: 22 and 23-25 Eastcastle Street | F21: Fifth Floor (23-25) | G21: Office | H21: 977 | I21: =H21 | J21: 1000 | K21: Element Pictures UK Ltd. | L21: 45476 | M21: 47301 | P21: 46364 | Q21: 58496 | R21: =Q21 | T21: 47400 | U21: =T21 | V21: 58600 | W21: =V21 | X21: =V21/H21 | Y21: =SUM(V21-T21)/T21 | Z21: B | AC21: No | AD21: Tenant break on 6 months notice.
B22: SH | C22: MEL | D22: 550910 | E22: 22 and 23-25 Eastcastle Street | F22: Sixth Floor (23-25) | G22: Office | H22: 744 | I22: =H22 | J22: 750 | K22: Vacant | N22: 45182 | Q22: 0 | R22: =Q22 | T22: 34400 | U22: =T22 | V22: 47000 | W22: =V22 | X22: =V22/H22 | Y22: =SUM(V22-T22)/T22 | Z22: D | AC22: No | AD22: LEM marketing. | AE22: 63.5 | AF22: 2 | AG22: 4 | AH22: LEM
B23: SH | C23: MEL | D23: 550910 | E23: 22 and 23-25 Eastcastle Street | F23: Garage | G23: Parking | H23: 185 | I23: =H23 | J23: 200 | K23: Vacant / Landlord | N23: N/A | Q23: 0 | R23: =Q23 | T23: 3000 | U23: =T23 | V23: 4500 | W23: =V23 | X23: =V23/H23 | Y23: =SUM(V23-T23)/T23 | AC23: No
C24: MEL
C25: MEL | F25: 22, 23 & 25 Eastcastle St | H25: =SUM(H11:H23) | Q25: =SUM(Q11:Q23) | S25: =SUM(R10:R23) | T25: =SUM(T11:T23) | V25: =SUM(V11:V23) | AB25: 14850000
C26: MEL
C27: MEL | G27: 26 Eastcastle Street
C28: MEL
B29: SH | C29: MEL | D29: 550920 | E29: 26 Eastcastle Street | F29: Lower Ground & Ground | G29: Showroom/ Offices | H29: 2940 | I29: =H29 | J29: 3000 | K29: Hela Brands Ltd | L29: 45649 | M29: 46743 | P29: 46013 | Q29: 132000 | R29: =Q29 | T29: 114600 | U29: =T29 | V29: 124500 | W29: =V29 | X29: =V29/H29 | Y29: =SUM(V29-T29)/T29 | Z29: C | AC29: No | AD29: Tenant rolling break from 22/12/25 on 4 months notice.
B30: SH | C30: MEL | D30: 550920 | E30: 26 Eastcastle Street | F30: First Floor | G30: Offices | H30: 1398 | I30: =H30 | J30: 1000 | K30: Alternative Real Estate Advisors Ltd | L30: 45470 | M30: 47295 | P30: 46564 | Q30: 89833 | R30: =Q30 | T30: 76900 | U30: =T30 | V30: 97900 | W30: =V30 | X30: =V30/H30 | Y30: =SUM(V30-T30)/T30 | Z30: D | AC30: No | AD30: Rent increases to £98,000 wef 27/06/27. Tenant break on 6 months notice.
B31: SH | C31: MEL | D31: 550920 | E31: 26 Eastcastle Street | F31: Second Floor | G31: Offices | H31: 1110 | I31: =H31 | J31: 1000 | K31: Vacant | N31: 43273 | Q31: 0 | R31: =Q31 | T31: 61100 | U31: =T31 | V31: 69400 | W31: =V31 | X31: =V31/H31 | Y31: =SUM(V31-T31)/T31 | Z31: C | AC31: No | AD31: LEM marketing. | AE31: 63.5 | AG31: 1
B32: SH | C32: MEL | D32: 550920 | E32: 26 Eastcastle Street | F32: Third Floor | G32: Offices | H32: 481 | I32: =H32 | J32: 500 | K32: Mr. A. Park | L32: 45541 | M32: 47366 | P32: 46635 | Q32: 26000 | R32: =Q32 | T32: 25300 | U32: =T32 | V32: 25300 | W32: =V32 | X32: =V32/H32 | Y32: =SUM(V32-T32)/T32 | Z32: D | AC32: No | AD32: Tenant break on 6 months notice.
C33: MEL
C34: MEL | F34: 26 Eastcastle Street | H34: =SUM(H29:H32) | Q34: =SUM(Q29:Q32) | S34: =SUM(R29:R32) | T34: =SUM(T29:T32) | V34: =SUM(V29:V32) | AB34: 4725000
C35: MEL
C36: MEL | G36: 27 - 28 Eastcastle Street
C37: MEL
B38: SH | C38: MEL | D38: 550930 | E38: 27 - 28 Eastcastle Street | F38: Lower Ground & Ground | G38: Showroom / Offices | H38: 3668 | I38: =H38 | J38: 3500 | K38: The London Hair Clinic Ltd | L38: 44757 | M38: 48409 | O38: 46583 | Q38: 170000 | R38: =Q38 | T38: 170000 | U38: =T38 | V38: 170000 | W38: =V38 | X38: =V38/H38 | Y38: =SUM(V38-T38)/T38 | Z38: B | AC38: No
B39: SH | C39: MEL | D39: 550930 | E39: 27 - 28 Eastcastle Street | F39: First Floor | G39: Offices | H39: 1418 | I39: =H39 | J39: 1500 | K39: Feldberg Capital UK Limited | L39: 45231 | M39: 46326 | Q39: 174500 | R39: =Q39 | T39: 78000 | U39: =T39 | V39: 99300 | W39: =V39 | X39: =V39/H39 | Y39: =SUM(V39-T39)/T39 | Z39: B | AC39: No | AD39: All inclusive including rates and furniture.
B40: SH | C40: MEL | D40: 550930 | E40: 27 - 28 Eastcastle Street | F40: Second Floor | G40: Offices | H40: 716 | I40: =H40 | J40: 750 | K40: MSP Secretaries Ltd. | L40: 44384 | M40: 46209 | Q40: 41000 | R40: =Q40 | T40: 39400 | U40: =T40 | V40: 41200 | W40: =V40 | X40: =V40/H40 | Y40: =SUM(V40-T40)/T40 | Z40: B | AC40: No
B41: SH | C41: MEL | D41: 550930 | E41: 27 - 28 Eastcastle Street | F41: Third Floor | G41: Offices | H41: 665 | I41: =H41 | J41: 750 | K41: Principle Estate Management LLP | L41: 45617 | M41: 47442 | P41: 46527 | Q41: 41875 | R41: =Q41 | T41: 36600 | U41: =T41 | V41: 38200 | W41: =V41 | X41: =V41/H41 | Y41: =SUM(V41-T41)/T41 | Z41: B | AC41: No | AD41: Tenant break on 6 months notice. 2 months rent free if break not exercised.
C42: MEL
C43: MEL | F43: 27/28 Eastcastle Street | H43: =SUM(H38:H41) | Q43: =SUM(Q36:Q41) | S43: =SUM(R38:R41) | T43: =SUM(T38:T41) | V43: =SUM(V38:V41) | AB43: 5675000
C44: MEL
C45: MEL | G45: 10 Great Castle Street
C46: MEL
B47: WS | C47: MEL | D47: 550560 | E47: 10 Great Castle Street | F47: Basmt. Ground - 1 to 4 Floors | G47: Office | H47: 12578 | I47: =H47 | J47: 12500 | K47: Guaranty Trust Bank (UK) Ltd | L47: 44771 | M47: 50249 | O47: 46597 | P47: 48423 | Q47: 633334 | R47: =Q47 | S47: =R47 | T47: 950000 | U47: =T47 | V47: 950000 | W47: =V47 | X47: =V47/H47 | Y47: =SUM(V47-T47)/T47 | Z47: C | AB47: 17050000 | AC47: No | AD47: Fixed increase to £950,000 wef 29/07/26. 5 yearly rent reviews. Tenant break on 9 months notice. Rent reduces by 20% for 12 months if break not activated.
C48: MEL | F48: 8-11 Great Castle Street | H48: =SUM(H47:H47) | Q48: =SUM(Q47:Q47) | T48: =SUM(T47:T47) | V48: =SUM(V47:V47)
C49: MEL | G49: Windsor House, 40-41 Great Castle Street
C50: MEL
B51: SH | C51: MEL | D51: 550070 | E51: Windsor House, 40-41 Great Castle Street | F51: Basement & Ground Floor | G51: Retail/Café | H51: 2235 | I51: =H51 | J51: 2000 | K51: Vacant | N51: 45754 | Q51: 0 | R51: =Q51 | T51: 143000 | U51: =T51 | V51: 145000 | W51: =V51 | X51: =V51/H51 | Y51: =SUM(V51-T51)/T51 | Z51: D | AC51: No | AD51: LEM Marketing. | AF51: 15 | AG51: 15
B52: SH | C52: MEL | D52: 550070 | E52: Windsor House, 40-41 Great Castle Street | F52: First Floor | G52: Office | H52: 694 | I52: =H52 | J52: 750 | K52: JRDL UK Ltd. | L52: 44904 | M52: 45999 | Q52: 42000 | R52: =Q52 | T52: 42000 | U52: =T52 | V52: 42000 | W52: =V52 | X52: =V52/H52 | Y52: =SUM(V52-T52)/T52 | Z52: D | AC52: No
B53: SH | C53: MEL | D53: 550070 | E53: Windsor House, 40-41 Great Castle Street | F53: Second Floor | G53: Office | H53: 690 | I53: =H53 | J53: 750 | K53: Jamieson Stone Services Ltd. | L53: 45412 | M53: 47237 | P53: 46326 | Q53: 40020 | R53: =Q53 | T53: 39700 | U53: =T53 | V53: 40000 | W53: =V53 | X53: =V53/H53 | Y53: =SUM(V53-T53)/T53 | Z53: D | AC53: No | AD53: Tenant break on 6 months notice.
B54: SH | C54: MEL | D54: 550070 | E54: Windsor House, 40-41 Great Castle Street | F54: Third Floor | G54: Office | H54: 620 | I54: =H54 | J54: 750 | K54: Arav Fashion UK Ltd. | L54: 44816 | M54: 45911 | Q54: 33480 | R54: =Q54 | T54: 34100 | U54: =T54 | V54: 36000 | W54: =V54 | X54: =V54/H54 | Y54: =SUM(V54-T54)/T54 | Z54: D | AC54: No
B55: SH | C55: MEL | D55: 550070 | E55: Windsor House, 40-41 Great Castle Street | F55: Fourth Floor | G55: Office | H55: 400 | I55: =H55 | J55: 500 | K55: Vacant | N55: 44168 | Q55: 0 | R55: =Q55 | T55: 21600 | U55: =T55 | V55: 22000 | W55: =V55 | X55: =V55/H55 | Y55: =SUM(V55-T55)/T55 | Z55: D | AC55: No | AD55: To be refurbished.
B56: SH | C56: MEL | D56: 550070 | E56: Windsor House, 40-41 Great Castle Street | F56: Roof | G56: Air Con Units | H56: 0 | I56: =H56 | K56: Vacant / Landlord | N56: N/A | Q56: 0 | R56: =Q56 | T56: 0 | U56: =T56 | V56: 0 | W56: =V56 | AC56: No
C57: MEL
C58: MEL | F58: 40/41 Great Castle Street | H58: =SUM(H51:H56) | Q58: =SUM(Q51:Q56) | S58: =SUM(R51:R56) | T58: =SUM(T51:T56) | V58: =SUM(V51:V56) | AB58: 4750000
C59: MEL
C60: MEL | G60: Portland House, 4 Great Portland Street
C61: MEL
B62: SH | C62: MEL | D62: 550470 | E62: Portland House, 4 Great Portland Street | F62: Basement (West) | G62: Restaurant/Bar | H62: 2945 | I62: =H62 | J62: 3000 | K62: The London Cocktail Club Ltd | L62: 41457 | M62: 46935 | Q62: 147500 | R62: =Q62 | T62: 147500 | U62: =T62 | V62: 147500 | W62: =V62 | X62: =V62/H62 | Y62: =SUM(V62-T62)/T62 | Z62: E | AC62: No | AD62: 5 year reversionary lease completed from 02/07/28 with day one rent review. Rent review to be documented at passing rent.
B63: SH | C63: MEL | D63: 550470 | E63: Portland House, 4 Great Portland Street | F63: Ground Floor | G63: Retail/Cafe | H63: 2103 | I63: =H63 | J63: 2000 | K63: Costa Ltd | L63: 45669 | M63: 51146 | O63: 47495 | P63: 49320 | Q63: 220000 | R63: =Q63 | T63: 176200 | U63: =T63 | V63: 220000 | W63: =V63 | X63: =V63/H63 | Y63: =SUM(V63-T63)/T63 | Z63: B | AC63: No | AD63: Mutual break on 6 months notice.
B64: SH | C64: MEL | D64: 550470 | E64: Portland House, 4 Great Portland Street | F64: Ground Floor & Basement (East) & Basement Vaults | G64: Restaurant | H64: 5667 | I64: =H64 | J64: 5500 | K64: Futuremaxx Ltd | L64: 45567 | M64: 51044 | O64: 47393 | Q64: 150000 | R64: =Q64 | T64: 255000 | U64: =T64 | V64: 300000 | W64: =V64 | X64: =V64/H64 | Y64: =SUM(V64-T64)/T64 | Z64: B | AC64: No | AD64: Stepped rent. £300,000 wef 02/10/25, £305,000 wef 02/10/26, £310,000 wef 02/10/27 and £320,000 wef 02/10/28. Min rent on review £330,000. Landlord redevelopment break option on 01/07/33 on 6 months notice.
B65: SH | C65: MEL | D65: 550470 | E65: Portland House, 4 Great Portland Street | F65: First Floor (West) | G65: Office | H65: 1784 | I65: =H65 | J65: 1750 | K65: Time & Tide Holdings (UK) Ltd | L65: 45457 | M65: 47282 | Q65: 60700 | R65: =Q65 | T65: 99700 | U65: =T65 | V65: 120400 | W65: =V65 | X65: =V65/H65 | Y65: =SUM(V65-T65)/T65 | Z65: B | AC65: No | AD65: Rent increases to £121,400 wef 14/08/25
B66: SH | C66: MEL | D66: 550470 | E66: Portland House, 4 Great Portland Street | F66: First Floor (East) | G66: Office | H66: 2075 | I66: =H66 | J66: 2000 | K66: L52 Communications Ltd | L66: 45384 | M66: 47209 | P66: 46478 | Q66: 133280 | R66: =Q66 | T66: 114700 | U66: =T66 | V66: 140100 | W66: =V66 | X66: =V66/H66 | Y66: =SUM(V66-T66)/T66 | Z66: B | AC66: No | AD66: Tenant break on 6 months notice. 1 month rent free from 02/04/27 if not exercised.
B67: SH | C67: MEL | D67: 550470 | E67: Portland House, 4 Great Portland Street | F67: Second Floor (East) | G67: Office | H67: 2063 | I67: =H67 | J67: 2000 | K67: Tekcor4 Limited | L67: 45516 | M67: 47341 | P67: 46610 | Q67: 146450 | R67: =Q67 | T67: 120700 | U67: =T67 | V67: 139260 | W67: =V67 | X67: =V67/H67 | Y67: =SUM(V67-T67)/T67 | Z67: B | AC67: No | AD67: Tenant break on 6 months notice.
B68: SH | C68: MEL | D68: 550470 | E68: Portland House, 4 Great Portland Street | F68: Second Floor (West) | G68: Office | H68: 1796 | I68: =H68 | J68: 1750 | K68: Vacant | N68: 45051 | Q68: 0 | R68: =Q68 | T68: 87300 | U68: =T68 | V68: 121240 | W68: =V68 | X68: =V68/H68 | Y68: =SUM(V68-T68)/T68 | Z68: B | AC68: No | AD68: LEM marketing. | AE68: 72.5 | AF68: 3 | AG68: 13 | AH68: LEM/LDG
B69: SH | C69: MEL | D69: 550470 | E69: Portland House, 4 Great Portland Street | F69: Third Floor (West) | G69: Office | H69: 1691 | I69: =H69 | J69: 1500 | K69: J&M Davidson Limited. | L69: 44795 | M69: 46620 | P69: 45890 | Q69: 102705 | R69: =Q69 | T69: 102705 | U69: =T69 | V69: 114100 | W69: =V69 | X69: =V69/H69 | Y69: =SUM(V69-T69)/T69 | Z69: B | AC69: No | AD69: Tenant break on 6 months notice.
B70: SH | C70: MEL | D70: 550470 | E70: Portland House, 4 Great Portland Street | F70: Third Floor (East) | G70: Office | H70: 2055 | I70: =H70 | J70: 2000 | K70: Media Campaign Limited | L70: 45488 | M70: 47313 | P70: 46582 | Q70: 181050 | R70: =Q70 | T70: 125050 | U70: =T70 | V70: 138700 | W70: =V70 | X70: =V70/H70 | Y70: =SUM(V70-T70)/T70 | Z70: B | AC70: No | AD70: Tenant break on 6 months notice. 2 months rent free @ 15/07/27 if not exercised.
B71: SH | C71: MEL | D71: 550470 | E71: Portland House, 4 Great Portland Street | F71: Fourth Floor (West) | G71: Office | H71: 1548 | I71: =H71 | J71: 1500 | K71: Racoon Media Services Limited | L71: 45609 | M71: 47434 | P71: 46703 | Q71: 90090 | R71: =Q71 | T71: 90100 | U71: =T71 | V71: 104500 | W71: =V71 | X71: =V71/H71 | Y71: =SUM(V71-T71)/T71 | Z71: B | AC71: No | AD71: Tenant break on 6 months notice. Rent PA corrected.
B72: SH | C72: MEL | D72: 550470 | E72: Portland House, 4 Great Portland Street | F72: Fourth Floor (East) | G72: Office | H72: 1957 | I72: =H72 | J72: 2000 | K72: Racoon Media Services Limited | L72: 45609 | M72: 47434 | P72: 46703 | Q72: 114253 | R72: =Q72 | T72: 115800 | U72: =T72 | V72: 132100 | W72: =V72 | X72: =V72/H72 | Y72: =SUM(V72-T72)/T72 | Z72: B | AC72: No | AD72: Tenant break on 6 months notice.
B73: SH | C73: MEL | D73: 550470 | E73: Portland House, 4 Great Portland Street | F73: Fifth Floor (East) | G73: Office | H73: 1845 | I73: =H73 | J73: 2000 | K73: Greek National Tourism Organisation. | L73: 45256 | M73: 47082 | P73: 46351 | Q73: 115500 | R73: =Q73 | T73: 107400 | U73: =T73 | V73: 124500 | W73: =V73 | X73: =V73/H73 | Y73: =SUM(V73-T73)/T73 | Z73: B | AC73: No | AD73: Tenant break on 6 months notice.
B74: SH | C74: MEL | D74: 550470 | E74: Portland House, 4 Great Portland Street | F74: Fifth Floor (West) | G74: Office | H74: 1528 | I74: =H74 | J74: 1500 | K74: Rios Designs Ltd | L74: 45622 | M74: 47447 | P74: 46716 | Q74: 54340 | R74: =Q74 | T74: 76600 | U74: =T74 | V74: 103100 | W74: =V74 | X74: =V74/H74 | Y74: =SUM(V74-T74)/T74 | Z74: B | AC74: No | AD74: Rent increases to £108,680 wef 26/11/25. Tenant break on 6 months notice. | AG74: 2 | AH74: LEM/LDG
B75: SH | C75: MEL | D75: 550470 | E75: Portland House, 4 Great Portland Street | F75: Sixth Floor (West) | G75: Office | H75: 1253 | I75: =H75 | J75: 1250 | K75: Directors Cut Films West Limited | L75: 45617 | M75: 47442 | Q75: 66700 | R75: =Q75 | T75: 66700 | U75: =T75 | V75: 78300 | W75: =V75 | X75: =V75/H75 | Y75: =SUM(V75-T75)/T75 | Z75: D | AC75: No
B76: SH | C76: MEL | D76: 550470 | E76: Portland House, 4 Great Portland Street | F76: Sixth Floor (East) | G76: Office | H76: 859 | I76: =H76 | J76: 1000 | K76: Vacant | N76: 44609 | Q76: 0 | R76: =Q76 | T76: 65750 | U76: =T76 | V76: 53700 | W76: =V76 | X76: =V76/H76 | Y76: =SUM(V76-T76)/T76 | Z76: D | AC76: No | AD76: LEM marketing. | AE76: 63 | AG76: 2
B77: SH | C77: MEL | D77: 550470 | E77: Portland House, 4 Great Portland Street | F77: Cupboards 2nd, 4th, 5th & 6th Floors | G77: Storage | H77: 0 | I77: =H77 | K77: Vacant / Landlord | N77: N/A | Q77: 0 | R77: =Q77 | T77: 1460 | U77: =T77 | V77: 0 | W77: =V77 | AD77: To be converted into extra toilet facilities.
B78: SH | C78: MEL | D78: 550470 | E78: Portland House, 4 Great Portland Street | F78: Transformer Chamber | G78: Sub-Station | H78: 0 | I78: =H78 | K78: London Power Networks Plc | L78: 35240 | M78: 68735 | Q78: 0 | R78: =Q78 | T78: 0 | U78: =T78 | V78: 0 | W78: =V78 | AC78: Yes | AD78: Rolling redevelopment break on 6 months notice.
C79: MEL
C80: MEL | F80: 4 Great Portland Street | H80: =SUM(H62:H78) | Q80: =SUM(Q62:Q78) | S80: =SUM(R62:R78) | T80: =SUM(T62:T78) | V80: =SUM(V62:V78) | AB80: 34025000
C81: MEL
C82: MEL | G82: 6-10a Great Portland Street
C83: MEL
B84: SH | C84: MEL | D84: 550480 | E84: 6-10a Great Portland Street | F84: Basement & Ground | G84: Retail | H84: 4958 | I84: =H84 | J84: 5000 | K84: PrettyLittleThing.com | L84: 45699 | M84: 47524 | P84: 46793 | Q84: 187500 | R84: =Q84 | T84: 337100 | U84: =T84 | V84: 380000 | W84: =V84 | X84: =V84/H84 | Y84: =SUM(V84-T84)/T84 | Z84: B | AC84: No | AD84: Rent increasing to £375,000 wef 11/09/25. Tenant break on 6 months notice. 3 months rent free if not exercised. | AE84: 68 | AF84: 1 | AG84: 13 | AH84: LEM / Colliers
B85: SH | C85: MEL | D85: 550480 | E85: 6-10a Great Portland Street | F85: First Floor | G85: Office | H85: 1862 | I85: =H85 | J85: 2000 | K85: The Yuki Clinic Ltd. | L85: 44452 | M85: 46277 | Q85: 108170 | R85: =Q85 | T85: 107200 | U85: =T85 | V85: 114500 | W85: =V85 | X85: =V85/H85 | Y85: =SUM(V85-T85)/T85 | Z85: D | AC85: No
B86: SH | C86: MEL | D86: 550480 | E86: 6-10a Great Portland Street | F86: Second Floor | G86: Office | H86: 1818 | I86: =H86 | J86: 2000 | K86: Vacant | N86: 45609 | Q86: 0 | R86: =Q86 | T86: 105500 | U86: =T86 | V86: 109100 | W86: =V86 | X86: =V86/H86 | Y86: =SUM(V86-T86)/T86 | Z86: E | AC86: No | AD86: LEM marketing. | AE86: 65 | AF86: 4 | AG86: 6
B87: SH | C87: MEL | D87: 550480 | E87: 6-10a Great Portland Street | F87: Third Floor | G87: Office | H87: 1808 | I87: =H87 | J87: 2000 | K87: Vacant | N87: 45609 | Q87: 0 | R87: =Q87 | T87: 108800 | U87: =T87 | V87: 108500 | W87: =V87 | X87: =V87/H87 | Y87: =SUM(V87-T87)/T87 | Z87: E | AC87: No | AD87: LEM marketing. | AE87: 65 | AF87: 4 | AG87: 6
B88: SH | C88: MEL | D88: 550480 | E88: 6-10a Great Portland Street | F88: Fourth Floor | G88: Office | H88: 1672 | I88: =H88 | J88: 1500 | K88: Vacant | N88: 45457 | Q88: 0 | R88: =Q88 | T88: 94400 | U88: =T88 | V88: 97800 | W88: =V88 | X88: =V88/H88 | Y88: =SUM(V88-T88)/T88 | Z88: B | AC88: No | AD88: To be refurbished. | AE88: 65 | AF88: 1 | AG88: 2 | AH88: LEM
B89: SH | C89: MEL | D89: 550480 | E89: 6-10a Great Portland Street | F89: Fifth Floor | G89: Office | H89: 995 | I89: =H89 | J89: 1000 | K89: Racoon Media Services Limited | L89: 45609 | M89: 47434 | P89: 46703 | Q89: 61928 | R89: =Q89 | T89: 61200 | U89: =T89 | V89: 57200 | W89: =V89 | X89: =V89/H89 | Y89: =SUM(V89-T89)/T89 | Z89: E | AC89: No | AD89: Tenant break on 6 months notice.
B90: SH | C90: MEL | D90: 550480 | E90: 6-10a Great Portland Street | F90: Basement | G90: Sub-Station | H90: 0 | I90: =H90 | K90: London Power Networks Plc | L90: 39295 | M90: 46599 | O90: 45870 | Q90: 903 | R90: =Q90 | T90: 625 | U90: =T90 | V90: 625 | W90: =V90 | AC90: No | AD90: Landlords redevelopment break on 6 months notice. Rent review is RPI indexation (every 2 years. Rent review completed. Backdated rent increased £737 wef 01/08/21 & £903 wef 01/08/23.
C91: MEL
C92: MEL | F92: 6/10a Great Portland Street | H92: =SUM(H84:H90) | Q92: =SUM(Q84:Q90) | S92: =SUM(R83:R90) | T92: =SUM(T84:T90) | V92: =SUM(V84:V90) | AB92: 13775000
C93: MEL
C94: MEL | G94: 15-17 Great Portland Street & 6-7 Great Castle Street
C95: MEL
B96: SH | C96: MEL | D96: 550530 | E96: 15-17 Great Portland Street & 6-7 Great Castle Street | F96: Whole Building | G96: Office/Bank | H96: 9884 | I96: =H96 | J96: 10000 | K96: Barclays Bank UK Plc | L96: 44856 | M96: 47411 | O96: 46682 | Q96: 580000 | R96: =Q96 | S96: =R96 | T96: 580000 | U96: =T96 | V96: 607100 | W96: =V96 | X96: =V96/H96 | Y96: =SUM(V96-T96)/T96 | Z96: B | AB96: 10650000 | AC96: Yes
C97: MEL | F97: 15/17 Great Portland Street | H97: =SUM(H96:H96) | Q97: =SUM(Q96:Q96) | T97: =SUM(T96:T96) | V97: =SUM(V96:V96)
C98: MEL
C99: MEL | G99: 19-21 Great Portland Street
C100: MEL
B101: CD | C101: MEL | D101: 550410 | E101: 19-21 Great Portland Street . | F101: Basement, Ground & First Floors | G101: Restaurant | H101: 11225 | I101: =H101 | J101: 10000 | K101: UK VAP GPS | L101: 44729 | M101: 50207 | O101: 46555 | P101: 48381 | Q101: 625000 | R101: =Q101 | T101: 750000 | U101: =T101 | V101: 650000 | W101: =V101 | X101: =V101/H101 | Y101: =SUM(V101-T101)/T101 | Z101: B | AC101: No | AD101: Rent increasing to £650,000 wef 25/03/26. Mutual break @ 16/06/32 on 6 months notice.
B102: CD | C102: MEL | D102: 550410 | E102: 19-21 Great Portland Street . | F102: Second Floor. | G102: Offices | H102: 2847 | I102: =H102 | J102: 3000 | K102: Vacant | N102: 45219 | Q102: 0 | R102: =Q102 | T102: 170000 | U102: =T102 | V102: 185100 | W102: =V102 | X102: =V102/H102 | Y102: =SUM(V102-T102)/T102 | Z102: B | AC102: No | AD102: LEM marketing. | AE102: 70 | AF102: 6 | AG102: 20 | AH102: LEM / Savills
B103: CD | C103: MEL | D103: 550410 | E103: 19-21 Great Portland Street . | F103: Third Floor | G103: Offices | H103: 2651 | I103: =H103 | J103: 2500 | K103: Vacant | N103: 44124 | Q103: 0 | R103: =Q103 | T103: 172000 | U103: =T103 | V103: 181600 | W103: =V103 | X103: =V103/H103 | Y103: =SUM(V103-T103)/T103 | Z103: B | AC103: No | AD103: LEM marketing. | AE103: 72.5 | AF103: 6 | AG103: 20 | AH103: LEM / Savills
...

Sheet Voids Tab
B3: Surveyor | C3: Client | D3: Property Number | E3: Property | F3: Unit Demise | G3: Unit Type | H3: Net Area | I3: . | J3: Agency Area | K3: Tenant Name | L3: Start Date | M3: Expiry Date | N3: Vacant Since? | O3: RRs | P3: Break Date | Q3: Rent PA (£) | R3: check 1 | S3: check 2 | T3: 2023 ERV (£) | U3: check 3 | V3: 2024 ERV (£) | W3: check 4 | X3: ERV 2024 £.Sq.ft | Z3: EPC | AA3: * | AB3: 2024 Cap Valn. (£) | AC3: 1954 Act Protected | AD3: Remarks | AE3: Agency Quoting Rent £.sq.ft | AF3: Monthly Viewings | AG3: Total Viewings | AH3: Marketing Agent
A4: {=IFERROR(INDEX('Bank Schedule'!A:A, SMALL(IF('Bank Schedule'!$K$2:$K$825="Vacant", ROW('Bank Schedule'!$K$2:$K$825)), ROW(1:1))), "")} | B4: {=IFERROR(INDEX('Bank Schedule'!B:B, SMALL(IF('Bank Schedule'!$K$2:$K$825="Vacant", ROW('Bank Schedule'!$K$2:$K$825)), ROW(1:1))), "")} | C4: {=IFERROR(INDEX('Bank Schedule'!C:C, SMALL(IF('Bank Schedule'!$K$2:$K$825="Vacant", ROW('Bank Schedule'!$K$2:$K$825)), ROW(1:1))), "")} | D4: {=IFERROR(INDEX('Bank Schedule'!D:D, SMALL(IF('Bank Schedule'!$K$2:$K$825="Vacant", ROW('Bank Schedule'!$K$2:$K$825)), ROW(1:1))), "")} | E4: {=IFERROR(INDEX('Bank Schedule'!E:E, SMALL(IF('Bank Schedule'!$K$2:$K$825="Vacant", ROW('Bank Schedule'!$K$2:$K$825)), ROW(1:1))), "")} | F4: {=IFERROR(INDEX('Bank Schedule'!F:F, SMALL(IF('Bank Schedule'!$K$2:$K$825="Vacant", ROW('Bank Schedule'!$K$2:$K$825)), ROW(1:1))), "")} | G4: {=IFERROR(INDEX('Bank Schedule'!G:G, SMALL(IF('Bank Schedule'!$K$2:$K$825="Vacant", ROW('Bank Schedule'!$K$2:$K$825)), ROW(1:1))), "")} | H4: {=IFERROR(INDEX('Bank Schedule'!H:H, SMALL(IF('Bank Schedule'!$K$2:$K$825="Vacant", ROW('Bank Schedule'!$K$2:$K$825)), ROW(1:1))), "")} | I4: {=IFERROR(INDEX('Bank Schedule'!I:I, SMALL(IF('Bank Schedule'!$K$2:$K$825="Vacant", ROW('Bank Schedule'!$K$2:$K$825)), ROW(1:1))), "")} | J4: {=IFERROR(INDEX('Bank Schedule'!J:J, SMALL(IF('Bank Schedule'!$K$2:$K$825="Vacant", ROW('Bank Schedule'!$K$2:$K$825)), ROW(1:1))), "")} | K4: {=IFERROR(INDEX('Bank Schedule'!K:K, SMALL(IF('Bank Schedule'!$K$2:$K$825="Vacant", ROW('Bank Schedule'!$K$2:$K$825)), ROW(1:1))), "")} | L4: {=IFERROR(INDEX('Bank Schedule'!L:L, SMALL(IF('Bank Schedule'!$K$2:$K$825="Vacant", ROW('Bank Schedule'!$K$2:$K$825)), ROW(1:1))), "")} | M4: {=IFERROR(INDEX('Bank Schedule'!M:M, SMALL(IF('Bank Schedule'!$K$2:$K$825="Vacant", ROW('Bank Schedule'!$K$2:$K$825)), ROW(1:1))), "")} | N4: {=IFERROR(INDEX('Bank Schedule'!N:N, SMALL(IF('Bank Schedule'!$K$2:$K$825="Vacant", ROW('Bank Schedule'!$K$2:$K$825)), ROW(1:1))), "")} | O4: {=IFERROR(INDEX('Bank Schedule'!O:O, SMALL(IF('Bank Schedule'!$K$2:$K$825="Vacant", ROW('Bank Schedule'!$K$2:$K$825)), ROW(1:1))), "")} | P4: {=IFERROR(INDEX('Bank Schedule'!P:P, SMALL(IF('Bank Schedule'!$K$2:$K$825="Vacant", ROW('Bank Schedule'!$K$2:$K$825)), ROW(1:1))), "")} | Q4: {=IFERROR(INDEX('Bank Schedule'!Q:Q, SMALL(IF('Bank Schedule'!$K$2:$K$825="Vacant", ROW('Bank Schedule'!$K$2:$K$825)), ROW(1:1))), "")} | R4: {=IFERROR(INDEX('Bank Schedule'!R:R, SMALL(IF('Bank Schedule'!$K$2:$K$825="Vacant", ROW('Bank Schedule'!$K$2:$K$825)), ROW(1:1))), "")} | S4: {=IFERROR(INDEX('Bank Schedule'!S:S, SMALL(IF('Bank Schedule'!$K$2:$K$825="Vacant", ROW('Bank Schedule'!$K$2:$K$825)), ROW(1:1))), "")} | T4: {=IFERROR(INDEX('Bank Schedule'!T:T, SMALL(IF('Bank Schedule'!$K$2:$K$825="Vacant", ROW('Bank Schedule'!$K$2:$K$825)), ROW(1:1))), "")} | U4: {=IFERROR(INDEX('Bank Schedule'!U:U, SMALL(IF('Bank Schedule'!$K$2:$K$825="Vacant", ROW('Bank Schedule'!$K$2:$K$825)), ROW(1:1))), "")} | V4: {=IFERROR(INDEX('Bank Schedule'!V:V, SMALL(IF('Bank Schedule'!$K$2:$K$825="Vacant", ROW('Bank Schedule'!$K$2:$K$825)), ROW(1:1))), "")} | W4: {=IFERROR(INDEX('Bank Schedule'!W:W, SMALL(IF('Bank Schedule'!$K$2:$K$825="Vacant", ROW('Bank Schedule'!$K$2:$K$825)), ROW(1:1))), "")} | X4: {=IFERROR(INDEX('Bank Schedule'!X:X, SMALL(IF('Bank Schedule'!$K$2:$K$825="Vacant", ROW('Bank Schedule'!$K$2:$K$825)), ROW(1:1))), "")} | Y4: {=IFERROR(INDEX('Bank Schedule'!Y:Y, SMALL(IF('Bank Schedule'!$K$2:$K$825="Vacant", ROW('Bank Schedule'!$K$2:$K$825)), ROW(1:1))), "")} | Z4: {=IFERROR(INDEX('Bank Schedule'!Z:Z, SMALL(IF('Bank Schedule'!$K$2:$K$825="Vacant", ROW('Bank Schedule'!$K$2:$K$825)), ROW(1:1))), "")} | AA4: {=IFERROR(INDEX('Bank Schedule'!AA:AA, SMALL(IF('Bank Schedule'!$K$2:$K$825="Vacant", ROW('Bank Schedule'!$K$2:$K$825)), ROW(1:1))), "")} | AB4: {=IFERROR(INDEX('Bank Schedule'!AB:AB, SMALL(IF('Bank Schedule'!$K$2:$K$825="Vacant", ROW('Bank Schedule'!$K$2:$K$825)), ROW(1:1))), "")} | AC4: {=IFERROR(INDEX('Bank Schedule'!AC:AC, SMALL(IF('Bank Schedule'!$K$2:$K$825="Vacant", ROW('Bank Schedule'!$K$2:$K$825)), ROW(1:1))), "")} | AD4: {=IFERROR(INDEX('Bank Schedule'!AD:AD, SMALL(IF('Bank Schedule'!$K$2:$K$825="Vacant", ROW('Bank Schedule'!$K$2:$K$825)), ROW(1:1))), "")} | AE4: {=IFERROR(INDEX('Bank Schedule'!AE:AE, SMALL(IF('Bank Schedule'!$K$2:$K$825="Vacant", ROW('Bank Schedule'!$K$2:$K$825)), ROW(1:1))), "")} | AF4: {=IFERROR(INDEX('Bank Schedule'!AF:AF, SMALL(IF('Bank Schedule'!$K$2:$K$825="Vacant", ROW('Bank Schedule'!$K$2:$K$825)), ROW(1:1))), "")} | AG4: {=IFERROR(INDEX('Bank Schedule'!AG:AG, SMALL(IF('Bank Schedule'!$K$2:$K$825="Vacant", ROW('Bank Schedule'!$K$2:$K$825)), ROW(1:1))), "")} | AH4: {=IFERROR(INDEX('Bank Schedule'!AH:AH, SMALL(IF('Bank Schedule'!$K$2:$K$825="Vacant", ROW('Bank Schedule'!$K$2:$K$825)), ROW(1:1))), "")}
A5: {=IFERROR(INDEX('Bank Schedule'!A:A, SMALL(IF('Bank Schedule'!$K$2:$K$825="Vacant", ROW('Bank Schedule'!$K$2:$K$825)), ROW(2:2))), "")} | B5: {=IFERROR(INDEX('Bank Schedule'!B:B, SMALL(IF('Bank Schedule'!$K$2:$K$825="Vacant", ROW('Bank Schedule'!$K$2:$K$825)), ROW(2:2))), "")} | C5: {=IFERROR(INDEX('Bank Schedule'!C:C, SMALL(IF('Bank Schedule'!$K$2:$K$825="Vacant", ROW('Bank Schedule'!$K$2:$K$825)), ROW(2:2))), "")} | D5: {=IFERROR(INDEX('Bank Schedule'!D:D, SMALL(IF('Bank Schedule'!$K$2:$K$825="Vacant", ROW('Bank Schedule'!$K$2:$K$825)), ROW(2:2))), "")} | E5: {=IFERROR(INDEX('Bank Schedule'!E:E, SMALL(IF('Bank Schedule'!$K$2:$K$825="Vacant", ROW('Bank Schedule'!$K$2:$K$825)), ROW(2:2))), "")} | F5: {=IFERROR(INDEX('Bank Schedule'!F:F, SMALL(IF('Bank Schedule'!$K$2:$K$825="Vacant", ROW('Bank Schedule'!$K$2:$K$825)), ROW(2:2))), "")} | G5: {=IFERROR(INDEX('Bank Schedule'!G:G, SMALL(IF('Bank Schedule'!$K$2:$K$825="Vacant", ROW('Bank Schedule'!$K$2:$K$825)), ROW(2:2))), "")} | H5: {=IFERROR(INDEX('Bank Schedule'!H:H, SMALL(IF('Bank Schedule'!$K$2:$K$825="Vacant", ROW('Bank Schedule'!$K$2:$K$825)), ROW(2:2))), "")} | I5: {=IFERROR(INDEX('Bank Schedule'!I:I, SMALL(IF('Bank Schedule'!$K$2:$K$825="Vacant", ROW('Bank Schedule'!$K$2:$K$825)), ROW(2:2))), "")} | J5: {=IFERROR(INDEX('Bank Schedule'!J:J, SMALL(IF('Bank Schedule'!$K$2:$K$825="Vacant", ROW('Bank Schedule'!$K$2:$K$825)), ROW(2:2))), "")} | K5: {=IFERROR(INDEX('Bank Schedule'!K:K, SMALL(IF('Bank Schedule'!$K$2:$K$825="Vacant", ROW('Bank Schedule'!$K$2:$K$825)), ROW(2:2))), "")} | L5: {=IFERROR(INDEX('Bank Schedule'!L:L, SMALL(IF('Bank Schedule'!$K$2:$K$825="Vacant", ROW('Bank Schedule'!$K$2:$K$825)), ROW(2:2))), "")} | M5: {=IFERROR(INDEX('Bank Schedule'!M:M, SMALL(IF('Bank Schedule'!$K$2:$K$825="Vacant", ROW('Bank Schedule'!$K$2:$K$825)), ROW(2:2))), "")} | N5: {=IFERROR(INDEX('Bank Schedule'!N:N, SMALL(IF('Bank Schedule'!$K$2:$K$825="Vacant", ROW('Bank Schedule'!$K$2:$K$825)), ROW(2:2))), "")} | O5: {=IFERROR(INDEX('Bank Schedule'!O:O, SMALL(IF('Bank Schedule'!$K$2:$K$825="Vacant", ROW('Bank Schedule'!$K$2:$K$825)), ROW(2:2))), "")} | P5: {=IFERROR(INDEX('Bank Schedule'!P:P, SMALL(IF('Bank Schedule'!$K$2:$K$825="Vacant", ROW('Bank Schedule'!$K$2:$K$825)), ROW(2:2))), "")} | Q5: {=IFERROR(INDEX('Bank Schedule'!Q:Q, SMALL(IF('Bank Schedule'!$K$2:$K$825="Vacant", ROW('Bank Schedule'!$K$2:$K$825)), ROW(2:2))), "")} | R5: {=IFERROR(INDEX('Bank Schedule'!R:R, SMALL(IF('Bank Schedule'!$K$2:$K$825="Vacant", ROW('Bank Schedule'!$K$2:$K$825)), ROW(2:2))), "")} | S5: {=IFERROR(INDEX('Bank Schedule'!S:S, SMALL(IF('Bank Schedule'!$K$2:$K$825="Vacant", ROW('Bank Schedule'!$K$2:$K$825)), ROW(2:2))), "")} | T5: {=IFERROR(INDEX('Bank Schedule'!T:T, SMALL(IF('Bank Schedule'!$K$2:$K$825="Vacant", ROW('Bank Schedule'!$K$2:$K$825)), ROW(2:2))), "")} | U5: {=IFERROR(INDEX('Bank Schedule'!U:U, SMALL(IF('Bank Schedule'!$K$2:$K$825="Vacant", ROW('Bank Schedule'!$K$2:$K$825)), ROW(2:2))), "")} | V5: {=IFERROR(INDEX('Bank Schedule'!V:V, SMALL(IF('Bank Schedule'!$K$2:$K$825="Vacant", ROW('Bank Schedule'!$K$2:$K$825)), ROW(2:2))), "")} | W5: {=IFERROR(INDEX('Bank Schedule'!W:W, SMALL(IF('Bank Schedule'!$K$2:$K$825="Vacant", ROW('Bank Schedule'!$K$2:$K$825)), ROW(2:2))), "")} | X5: {=IFERROR(INDEX('Bank Schedule'!X:X, SMALL(IF('Bank Schedule'!$K$2:$K$825="Vacant", ROW('Bank Schedule'!$K$2:$K$825)), ROW(2:2))), "")} | Y5: {=IFERROR(INDEX('Bank Schedule'!Y:Y, SMALL(IF('Bank Schedule'!$K$2:$K$825="Vacant", ROW('Bank Schedule'!$K$2:$K$825)), ROW(2:2))), "")} | Z5: {=IFERROR(INDEX('Bank Schedule'!Z:Z, SMALL(IF('Bank Schedule'!$K$2:$K$825="Vacant", ROW('Bank Schedule'!$K$2:$K$825)), ROW(2:2))), "")} | AA5: {=IFERROR(INDEX('Bank Schedule'!AA:AA, SMALL(IF('Bank Schedule'!$K$2:$K$825="Vacant", ROW('Bank Schedule'!$K$2:$K$825)), ROW(2:2))), "")} | AB5: {=IFERROR(INDEX('Bank Schedule'!AB:AB, SMALL(IF('Bank Schedule'!$K$2:$K$825="Vacant", ROW('Bank Schedule'!$K$2:$K$825)), ROW(2:2))), "")} | AC5: {=IFERROR(INDEX('Bank Schedule'!AC:AC, SMALL(IF('Bank Schedule'!$K$2:$K$825="Vacant", ROW('Bank Schedule'!$K$2:$K$825)), ROW(2:2))), "")} | AD5: {=IFERROR(INDEX('Bank Schedule'!AD:AD, SMALL(IF('Bank Schedule'!$K$2:$K$825="Vacant", ROW('Bank Schedule'!$K$2:$K$825)), ROW(2:2))), "")} | AE5: {=IFERROR(INDEX('Bank Schedule'!AE:AE, SMALL(IF('Bank Schedule'!$K$2:$K$825="Vacant", ROW('Bank Schedule'!$K$2:$K$825)), ROW(2:2))), "")} | AF5: {=IFERROR(INDEX('Bank Schedule'!AF:AF, SMALL(IF('Bank Schedule'!$K$2:$K$825="Vacant", ROW('Bank Schedule'!$K$2:$K$825)), ROW(2:2))), "")} | AG5: {=IFERROR(INDEX('Bank Schedule'!AG:AG, SMALL(IF('Bank Schedule'!$K$2:$K$825="Vacant", ROW('Bank Schedule'!$K$2:$K$825)), ROW(2:2))), "")} | AH5: {=IFERROR(INDEX('Bank Schedule'!AH:AH, SMALL(IF('Bank Schedule'!$K$2:$K$825="Vacant", ROW('Bank Schedule'!$K$2:$K$825)), ROW(2:2))), "")}
A6: {=IFERROR(INDEX('Bank Schedule'!A:A, SMALL(IF('Bank Schedule'!$K$2:$K$825="Vacant", ROW('Bank Schedule'!$K$2:$K$825)), ROW(3:3))), "")} | B6: {=IFERROR(INDEX('Bank Schedule'!B:B, SMALL(IF('Bank Schedule'!$K$2:$K$825="Vacant", ROW('Bank Schedule'!$K$2:$K$825)), ROW(3:3))), "")} | C6: {=IFERROR(INDEX('Bank Schedule'!C:C, SMALL(IF('Bank Schedule'!$K$2:$K$825="Vacant", ROW('Bank Schedule'!$K$2:$K$825)), ROW(3:3))), "")} | D6: {=IFERROR(INDEX('Bank Schedule'!D:D, SMALL(IF('Bank Schedule'!$K$2:$K$825="Vacant", ROW('Bank Schedule'!$K$2:$K$825)), ROW(3:3))), "")} | E6: {=IFERROR(INDEX('Bank Schedule'!E:E, SMALL(IF('Bank Schedule'!$K$2:$K$825="Vacant", ROW('Bank Schedule'!$K$2:$K$825)), ROW(3:3))), "")} | F6: {=IFERROR(INDEX('Bank Schedule'!F:F, SMALL(IF('Bank Schedule'!$K$2:$K$825="Vacant", ROW('Bank Schedule'!$K$2:$K$825)), ROW(3:3))), "")} | G6: {=IFERROR(INDEX('Bank Schedule'!G:G, SMALL(IF('Bank Schedule'!$K$2:$K$825="Vacant", ROW('Bank Schedule'!$K$2:$K$825)), ROW(3:3))), "")} | H6: {=IFERROR(INDEX('Bank Schedule'!H:H, SMALL(IF('Bank Schedule'!$K$2:$K$825="Vacant", ROW('Bank Schedule'!$K$2:$K$825)), ROW(3:3))), "")} | I6: {=IFERROR(INDEX('Bank Schedule'!I:I, SMALL(IF('Bank Schedule'!$K$2:$K$825="Vacant", ROW('Bank Schedule'!$K$2:$K$825)), ROW(3:3))), "")} | J6: {=IFERROR(INDEX('Bank Schedule'!J:J, SMALL(IF('Bank Schedule'!$K$2:$K$825="Vacant", ROW('Bank Schedule'!$K$2:$K$825)), ROW(3:3))), "")} | K6: {=IFERROR(INDEX('Bank Schedule'!K:K, SMALL(IF('Bank Schedule'!$K$2:$K$825="Vacant", ROW('Bank Schedule'!$K$2:$K$825)), ROW(3:3))), "")} | L6: {=IFERROR(INDEX('Bank Schedule'!L:L, SMALL(IF('Bank Schedule'!$K$2:$K$825="Vacant", ROW('Bank Schedule'!$K$2:$K$825)), ROW(3:3))), "")} | M6: {=IFERROR(INDEX('Bank Schedule'!M:M, SMALL(IF('Bank Schedule'!$K$2:$K$825="Vacant", ROW('Bank Schedule'!$K$2:$K$825)), ROW(3:3))), "")} | N6: {=IFERROR(INDEX('Bank Schedule'!N:N, SMALL(IF('Bank Schedule'!$K$2:$K$825="Vacant", ROW('Bank Schedule'!$K$2:$K$825)), ROW(3:3))), "")} | O6: {=IFERROR(INDEX('Bank Schedule'!O:O, SMALL(IF('Bank Schedule'!$K$2:$K$825="Vacant", ROW('Bank Schedule'!$K$2:$K$825)), ROW(3:3))), "")} | P6: {=IFERROR(INDEX('Bank Schedule'!P:P, SMALL(IF('Bank Schedule'!$K$2:$K$825="Vacant", ROW('Bank Schedule'!$K$2:$K$825)), ROW(3:3))), "")} | Q6: {=IFERROR(INDEX('Bank Schedule'!Q:Q, SMALL(IF('Bank Schedule'!$K$2:$K$825="Vacant", ROW('Bank Schedule'!$K$2:$K$825)), ROW(3:3))), "")} | R6: {=IFERROR(INDEX('Bank Schedule'!R:R, SMALL(IF('Bank Schedule'!$K$2:$K$825="Vacant", ROW('Bank Schedule'!$K$2:$K$825)), ROW(3:3))), "")} | S6: {=IFERROR(INDEX('Bank Schedule'!S:S, SMALL(IF('Bank Schedule'!$K$2:$K$825="Vacant", ROW('Bank Schedule'!$K$2:$K$825)), ROW(3:3))), "")} | T6: {=IFERROR(INDEX('Bank Schedule'!T:T, SMALL(IF('Bank Schedule'!$K$2:$K$825="Vacant", ROW('Bank Schedule'!$K$2:$K$825)), ROW(3:3))), "")} | U6: {=IFERROR(INDEX('Bank Schedule'!U:U, SMALL(IF('Bank Schedule'!$K$2:$K$825="Vacant", ROW('Bank Schedule'!$K$2:$K$825)), ROW(3:3))), "")} | V6: {=IFERROR(INDEX('Bank Schedule'!V:V, SMALL(IF('Bank Schedule'!$K$2:$K$825="Vacant", ROW('Bank Schedule'!$K$2:$K$825)), ROW(3:3))), "")} | W6: {=IFERROR(INDEX('Bank Schedule'!W:W, SMALL(IF('Bank Schedule'!$K$2:$K$825="Vacant", ROW('Bank Schedule'!$K$2:$K$825)), ROW(3:3))), "")} | X6: {=IFERROR(INDEX('Bank Schedule'!X:X, SMALL(IF('Bank Schedule'!$K$2:$K$825="Vacant", ROW('Bank Schedule'!$K$2:$K$825)), ROW(3:3))), "")} | Y6: {=IFERROR(INDEX('Bank Schedule'!Y:Y, SMALL(IF('Bank Schedule'!$K$2:$K$825="Vacant", ROW('Bank Schedule'!$K$2:$K$825)), ROW(3:3))), "")} | Z6: {=IFERROR(INDEX('Bank Schedule'!Z:Z, SMALL(IF('Bank Schedule'!$K$2:$K$825="Vacant", ROW('Bank Schedule'!$K$2:$K$825)), ROW(3:3))), "")} | AA6: {=IFERROR(INDEX('Bank Schedule'!AA:AA, SMALL(IF('Bank Schedule'!$K$2:$K$825="Vacant", ROW('Bank Schedule'!$K$2:$K$825)), ROW(3:3))), "")} | AB6: {=IFERROR(INDEX('Bank Schedule'!AB:AB, SMALL(IF('Bank Schedule'!$K$2:$K$825="Vacant", ROW('Bank Schedule'!$K$2:$K$825)), ROW(3:3))), "")} | AC6: {=IFERROR(INDEX('Bank Schedule'!AC:AC, SMALL(IF('Bank Schedule'!$K$2:$K$825="Vacant", ROW('Bank Schedule'!$K$2:$K$825)), ROW(3:3))), "")} | AD6: {=IFERROR(INDEX('Bank Schedule'!AD:AD, SMALL(IF('Bank Schedule'!$K$2:$K$825="Vacant", ROW('Bank Schedule'!$K$2:$K$825)), ROW(3:3))), "")} | AE6: {=IFERROR(INDEX('Bank Schedule'!AE:AE, SMALL(IF('Bank Schedule'!$K$2:$K$825="Vacant", ROW('Bank Schedule'!$K$2:$K$825)), ROW(3:3))), "")} | AF6: {=IFERROR(INDEX('Bank Schedule'!AF:AF, SMALL(IF('Bank Schedule'!$K$2:$K$825="Vacant", ROW('Bank Schedule'!$K$2:$K$825)), ROW(3:3))), "")} | AG6: {=IFERROR(INDEX('Bank Schedule'!AG:AG, SMALL(IF('Bank Schedule'!$K$2:$K$825="Vacant", ROW('Bank Schedule'!$K$2:$K$825)), ROW(3:3))), "")} | AH6: {=IFERROR(INDEX('Bank Schedule'!AH:AH, SMALL(IF('Bank Schedule'!$K$2:$K$825="Vacant", ROW('Bank Schedule'!$K$2:$K$825)), ROW(3:3))), "")}
A7: {=IFERROR(INDEX('Bank Schedule'!A:A, SMALL(IF('Bank Schedule'!$K$2:$K$825="Vacant", ROW('Bank Schedule'!$K$2:$K$825)), ROW(4:4))), "")} | B7: {=IFERROR(INDEX('Bank Schedule'!B:B, SMALL(IF('Bank Schedule'!$K$2:$K$825="Vacant", ROW('Bank Schedule'!$K$2:$K$825)), ROW(4:4))), "")} | C7: {=IFERROR(INDEX('Bank Schedule'!C:C, SMALL(IF('Bank Schedule'!$K$2:$K$825="Vacant", ROW('Bank Schedule'!$K$2:$K$825)), ROW(4:4))), "")} | D7: {=IFERROR(INDEX('Bank Schedule'!D:D, SMALL(IF('Bank Schedule'!$K$2:$K$825="Vacant", ROW('Bank Schedule'!$K$2:$K$825)), ROW(4:4))), "")} | E7: {=IFERROR(INDEX('Bank Schedule'!E:E, SMALL(IF('Bank Schedule'!$K$2:$K$825="Vacant", ROW('Bank Schedule'!$K$2:$K$825)), ROW(4:4))), "")} | F7: {=IFERROR(INDEX('Bank Schedule'!F:F, SMALL(IF('Bank Schedule'!$K$2:$K$825="Vacant", ROW('Bank Schedule'!$K$2:$K$825)), ROW(4:4))), "")} | G7: {=IFERROR(INDEX('Bank Schedule'!G:G, SMALL(IF('Bank Schedule'!$K$2:$K$825="Vacant", ROW('Bank Schedule'!$K$2:$K$825)), ROW(4:4))), "")} | H7: {=IFERROR(INDEX('Bank Schedule'!H:H, SMALL(IF('Bank Schedule'!$K$2:$K$825="Vacant", ROW('Bank Schedule'!$K$2:$K$825)), ROW(4:4))), "")} | I7: {=IFERROR(INDEX('Bank Schedule'!I:I, SMALL(IF('Bank Schedule'!$K$2:$K$825="Vacant", ROW('Bank Schedule'!$K$2:$K$825)), ROW(4:4))), "")} | J7: {=IFERROR(INDEX('Bank Schedule'!J:J, SMALL(IF('Bank Schedule'!$K$2:$K$825="Vacant", ROW('Bank Schedule'!$K$2:$K$825)), ROW(4:4))), "")} | K7: {=IFERROR(INDEX('Bank Schedule'!K:K, SMALL(IF('Bank Schedule'!$K$2:$K$825="Vacant", ROW('Bank Schedule'!$K$2:$K$825)), ROW(4:4))), "")} | L7: {=IFERROR(INDEX('Bank Schedule'!L:L, SMALL(IF('Bank Schedule'!$K$2:$K$825="Vacant", ROW('Bank Schedule'!$K$2:$K$825)), ROW(4:4))), "")} | M7: {=IFERROR(INDEX('Bank Schedule'!M:M, SMALL(IF('Bank Schedule'!$K$2:$K$825="Vacant", ROW('Bank Schedule'!$K$2:$K$825)), ROW(4:4))), "")} | N7: {=IFERROR(INDEX('Bank Schedule'!N:N, SMALL(IF('Bank Schedule'!$K$2:$K$825="Vacant", ROW('Bank Schedule'!$K$2:$K$825)), ROW(4:4))), "")} | O7: {=IFERROR(INDEX('Bank Schedule'!O:O, SMALL(IF('Bank Schedule'!$K$2:$K$825="Vacant", ROW('Bank Schedule'!$K$2:$K$825)), ROW(4:4))), "")} | P7: {=IFERROR(INDEX('Bank Schedule'!P:P, SMALL(IF('Bank Schedule'!$K$2:$K$825="Vacant", ROW('Bank Schedule'!$K$2:$K$825)), ROW(4:4))), "")} | Q7: {=IFERROR(INDEX('Bank Schedule'!Q:Q, SMALL(IF('Bank Schedule'!$K$2:$K$825="Vacant", ROW('Bank Schedule'!$K$2:$K$825)), ROW(4:4))), "")} | R7: {=IFERROR(INDEX('Bank Schedule'!R:R, SMALL(IF('Bank Schedule'!$K$2:$K$825="Vacant", ROW('Bank Schedule'!$K$2:$K$825)), ROW(4:4))), "")} | S7: {=IFERROR(INDEX('Bank Schedule'!S:S, SMALL(IF('Bank Schedule'!$K$2:$K$825="Vacant", ROW('Bank Schedule'!$K$2:$K$825)), ROW(4:4))), "")} | T7: {=IFERROR(INDEX('Bank Schedule'!T:T, SMALL(IF('Bank Schedule'!$K$2:$K$825="Vacant", ROW('Bank Schedule'!$K$2:$K$825)), ROW(4:4))), "")} | U7: {=IFERROR(INDEX('Bank Schedule'!U:U, SMALL(IF('Bank Schedule'!$K$2:$K$825="Vacant", ROW('Bank Schedule'!$K$2:$K$825)), ROW(4:4))), "")} | V7: {=IFERROR(INDEX('Bank Schedule'!V:V, SMALL(IF('Bank Schedule'!$K$2:$K$825="Vacant", ROW('Bank Schedule'!$K$2:$K$825)), ROW(4:4))), "")} | W7: {=IFERROR(INDEX('Bank Schedule'!W:W, SMALL(IF('Bank Schedule'!$K$2:$K$825="Vacant", ROW('Bank Schedule'!$K$2:$K$825)), ROW(4:4))), "")} | X7: {=IFERROR(INDEX('Bank Schedule'!X:X, SMALL(IF('Bank Schedule'!$K$2:$K$825="Vacant", ROW('Bank Schedule'!$K$2:$K$825)), ROW(4:4))), "")} | Y7: {=IFERROR(INDEX('Bank Schedule'!Y:Y, SMALL(IF('Bank Schedule'!$K$2:$K$825="Vacant", ROW('Bank Schedule'!$K$2:$K$825)), ROW(4:4))), "")} | Z7: {=IFERROR(INDEX('Bank Schedule'!Z:Z, SMALL(IF('Bank Schedule'!$K$2:$K$825="Vacant", ROW('Bank Schedule'!$K$2:$K$825)), ROW(4:4))), "")} | AA7: {=IFERROR(INDEX('Bank Schedule'!AA:AA, SMALL(IF('Bank Schedule'!$K$2:$K$825="Vacant", ROW('Bank Schedule'!$K$2:$K$825)), ROW(4:4))), "")} | AB7: {=IFERROR(INDEX('Bank Schedule'!AB:AB, SMALL(IF('Bank Schedule'!$K$2:$K$825="Vacant", ROW('Bank Schedule'!$K$2:$K$825)), ROW(4:4))), "")} | AC7: {=IFERROR(INDEX('Bank Schedule'!AC:AC, SMALL(IF('Bank Schedule'!$K$2:$K$825="Vacant", ROW('Bank Schedule'!$K$2:$K$825)), ROW(4:4))), "")} | AD7: {=IFERROR(INDEX('Bank Schedule'!AD:AD, SMALL(IF('Bank Schedule'!$K$2:$K$825="Vacant", ROW('Bank Schedule'!$K$2:$K$825)), ROW(4:4))), "")} | AE7: {=IFERROR(INDEX('Bank Schedule'!AE:AE, SMALL(IF('Bank Schedule'!$K$2:$K$825="Vacant", ROW('Bank Schedule'!$K$2:$K$825)), ROW(4:4))), "")} | AF7: {=IFERROR(INDEX('Bank Schedule'!AF:AF, SMALL(IF('Bank Schedule'!$K$2:$K$825="Vacant", ROW('Bank Schedule'!$K$2:$K$825)), ROW(4:4))), "")} | AG7: {=IFERROR(INDEX('Bank Schedule'!AG:AG, SMALL(IF('Bank Schedule'!$K$2:$K$825="Vacant", ROW('Bank Schedule'!$K$2:$K$825)), ROW(4:4))), "")} | AH7: {=IFERROR(INDEX('Bank Schedule'!AH:AH, SMALL(IF('Bank Schedule'!$K$2:$K$825="Vacant", ROW('Bank Schedule'!$K$2:$K$825)), ROW(4:4))), "")}
A8: {=IFERROR(INDEX('Bank Schedule'!A:A, SMALL(IF('Bank Schedule'!$K$2:$K$825="Vacant", ROW('Bank Schedule'!$K$2:$K$825)), ROW(5:5))), "")} | B8: {=IFERROR(INDEX('Bank Schedule'!B:B, SMALL(IF('Bank Schedule'!$K$2:$K$825="Vacant", ROW('Bank Schedule'!$K$2:$K$825)), ROW(5:5))), "")} | C8: {=IFERROR(INDEX('Bank Schedule'!C:C, SMALL(IF('Bank Schedule'!$K$2:$K$825="Vacant", ROW('Bank Schedule'!$K$2:$K$825)), ROW(5:5))), "")} | D8: {=IFERROR(INDEX('Bank Schedule'!D:D, SMALL(IF('Bank Schedule'!$K$2:$K$825="Vacant", ROW('Bank Schedule'!$K$2:$K$825)), ROW(5:5))), "")} | E8: {=IFERROR(INDEX('Bank Schedule'!E:E, SMALL(IF('Bank Schedule'!$K$2:$K$825="Vacant", ROW('Bank Schedule'!$K$2:$K$825)), ROW(5:5))), "")} | F8: {=IFERROR(INDEX('Bank Schedule'!F:F, SMALL(IF('Bank Schedule'!$K$2:$K$825="Vacant", ROW('Bank Schedule'!$K$2:$K$825)), ROW(5:5))), "")} | G8: {=IFERROR(INDEX('Bank Schedule'!G:G, SMALL(IF('Bank Schedule'!$K$2:$K$825="Vacant", ROW('Bank Schedule'!$K$2:$K$825)), ROW(5:5))), "")} | H8: {=IFERROR(INDEX('Bank Schedule'!H:H, SMALL(IF('Bank Schedule'!$K$2:$K$825="Vacant", ROW('Bank Schedule'!$K$2:$K$825)), ROW(5:5))), "")} | I8: {=IFERROR(INDEX('Bank Schedule'!I:I, SMALL(IF('Bank Schedule'!$K$2:$K$825="Vacant", ROW('Bank Schedule'!$K$2:$K$825)), ROW(5:5))), "")} | J8: {=IFERROR(INDEX('Bank Schedule'!J:J, SMALL(IF('Bank Schedule'!$K$2:$K$825="Vacant", ROW('Bank Schedule'!$K$2:$K$825)), ROW(5:5))), "")} | K8: {=IFERROR(INDEX('Bank Schedule'!K:K, SMALL(IF('Bank Schedule'!$K$2:$K$825="Vacant", ROW('Bank Schedule'!$K$2:$K$825)), ROW(5:5))), "")} | L8: {=IFERROR(INDEX('Bank Schedule'!L:L, SMALL(IF('Bank Schedule'!$K$2:$K$825="Vacant", ROW('Bank Schedule'!$K$2:$K$825)), ROW(5:5))), "")} | M8: {=IFERROR(INDEX('Bank Schedule'!M:M, SMALL(IF('Bank Schedule'!$K$2:$K$825="Vacant", ROW('Bank Schedule'!$K$2:$K$825)), ROW(5:5))), "")} | N8: {=IFERROR(INDEX('Bank Schedule'!N:N, SMALL(IF('Bank Schedule'!$K$2:$K$825="Vacant", ROW('Bank Schedule'!$K$2:$K$825)), ROW(5:5))), "")} | O8: {=IFERROR(INDEX('Bank Schedule'!O:O, SMALL(IF('Bank Schedule'!$K$2:$K$825="Vacant", ROW('Bank Schedule'!$K$2:$K$825)), ROW(5:5))), "")} | P8: {=IFERROR(INDEX('Bank Schedule'!P:P, SMALL(IF('Bank Schedule'!$K$2:$K$825="Vacant", ROW('Bank Schedule'!$K$2:$K$825)), ROW(5:5))), "")} | Q8: {=IFERROR(INDEX('Bank Schedule'!Q:Q, SMALL(IF('Bank Schedule'!$K$2:$K$825="Vacant", ROW('Bank Schedule'!$K$2:$K$825)), ROW(5:5))), "")} | R8: {=IFERROR(INDEX('Bank Schedule'!R:R, SMALL(IF('Bank Schedule'!$K$2:$K$825="Vacant", ROW('Bank Schedule'!$K$2:$K$825)), ROW(5:5))), "")} | S8: {=IFERROR(INDEX('Bank Schedule'!S:S, SMALL(IF('Bank Schedule'!$K$2:$K$825="Vacant", ROW('Bank Schedule'!$K$2:$K$825)), ROW(5:5))), "")} | T8: {=IFERROR(INDEX('Bank Schedule'!T:T, SMALL(IF('Bank Schedule'!$K$2:$K$825="Vacant", ROW('Bank Schedule'!$K$2:$K$825)), ROW(5:5))), "")} | U8: {=IFERROR(INDEX('Bank Schedule'!U:U, SMALL(IF('Bank Schedule'!$K$2:$K$825="Vacant", ROW('Bank Schedule'!$K$2:$K$825)), ROW(5:5))), "")} | V8: {=IFERROR(INDEX('Bank Schedule'!V:V, SMALL(IF('Bank Schedule'!$K$2:$K$825="Vacant", ROW('Bank Schedule'!$K$2:$K$825)), ROW(5:5))), "")} | W8: {=IFERROR(INDEX('Bank Schedule'!W:W, SMALL(IF('Bank Schedule'!$K$2:$K$825="Vacant", ROW('Bank Schedule'!$K$2:$K$825)), ROW(5:5))), "")} | X8: {=IFERROR(INDEX('Bank Schedule'!X:X, SMALL(IF('Bank Schedule'!$K$2:$K$825="Vacant", ROW('Bank Schedule'!$K$2:$K$825)), ROW(5:5))), "")} | Y8: {=IFERROR(INDEX('Bank Schedule'!Y:Y, SMALL(IF('Bank Schedule'!$K$2:$K$825="Vacant", ROW('Bank Schedule'!$K$2:$K$825)), ROW(5:5))), "")} | Z8: {=IFERROR(INDEX('Bank Schedule'!Z:Z, SMALL(IF('Bank Schedule'!$K$2:$K$825="Vacant", ROW('Bank Schedule'!$K$2:$K$825)), ROW(5:5))), "")} | AA8: {=IFERROR(INDEX('Bank Schedule'!AA:AA, SMALL(IF('Bank Schedule'!$K$2:$K$825="Vacant", ROW('Bank Schedule'!$K$2:$K$825)), ROW(5:5))), "")} | AB8: {=IFERROR(INDEX('Bank Schedule'!AB:AB, SMALL(IF('Bank Schedule'!$K$2:$K$825="Vacant", ROW('Bank Schedule'!$K$2:$K$825)), ROW(5:5))), "")} | AC8: {=IFERROR(INDEX('Bank Schedule'!AC:AC, SMALL(IF('Bank Schedule'!$K$2:$K$825="Vacant", ROW('Bank Schedule'!$K$2:$K$825)), ROW(5:5))), "")} | AD8: {=IFERROR(INDEX('Bank Schedule'!AD:AD, SMALL(IF('Bank Schedule'!$K$2:$K$825="Vacant", ROW('Bank Schedule'!$K$2:$K$825)), ROW(5:5))), "")} | AE8: {=IFERROR(INDEX('Bank Schedule'!AE:AE, SMALL(IF('Bank Schedule'!$K$2:$K$825="Vacant", ROW('Bank Schedule'!$K$2:$K$825)), ROW(5:5))), "")} | AF8: {=IFERROR(INDEX('Bank Schedule'!AF:AF, SMALL(IF('Bank Schedule'!$K$2:$K$825="Vacant", ROW('Bank Schedule'!$K$2:$K$825)), ROW(5:5))), "")} | AG8: {=IFERROR(INDEX('Bank Schedule'!AG:AG, SMALL(IF('Bank Schedule'!$K$2:$K$825="Vacant", ROW('Bank Schedule'!$K$2:$K$825)), ROW(5:5))), "")} | AH8: {=IFERROR(INDEX('Bank Schedule'!AH:AH, SMALL(IF('Bank Schedule'!$K$2:$K$825="Vacant", ROW('Bank Schedule'!$K$2:$K$825)), ROW(5:5))), "")}
A9: {=IFERROR(INDEX('Bank Schedule'!A:A, SMALL(IF('Bank Schedule'!$K$2:$K$825="Vacant", ROW('Bank Schedule'!$K$2:$K$825)), ROW(6:6))), "")} | B9: {=IFERROR(INDEX('Bank Schedule'!B:B, SMALL(IF('Bank Schedule'!$K$2:$K$825="Vacant", ROW('Bank Schedule'!$K$2:$K$825)), ROW(6:6))), "")} | C9: {=IFERROR(INDEX('Bank Schedule'!C:C, SMALL(IF('Bank Schedule'!$K$2:$K$825="Vacant", ROW('Bank Schedule'!$K$2:$K$825)), ROW(6:6))), "")} | D9: {=IFERROR(INDEX('Bank Schedule'!D:D, SMALL(IF('Bank Schedule'!$K$2:$K$825="Vacant", ROW('Bank Schedule'!$K$2:$K$825)), ROW(6:6))), "")} | E9: {=IFERROR(INDEX('Bank Schedule'!E:E, SMALL(IF('Bank Schedule'!$K$2:$K$825="Vacant", ROW('Bank Schedule'!$K$2:$K$825)), ROW(6:6))), "")} | F9: {=IFERROR(INDEX('Bank Schedule'!F:F, SMALL(IF('Bank Schedule'!$K$2:$K$825="Vacant", ROW('Bank Schedule'!$K$2:$K$825)), ROW(6:6))), "")} | G9: {=IFERROR(INDEX('Bank Schedule'!G:G, SMALL(IF('Bank Schedule'!$K$2:$K$825="Vacant", ROW('Bank Schedule'!$K$2:$K$825)), ROW(6:6))), "")} | H9: {=IFERROR(INDEX('Bank Schedule'!H:H, SMALL(IF('Bank Schedule'!$K$2:$K$825="Vacant", ROW('Bank Schedule'!$K$2:$K$825)), ROW(6:6))), "")} | I9: {=IFERROR(INDEX('Bank Schedule'!I:I, SMALL(IF('Bank Schedule'!$K$2:$K$825="Vacant", ROW('Bank Schedule'!$K$2:$K$825)), ROW(6:6))), "")} | J9: {=IFERROR(INDEX('Bank Schedule'!J:J, SMALL(IF('Bank Schedule'!$K$2:$K$825="Vacant", ROW('Bank Schedule'!$K$2:$K$825)), ROW(6:6))), "")} | K9: {=IFERROR(INDEX('Bank Schedule'!K:K, SMALL(IF('Bank Schedule'!$K$2:$K$825="Vacant", ROW('Bank Schedule'!$K$2:$K$825)), ROW(6:6))), "")} | L9: {=IFERROR(INDEX('Bank Schedule'!L:L, SMALL(IF('Bank Schedule'!$K$2:$K$825="Vacant", ROW('Bank Schedule'!$K$2:$K$825)), ROW(6:6))), "")} | M9: {=IFERROR(INDEX('Bank Schedule'!M:M, SMALL(IF('Bank Schedule'!$K$2:$K$825="Vacant", ROW('Bank Schedule'!$K$2:$K$825)), ROW(6:6))), "")} | N9: {=IFERROR(INDEX('Bank Schedule'!N:N, SMALL(IF('Bank Schedule'!$K$2:$K$825="Vacant", ROW('Bank Schedule'!$K$2:$K$825)), ROW(6:6))), "")} | O9: {=IFERROR(INDEX('Bank Schedule'!O:O, SMALL(IF('Bank Schedule'!$K$2:$K$825="Vacant", ROW('Bank Schedule'!$K$2:$K$825)), ROW(6:6))), "")} | P9: {=IFERROR(INDEX('Bank Schedule'!P:P, SMALL(IF('Bank Schedule'!$K$2:$K$825="Vacant", ROW('Bank Schedule'!$K$2:$K$825)), ROW(6:6))), "")} | Q9: {=IFERROR(INDEX('Bank Schedule'!Q:Q, SMALL(IF('Bank Schedule'!$K$2:$K$825="Vacant", ROW('Bank Schedule'!$K$2:$K$825)), ROW(6:6))), "")} | R9: {=IFERROR(INDEX('Bank Schedule'!R:R, SMALL(IF('Bank Schedule'!$K$2:$K$825="Vacant", ROW('Bank Schedule'!$K$2:$K$825)), ROW(6:6))), "")} | S9: {=IFERROR(INDEX('Bank Schedule'!S:S, SMALL(IF('Bank Schedule'!$K$2:$K$825="Vacant", ROW('Bank Schedule'!$K$2:$K$825)), ROW(6:6))), "")} | T9: {=IFERROR(INDEX('Bank Schedule'!T:T, SMALL(IF('Bank Schedule'!$K$2:$K$825="Vacant", ROW('Bank Schedule'!$K$2:$K$825)), ROW(6:6))), "")} | U9: {=IFERROR(INDEX('Bank Schedule'!U:U, SMALL(IF('Bank Schedule'!$K$2:$K$825="Vacant", ROW('Bank Schedule'!$K$2:$K$825)), ROW(6:6))), "")} | V9: {=IFERROR(INDEX('Bank Schedule'!V:V, SMALL(IF('Bank Schedule'!$K$2:$K$825="Vacant", ROW('Bank Schedule'!$K$2:$K$825)), ROW(6:6))), "")} | W9: {=IFERROR(INDEX('Bank Schedule'!W:W, SMALL(IF('Bank Schedule'!$K$2:$K$825="Vacant", ROW('Bank Schedule'!$K$2:$K$825)), ROW(6:6))), "")} | X9: {=IFERROR(INDEX('Bank Schedule'!X:X, SMALL(IF('Bank Schedule'!$K$2:$K$825="Vacant", ROW('Bank Schedule'!$K$2:$K$825)), ROW(6:6))), "")} | Y9: {=IFERROR(INDEX('Bank Schedule'!Y:Y, SMALL(IF('Bank Schedule'!$K$2:$K$825="Vacant", ROW('Bank Schedule'!$K$2:$K$825)), ROW(6:6))), "")} | Z9: {=IFERROR(INDEX('Bank Schedule'!Z:Z, SMALL(IF('Bank Schedule'!$K$2:$K$825="Vacant", ROW('Bank Schedule'!$K$2:$K$825)), ROW(6:6))), "")} | AA9: {=IFERROR(INDEX('Bank Schedule'!AA:AA, SMALL(IF('Bank Schedule'!$K$2:$K$825="Vacant", ROW('Bank Schedule'!$K$2:$K$825)), ROW(6:6))), "")} | AB9: {=IFERROR(INDEX('Bank Schedule'!AB:AB, SMALL(IF('Bank Schedule'!$K$2:$K$825="Vacant", ROW('Bank Schedule'!$K$2:$K$825)), ROW(6:6))), "")} | AC9: {=IFERROR(INDEX('Bank Schedule'!AC:AC, SMALL(IF('Bank Schedule'!$K$2:$K$825="Vacant", ROW('Bank Schedule'!$K$2:$K$825)), ROW(6:6))), "")} | AD9: {=IFERROR(INDEX('Bank Schedule'!AD:AD, SMALL(IF('Bank Schedule'!$K$2:$K$825="Vacant", ROW('Bank Schedule'!$K$2:$K$825)), ROW(6:6))), "")} | AE9: {=IFERROR(INDEX('Bank Schedule'!AE:AE, SMALL(IF('Bank Schedule'!$K$2:$K$825="Vacant", ROW('Bank Schedule'!$K$2:$K$825)), ROW(6:6))), "")} | AF9: {=IFERROR(INDEX('Bank Schedule'!AF:AF, SMALL(IF('Bank Schedule'!$K$2:$K$825="Vacant", ROW('Bank Schedule'!$K$2:$K$825)), ROW(6:6))), "")} | AG9: {=IFERROR(INDEX('Bank Schedule'!AG:AG, SMALL(IF('Bank Schedule'!$K$2:$K$825="Vacant", ROW('Bank Schedule'!$K$2:$K$825)), ROW(6:6))), "")} | AH9: {=IFERROR(INDEX('Bank Schedule'!AH:AH, SMALL(IF('Bank Schedule'!$K$2:$K$825="Vacant", ROW('Bank Schedule'!$K$2:$K$825)), ROW(6:6))), "")}
A10: {=IFERROR(INDEX('Bank Schedule'!A:A, SMALL(IF('Bank Schedule'!$K$2:$K$825="Vacant", ROW('Bank Schedule'!$K$2:$K$825)), ROW(7:7))), "")} | B10: {=IFERROR(INDEX('Bank Schedule'!B:B, SMALL(IF('Bank Schedule'!$K$2:$K$825="Vacant", ROW('Bank Schedule'!$K$2:$K$825)), ROW(7:7))), "")} | C10: {=IFERROR(INDEX('Bank Schedule'!C:C, SMALL(IF('Bank Schedule'!$K$2:$K$825="Vacant", ROW('Bank Schedule'!$K$2:$K$825)), ROW(7:7))), "")} | D10: {=IFERROR(INDEX('Bank Schedule'!D:D, SMALL(IF('Bank Schedule'!$K$2:$K$825="Vacant", ROW('Bank Schedule'!$K$2:$K$825)), ROW(7:7))), "")} | E10: {=IFERROR(INDEX('Bank Schedule'!E:E, SMALL(IF('Bank Schedule'!$K$2:$K$825="Vacant", ROW('Bank Schedule'!$K$2:$K$825)), ROW(7:7))), "")} | F10: {=IFERROR(INDEX('Bank Schedule'!F:F, SMALL(IF('Bank Schedule'!$K$2:$K$825="Vacant", ROW('Bank Schedule'!$K$2:$K$825)), ROW(7:7))), "")} | G10: {=IFERROR(INDEX('Bank Schedule'!G:G, SMALL(IF('Bank Schedule'!$K$2:$K$825="Vacant", ROW('Bank Schedule'!$K$2:$K$825)), ROW(7:7))), "")} | H10: {=IFERROR(INDEX('Bank Schedule'!H:H, SMALL(IF('Bank Schedule'!$K$2:$K$825="Vacant", ROW('Bank Schedule'!$K$2:$K$825)), ROW(7:7))), "")} | I10: {=IFERROR(INDEX('Bank Schedule'!I:I, SMALL(IF('Bank Schedule'!$K$2:$K$825="Vacant", ROW('Bank Schedule'!$K$2:$K$825)), ROW(7:7))), "")} | J10: {=IFERROR(INDEX('Bank Schedule'!J:J, SMALL(IF('Bank Schedule'!$K$2:$K$825="Vacant", ROW('Bank Schedule'!$K$2:$K$825)), ROW(7:7))), "")} | K10: {=IFERROR(INDEX('Bank Schedule'!K:K, SMALL(IF('Bank Schedule'!$K$2:$K$825="Vacant", ROW('Bank Schedule'!$K$2:$K$825)), ROW(7:7))), "")} | L10: {=IFERROR(INDEX('Bank Schedule'!L:L, SMALL(IF('Bank Schedule'!$K$2:$K$825="Vacant", ROW('Bank Schedule'!$K$2:$K$825)), ROW(7:7))), "")} | M10: {=IFERROR(INDEX('Bank Schedule'!M:M, SMALL(IF('Bank Schedule'!$K$2:$K$825="Vacant", ROW('Bank Schedule'!$K$2:$K$825)), ROW(7:7))), "")} | N10: {=IFERROR(INDEX('Bank Schedule'!N:N, SMALL(IF('Bank Schedule'!$K$2:$K$825="Vacant", ROW('Bank Schedule'!$K$2:$K$825)), ROW(7:7))), "")} | O10: {=IFERROR(INDEX('Bank Schedule'!O:O, SMALL(IF('Bank Schedule'!$K$2:$K$825="Vacant", ROW('Bank Schedule'!$K$2:$K$825)), ROW(7:7))), "")} | P10: {=IFERROR(INDEX('Bank Schedule'!P:P, SMALL(IF('Bank Schedule'!$K$2:$K$825="Vacant", ROW('Bank Schedule'!$K$2:$K$825)), ROW(7:7))), "")} | Q10: {=IFERROR(INDEX('Bank Schedule'!Q:Q, SMALL(IF('Bank Schedule'!$K$2:$K$825="Vacant", ROW('Bank Schedule'!$K$2:$K$825)), ROW(7:7))), "")} | R10: {=IFERROR(INDEX('Bank Schedule'!R:R, SMALL(IF('Bank Schedule'!$K$2:$K$825="Vacant", ROW('Bank Schedule'!$K$2:$K$825)), ROW(7:7))), "")} | S10: {=IFERROR(INDEX('Bank Schedule'!S:S, SMALL(IF('Bank Schedule'!$K$2:$K$825="Vacant", ROW('Bank Schedule'!$K$2:$K$825)), ROW(7:7))), "")} | T10: {=IFERROR(INDEX('Bank Schedule'!T:T, SMALL(IF('Bank Schedule'!$K$2:$K$825="Vacant", ROW('Bank Schedule'!$K$2:$K$825)), ROW(7:7))), "")} | U10: {=IFERROR(INDEX('Bank Schedule'!U:U, SMALL(IF('Bank Schedule'!$K$2:$K$825="Vacant", ROW('Bank Schedule'!$K$2:$K$825)), ROW(7:7))), "")} | V10: {=IFERROR(INDEX('Bank Schedule'!V:V, SMALL(IF('Bank Schedule'!$K$2:$K$825="Vacant", ROW('Bank Schedule'!$K$2:$K$825)), ROW(7:7))), "")} | W10: {=IFERROR(INDEX('Bank Schedule'!W:W, SMALL(IF('Bank Schedule'!$K$2:$K$825="Vacant", ROW('Bank Schedule'!$K$2:$K$825)), ROW(7:7))), "")} | X10: {=IFERROR(INDEX('Bank Schedule'!X:X, SMALL(IF('Bank Schedule'!$K$2:$K$825="Vacant", ROW('Bank Schedule'!$K$2:$K$825)), ROW(7:7))), "")} | Y10: {=IFERROR(INDEX('Bank Schedule'!Y:Y, SMALL(IF('Bank Schedule'!$K$2:$K$825="Vacant", ROW('Bank Schedule'!$K$2:$K$825)), ROW(7:7))), "")} | Z10: {=IFERROR(INDEX('Bank Schedule'!Z:Z, SMALL(IF('Bank Schedule'!$K$2:$K$825="Vacant", ROW('Bank Schedule'!$K$2:$K$825)), ROW(7:7))), "")} | AA10: {=IFERROR(INDEX('Bank Schedule'!AA:AA, SMALL(IF('Bank Schedule'!$K$2:$K$825="Vacant", ROW('Bank Schedule'!$K$2:$K$825)), ROW(7:7))), "")} | AB10: {=IFERROR(INDEX('Bank Schedule'!AB:AB, SMALL(IF('Bank Schedule'!$K$2:$K$825="Vacant", ROW('Bank Schedule'!$K$2:$K$825)), ROW(7:7))), "")} | AC10: {=IFERROR(INDEX('Bank Schedule'!AC:AC, SMALL(IF('Bank Schedule'!$K$2:$K$825="Vacant", ROW('Bank Schedule'!$K$2:$K$825)), ROW(7:7))), "")} | AD10: {=IFERROR(INDEX('Bank Schedule'!AD:AD, SMALL(IF('Bank Schedule'!$K$2:$K$825="Vacant", ROW('Bank Schedule'!$K$2:$K$825)), ROW(7:7))), "")} | AE10: {=IFERROR(INDEX('Bank Schedule'!AE:AE, SMALL(IF('Bank Schedule'!$K$2:$K$825="Vacant", ROW('Bank Schedule'!$K$2:$K$825)), ROW(7:7))), "")} | AF10: {=IFERROR(INDEX('Bank Schedule'!AF:AF, SMALL(IF('Bank Schedule'!$K$2:$K$825="Vacant", ROW('Bank Schedule'!$K$2:$K$825)), ROW(7:7))), "")} | AG10: {=IFERROR(INDEX('Bank Schedule'!AG:AG, SMALL(IF('Bank Schedule'!$K$2:$K$825="Vacant", ROW('Bank Schedule'!$K$2:$K$825)), ROW(7:7))), "")} | AH10: {=IFERROR(INDEX('Bank Schedule'!AH:AH, SMALL(IF('Bank Schedule'!$K$2:$K$825="Vacant", ROW('Bank Schedule'!$K$2:$K$825)), ROW(7:7))), "")}
A11: {=IFERROR(INDEX('Bank Schedule'!A:A, SMALL(IF('Bank Schedule'!$K$2:$K$825="Vacant", ROW('Bank Schedule'!$K$2:$K$825)), ROW(8:8))), "")} | B11: {=IFERROR(INDEX('Bank Schedule'!B:B, SMALL(IF('Bank Schedule'!$K$2:$K$825="Vacant", ROW('Bank Schedule'!$K$2:$K$825)), ROW(8:8))), "")} | C11: {=IFERROR(INDEX('Bank Schedule'!C:C, SMALL(IF('Bank Schedule'!$K$2:$K$825="Vacant", ROW('Bank Schedule'!$K$2:$K$825)), ROW(8:8))), "")} | D11: {=IFERROR(INDEX('Bank Schedule'!D:D, SMALL(IF('Bank Schedule'!$K$2:$K$825="Vacant", ROW('Bank Schedule'!$K$2:$K$825)), ROW(8:8))), "")} | E11: {=IFERROR(INDEX('Bank Schedule'!E:E, SMALL(IF('Bank Schedule'!$K$2:$K$825="Vacant", ROW('Bank Schedule'!$K$2:$K$825)), ROW(8:8))), "")} | F11: {=IFERROR(INDEX('Bank Schedule'!F:F, SMALL(IF('Bank Schedule'!$K$2:$K$825="Vacant", ROW('Bank Schedule'!$K$2:$K$825)), ROW(8:8))), "")} | G11: {=IFERROR(INDEX('Bank Schedule'!G:G, SMALL(IF('Bank Schedule'!$K$2:$K$825="Vacant", ROW('Bank Schedule'!$K$2:$K$825)), ROW(8:8))), "")} | H11: {=IFERROR(INDEX('Bank Schedule'!H:H, SMALL(IF('Bank Schedule'!$K$2:$K$825="Vacant", ROW('Bank Schedule'!$K$2:$K$825)), ROW(8:8))), "")} | I11: {=IFERROR(INDEX('Bank Schedule'!I:I, SMALL(IF('Bank Schedule'!$K$2:$K$825="Vacant", ROW('Bank Schedule'!$K$2:$K$825)), ROW(8:8))), "")} | J11: {=IFERROR(INDEX('Bank Schedule'!J:J, SMALL(IF('Bank Schedule'!$K$2:$K$825="Vacant", ROW('Bank Schedule'!$K$2:$K$825)), ROW(8:8))), "")} | K11: {=IFERROR(INDEX('Bank Schedule'!K:K, SMALL(IF('Bank Schedule'!$K$2:$K$825="Vacant", ROW('Bank Schedule'!$K$2:$K$825)), ROW(8:8))), "")} | L11: {=IFERROR(INDEX('Bank Schedule'!L:L, SMALL(IF('Bank Schedule'!$K$2:$K$825="Vacant", ROW('Bank Schedule'!$K$2:$K$825)), ROW(8:8))), "")} | M11: {=IFERROR(INDEX('Bank Schedule'!M:M, SMALL(IF('Bank Schedule'!$K$2:$K$825="Vacant", ROW('Bank Schedule'!$K$2:$K$825)), ROW(8:8))), "")} | N11: {=IFERROR(INDEX('Bank Schedule'!N:N, SMALL(IF('Bank Schedule'!$K$2:$K$825="Vacant", ROW('Bank Schedule'!$K$2:$K$825)), ROW(8:8))), "")} | O11: {=IFERROR(INDEX('Bank Schedule'!O:O, SMALL(IF('Bank Schedule'!$K$2:$K$825="Vacant", ROW('Bank Schedule'!$K$2:$K$825)), ROW(8:8))), "")} | P11: {=IFERROR(INDEX('Bank Schedule'!P:P, SMALL(IF('Bank Schedule'!$K$2:$K$825="Vacant", ROW('Bank Schedule'!$K$2:$K$825)), ROW(8:8))), "")} | Q11: {=IFERROR(INDEX('Bank Schedule'!Q:Q, SMALL(IF('Bank Schedule'!$K$2:$K$825="Vacant", ROW('Bank Schedule'!$K$2:$K$825)), ROW(8:8))), "")} | R11: {=IFERROR(INDEX('Bank Schedule'!R:R, SMALL(IF('Bank Schedule'!$K$2:$K$825="Vacant", ROW('Bank Schedule'!$K$2:$K$825)), ROW(8:8))), "")} | S11: {=IFERROR(INDEX('Bank Schedule'!S:S, SMALL(IF('Bank Schedule'!$K$2:$K$825="Vacant", ROW('Bank Schedule'!$K$2:$K$825)), ROW(8:8))), "")} | T11: {=IFERROR(INDEX('Bank Schedule'!T:T, SMALL(IF('Bank Schedule'!$K$2:$K$825="Vacant", ROW('Bank Schedule'!$K$2:$K$825)), ROW(8:8))), "")} | U11: {=IFERROR(INDEX('Bank Schedule'!U:U, SMALL(IF('Bank Schedule'!$K$2:$K$825="Vacant", ROW('Bank Schedule'!$K$2:$K$825)), ROW(8:8))), "")} | V11: {=IFERROR(INDEX('Bank Schedule'!V:V, SMALL(IF('Bank Schedule'!$K$2:$K$825="Vacant", ROW('Bank Schedule'!$K$2:$K$825)), ROW(8:8))), "")} | W11: {=IFERROR(INDEX('Bank Schedule'!W:W, SMALL(IF('Bank Schedule'!$K$2:$K$825="Vacant", ROW('Bank Schedule'!$K$2:$K$825)), ROW(8:8))), "")} | X11: {=IFERROR(INDEX('Bank Schedule'!X:X, SMALL(IF('Bank Schedule'!$K$2:$K$825="Vacant", ROW('Bank Schedule'!$K$2:$K$825)), ROW(8:8))), "")} | Y11: {=IFERROR(INDEX('Bank Schedule'!Y:Y, SMALL(IF('Bank Schedule'!$K$2:$K$825="Vacant", ROW('Bank Schedule'!$K$2:$K$825)), ROW(8:8))), "")} | Z11: {=IFERROR(INDEX('Bank Schedule'!Z:Z, SMALL(IF('Bank Schedule'!$K$2:$K$825="Vacant", ROW('Bank Schedule'!$K$2:$K$825)), ROW(8:8))), "")} | AA11: {=IFERROR(INDEX('Bank Schedule'!AA:AA, SMALL(IF('Bank Schedule'!$K$2:$K$825="Vacant", ROW('Bank Schedule'!$K$2:$K$825)), ROW(8:8))), "")} | AB11: {=IFERROR(INDEX('Bank Schedule'!AB:AB, SMALL(IF('Bank Schedule'!$K$2:$K$825="Vacant", ROW('Bank Schedule'!$K$2:$K$825)), ROW(8:8))), "")} | AC11: {=IFERROR(INDEX('Bank Schedule'!AC:AC, SMALL(IF('Bank Schedule'!$K$2:$K$825="Vacant", ROW('Bank Schedule'!$K$2:$K$825)), ROW(8:8))), "")} | AD11: {=IFERROR(INDEX('Bank Schedule'!AD:AD, SMALL(IF('Bank Schedule'!$K$2:$K$825="Vacant", ROW('Bank Schedule'!$K$2:$K$825)), ROW(8:8))), "")} | AE11: {=IFERROR(INDEX('Bank Schedule'!AE:AE, SMALL(IF('Bank Schedule'!$K$2:$K$825="Vacant", ROW('Bank Schedule'!$K$2:$K$825)), ROW(8:8))), "")} | AF11: {=IFERROR(INDEX('Bank Schedule'!AF:AF, SMALL(IF('Bank Schedule'!$K$2:$K$825="Vacant", ROW('Bank Schedule'!$K$2:$K$825)), ROW(8:8))), "")} | AG11: {=IFERROR(INDEX('Bank Schedule'!AG:AG, SMALL(IF('Bank Schedule'!$K$2:$K$825="Vacant", ROW('Bank Schedule'!$K$2:$K$825)), ROW(8:8))), "")} | AH11: {=IFERROR(INDEX('Bank Schedule'!AH:AH, SMALL(IF('Bank Schedule'!$K$2:$K$825="Vacant", ROW('Bank Schedule'!$K$2:$K$825)), ROW(8:8))), "")}
A12: {=IFERROR(INDEX('Bank Schedule'!A:A, SMALL(IF('Bank Schedule'!$K$2:$K$825="Vacant", ROW('Bank Schedule'!$K$2:$K$825)), ROW(9:9))), "")} | B12: {=IFERROR(INDEX('Bank Schedule'!B:B, SMALL(IF('Bank Schedule'!$K$2:$K$825="Vacant", ROW('Bank Schedule'!$K$2:$K$825)), ROW(9:9))), "")} | C12: {=IFERROR(INDEX('Bank Schedule'!C:C, SMALL(IF('Bank Schedule'!$K$2:$K$825="Vacant", ROW('Bank Schedule'!$K$2:$K$825)), ROW(9:9))), "")} | D12: {=IFERROR(INDEX('Bank Schedule'!D:D, SMALL(IF('Bank Schedule'!$K$2:$K$825="Vacant", ROW('Bank Schedule'!$K$2:$K$825)), ROW(9:9))), "")} | E12: {=IFERROR(INDEX('Bank Schedule'!E:E, SMALL(IF('Bank Schedule'!$K$2:$K$825="Vacant", ROW('Bank Schedule'!$K$2:$K$825)), ROW(9:9))), "")} | F12: {=IFERROR(INDEX('Bank Schedule'!F:F, SMALL(IF('Bank Schedule'!$K$2:$K$825="Vacant", ROW('Bank Schedule'!$K$2:$K$825)), ROW(9:9))), "")} | G12: {=IFERROR(INDEX('Bank Schedule'!G:G, SMALL(IF('Bank Schedule'!$K$2:$K$825="Vacant", ROW('Bank Schedule'!$K$2:$K$825)), ROW(9:9))), "")} | H12: {=IFERROR(INDEX('Bank Schedule'!H:H, SMALL(IF('Bank Schedule'!$K$2:$K$825="Vacant", ROW('Bank Schedule'!$K$2:$K$825)), ROW(9:9))), "")} | I12: {=IFERROR(INDEX('Bank Schedule'!I:I, SMALL(IF('Bank Schedule'!$K$2:$K$825="Vacant", ROW('Bank Schedule'!$K$2:$K$825)), ROW(9:9))), "")} | J12: {=IFERROR(INDEX('Bank Schedule'!J:J, SMALL(IF('Bank Schedule'!$K$2:$K$825="Vacant", ROW('Bank Schedule'!$K$2:$K$825)), ROW(9:9))), "")} | K12: {=IFERROR(INDEX('Bank Schedule'!K:K, SMALL(IF('Bank Schedule'!$K$2:$K$825="Vacant", ROW('Bank Schedule'!$K$2:$K$825)), ROW(9:9))), "")} | L12: {=IFERROR(INDEX('Bank Schedule'!L:L, SMALL(IF('Bank Schedule'!$K$2:$K$825="Vacant", ROW('Bank Schedule'!$K$2:$K$825)), ROW(9:9))), "")} | M12: {=IFERROR(INDEX('Bank Schedule'!M:M, SMALL(IF('Bank Schedule'!$K$2:$K$825="Vacant", ROW('Bank Schedule'!$K$2:$K$825)), ROW(9:9))), "")} | N12: {=IFERROR(INDEX('Bank Schedule'!N:N, SMALL(IF('Bank Schedule'!$K$2:$K$825="Vacant", ROW('Bank Schedule'!$K$2:$K$825)), ROW(9:9))), "")} | O12: {=IFERROR(INDEX('Bank Schedule'!O:O, SMALL(IF('Bank Schedule'!$K$2:$K$825="Vacant", ROW('Bank Schedule'!$K$2:$K$825)), ROW(9:9))), "")} | P12: {=IFERROR(INDEX('Bank Schedule'!P:P, SMALL(IF('Bank Schedule'!$K$2:$K$825="Vacant", ROW('Bank Schedule'!$K$2:$K$825)), ROW(9:9))), "")} | Q12: {=IFERROR(INDEX('Bank Schedule'!Q:Q, SMALL(IF('Bank Schedule'!$K$2:$K$825="Vacant", ROW('Bank Schedule'!$K$2:$K$825)), ROW(9:9))), "")} | R12: {=IFERROR(INDEX('Bank Schedule'!R:R, SMALL(IF('Bank Schedule'!$K$2:$K$825="Vacant", ROW('Bank Schedule'!$K$2:$K$825)), ROW(9:9))), "")} | S12: {=IFERROR(INDEX('Bank Schedule'!S:S, SMALL(IF('Bank Schedule'!$K$2:$K$825="Vacant", ROW('Bank Schedule'!$K$2:$K$825)), ROW(9:9))), "")} | T12: {=IFERROR(INDEX('Bank Schedule'!T:T, SMALL(IF('Bank Schedule'!$K$2:$K$825="Vacant", ROW('Bank Schedule'!$K$2:$K$825)), ROW(9:9))), "")} | U12: {=IFERROR(INDEX('Bank Schedule'!U:U, SMALL(IF('Bank Schedule'!$K$2:$K$825="Vacant", ROW('Bank Schedule'!$K$2:$K$825)), ROW(9:9))), "")} | V12: {=IFERROR(INDEX('Bank Schedule'!V:V, SMALL(IF('Bank Schedule'!$K$2:$K$825="Vacant", ROW('Bank Schedule'!$K$2:$K$825)), ROW(9:9))), "")} | W12: {=IFERROR(INDEX('Bank Schedule'!W:W, SMALL(IF('Bank Schedule'!$K$2:$K$825="Vacant", ROW('Bank Schedule'!$K$2:$K$825)), ROW(9:9))), "")} | X12: {=IFERROR(INDEX('Bank Schedule'!X:X, SMALL(IF('Bank Schedule'!$K$2:$K$825="Vacant", ROW('Bank Schedule'!$K$2:$K$825)), ROW(9:9))), "")} | Y12: {=IFERROR(INDEX('Bank Schedule'!Y:Y, SMALL(IF('Bank Schedule'!$K$2:$K$825="Vacant", ROW('Bank Schedule'!$K$2:$K$825)), ROW(9:9))), "")} | Z12: {=IFERROR(INDEX('Bank Schedule'!Z:Z, SMALL(IF('Bank Schedule'!$K$2:$K$825="Vacant", ROW('Bank Schedule'!$K$2:$K$825)), ROW(9:9))), "")} | AA12: {=IFERROR(INDEX('Bank Schedule'!AA:AA, SMALL(IF('Bank Schedule'!$K$2:$K$825="Vacant", ROW('Bank Schedule'!$K$2:$K$825)), ROW(9:9))), "")} | AB12: {=IFERROR(INDEX('Bank Schedule'!AB:AB, SMALL(IF('Bank Schedule'!$K$2:$K$825="Vacant", ROW('Bank Schedule'!$K$2:$K$825)), ROW(9:9))), "")} | AC12: {=IFERROR(INDEX('Bank Schedule'!AC:AC, SMALL(IF('Bank Schedule'!$K$2:$K$825="Vacant", ROW('Bank Schedule'!$K$2:$K$825)), ROW(9:9))), "")} | AD12: {=IFERROR(INDEX('Bank Schedule'!AD:AD, SMALL(IF('Bank Schedule'!$K$2:$K$825="Vacant", ROW('Bank Schedule'!$K$2:$K$825)), ROW(9:9))), "")} | AE12: {=IFERROR(INDEX('Bank Schedule'!AE:AE, SMALL(IF('Bank Schedule'!$K$2:$K$825="Vacant", ROW('Bank Schedule'!$K$2:$K$825)), ROW(9:9))), "")} | AF12: {=IFERROR(INDEX('Bank Schedule'!AF:AF, SMALL(IF('Bank Schedule'!$K$2:$K$825="Vacant", ROW('Bank Schedule'!$K$2:$K$825)), ROW(9:9))), "")} | AG12: {=IFERROR(INDEX('Bank Schedule'!AG:AG, SMALL(IF('Bank Schedule'!$K$2:$K$825="Vacant", ROW('Bank Schedule'!$K$2:$K$825)), ROW(9:9))), "")} | AH12: {=IFERROR(INDEX('Bank Schedule'!AH:AH, SMALL(IF('Bank Schedule'!$K$2:$K$825="Vacant", ROW('Bank Schedule'!$K$2:$K$825)), ROW(9:9))), "")}
A13: {=IFERROR(INDEX('Bank Schedule'!A:A, SMALL(IF('Bank Schedule'!$K$2:$K$825="Vacant", ROW('Bank Schedule'!$K$2:$K$825)), ROW(10:10))), "")} | B13: {=IFERROR(INDEX('Bank Schedule'!B:B, SMALL(IF('Bank Schedule'!$K$2:$K$825="Vacant", ROW('Bank Schedule'!$K$2:$K$825)), ROW(10:10))), "")} | C13: {=IFERROR(INDEX('Bank Schedule'!C:C, SMALL(IF('Bank Schedule'!$K$2:$K$825="Vacant", ROW('Bank Schedule'!$K$2:$K$825)), ROW(10:10))), "")} | D13: {=IFERROR(INDEX('Bank Schedule'!D:D, SMALL(IF('Bank Schedule'!$K$2:$K$825="Vacant", ROW('Bank Schedule'!$K$2:$K$825)), ROW(10:10))), "")} | E13: {=IFERROR(INDEX('Bank Schedule'!E:E, SMALL(IF('Bank Schedule'!$K$2:$K$825="Vacant", ROW('Bank Schedule'!$K$2:$K$825)), ROW(10:10))), "")} | F13: {=IFERROR(INDEX('Bank Schedule'!F:F, SMALL(IF('Bank Schedule'!$K$2:$K$825="Vacant", ROW('Bank Schedule'!$K$2:$K$825)), ROW(10:10))), "")} | G13: {=IFERROR(INDEX('Bank Schedule'!G:G, SMALL(IF('Bank Schedule'!$K$2:$K$825="Vacant", ROW('Bank Schedule'!$K$2:$K$825)), ROW(10:10))), "")} | H13: {=IFERROR(INDEX('Bank Schedule'!H:H, SMALL(IF('Bank Schedule'!$K$2:$K$825="Vacant", ROW('Bank Schedule'!$K$2:$K$825)), ROW(10:10))), "")} | I13: {=IFERROR(INDEX('Bank Schedule'!I:I, SMALL(IF('Bank Schedule'!$K$2:$K$825="Vacant", ROW('Bank Schedule'!$K$2:$K$825)), ROW(10:10))), "")} | J13: {=IFERROR(INDEX('Bank Schedule'!J:J, SMALL(IF('Bank Schedule'!$K$2:$K$825="Vacant", ROW('Bank Schedule'!$K$2:$K$825)), ROW(10:10))), "")} | K13: {=IFERROR(INDEX('Bank Schedule'!K:K, SMALL(IF('Bank Schedule'!$K$2:$K$825="Vacant", ROW('Bank Schedule'!$K$2:$K$825)), ROW(10:10))), "")} | L13: {=IFERROR(INDEX('Bank Schedule'!L:L, SMALL(IF('Bank Schedule'!$K$2:$K$825="Vacant", ROW('Bank Schedule'!$K$2:$K$825)), ROW(10:10))), "")} | M13: {=IFERROR(INDEX('Bank Schedule'!M:M, SMALL(IF('Bank Schedule'!$K$2:$K$825="Vacant", ROW('Bank Schedule'!$K$2:$K$825)), ROW(10:10))), "")} | N13: {=IFERROR(INDEX('Bank Schedule'!N:N, SMALL(IF('Bank Schedule'!$K$2:$K$825="Vacant", ROW('Bank Schedule'!$K$2:$K$825)), ROW(10:10))), "")} | O13: {=IFERROR(INDEX('Bank Schedule'!O:O, SMALL(IF('Bank Schedule'!$K$2:$K$825="Vacant", ROW('Bank Schedule'!$K$2:$K$825)), ROW(10:10))), "")} | P13: {=IFERROR(INDEX('Bank Schedule'!P:P, SMALL(IF('Bank Schedule'!$K$2:$K$825="Vacant", ROW('Bank Schedule'!$K$2:$K$825)), ROW(10:10))), "")} | Q13: {=IFERROR(INDEX('Bank Schedule'!Q:Q, SMALL(IF('Bank Schedule'!$K$2:$K$825="Vacant", ROW('Bank Schedule'!$K$2:$K$825)), ROW(10:10))), "")} | R13: {=IFERROR(INDEX('Bank Schedule'!R:R, SMALL(IF('Bank Schedule'!$K$2:$K$825="Vacant", ROW('Bank Schedule'!$K$2:$K$825)), ROW(10:10))), "")} | S13: {=IFERROR(INDEX('Bank Schedule'!S:S, SMALL(IF('Bank Schedule'!$K$2:$K$825="Vacant", ROW('Bank Schedule'!$K$2:$K$825)), ROW(10:10))), "")} | T13: {=IFERROR(INDEX('Bank Schedule'!T:T, SMALL(IF('Bank Schedule'!$K$2:$K$825="Vacant", ROW('Bank Schedule'!$K$2:$K$825)), ROW(10:10))), "")} | U13: {=IFERROR(INDEX('Bank Schedule'!U:U, SMALL(IF('Bank Schedule'!$K$2:$K$825="Vacant", ROW('Bank Schedule'!$K$2:$K$825)), ROW(10:10))), "")} | V13: {=IFERROR(INDEX('Bank Schedule'!V:V, SMALL(IF('Bank Schedule'!$K$2:$K$825="Vacant", ROW('Bank Schedule'!$K$2:$K$825)), ROW(10:10))), "")} | W13: {=IFERROR(INDEX('Bank Schedule'!W:W, SMALL(IF('Bank Schedule'!$K$2:$K$825="Vacant", ROW('Bank Schedule'!$K$2:$K$825)), ROW(10:10))), "")} | X13: {=IFERROR(INDEX('Bank Schedule'!X:X, SMALL(IF('Bank Schedule'!$K$2:$K$825="Vacant", ROW('Bank Schedule'!$K$2:$K$825)), ROW(10:10))), "")} | Y13: {=IFERROR(INDEX('Bank Schedule'!Y:Y, SMALL(IF('Bank Schedule'!$K$2:$K$825="Vacant", ROW('Bank Schedule'!$K$2:$K$825)), ROW(10:10))), "")} | Z13: {=IFERROR(INDEX('Bank Schedule'!Z:Z, SMALL(IF('Bank Schedule'!$K$2:$K$825="Vacant", ROW('Bank Schedule'!$K$2:$K$825)), ROW(10:10))), "")} | AA13: {=IFERROR(INDEX('Bank Schedule'!AA:AA, SMALL(IF('Bank Schedule'!$K$2:$K$825="Vacant", ROW('Bank Schedule'!$K$2:$K$825)), ROW(10:10))), "")} | AB13: {=IFERROR(INDEX('Bank Schedule'!AB:AB, SMALL(IF('Bank Schedule'!$K$2:$K$825="Vacant", ROW('Bank Schedule'!$K$2:$K$825)), ROW(10:10))), "")} | AC13: {=IFERROR(INDEX('Bank Schedule'!AC:AC, SMALL(IF('Bank Schedule'!$K$2:$K$825="Vacant", ROW('Bank Schedule'!$K$2:$K$825)), ROW(10:10))), "")} | AD13: {=IFERROR(INDEX('Bank Schedule'!AD:AD, SMALL(IF('Bank Schedule'!$K$2:$K$825="Vacant", ROW('Bank Schedule'!$K$2:$K$825)), ROW(10:10))), "")} | AE13: {=IFERROR(INDEX('Bank Schedule'!AE:AE, SMALL(IF('Bank Schedule'!$K$2:$K$825="Vacant", ROW('Bank Schedule'!$K$2:$K$825)), ROW(10:10))), "")} | AF13: {=IFERROR(INDEX('Bank Schedule'!AF:AF, SMALL(IF('Bank Schedule'!$K$2:$K$825="Vacant", ROW('Bank Schedule'!$K$2:$K$825)), ROW(10:10))), "")} | AG13: {=IFERROR(INDEX('Bank Schedule'!AG:AG, SMALL(IF('Bank Schedule'!$K$2:$K$825="Vacant", ROW('Bank Schedule'!$K$2:$K$825)), ROW(10:10))), "")} | AH13: {=IFERROR(INDEX('Bank Schedule'!AH:AH, SMALL(IF('Bank Schedule'!$K$2:$K$825="Vacant", ROW('Bank Schedule'!$K$2:$K$825)), ROW(10:10))), "")}
A14: {=IFERROR(INDEX('Bank Schedule'!A:A, SMALL(IF('Bank Schedule'!$K$2:$K$825="Vacant", ROW('Bank Schedule'!$K$2:$K$825)), ROW(11:11))), "")} | B14: {=IFERROR(INDEX('Bank Schedule'!B:B, SMALL(IF('Bank Schedule'!$K$2:$K$825="Vacant", ROW('Bank Schedule'!$K$2:$K$825)), ROW(11:11))), "")} | C14: {=IFERROR(INDEX('Bank Schedule'!C:C, SMALL(IF('Bank Schedule'!$K$2:$K$825="Vacant", ROW('Bank Schedule'!$K$2:$K$825)), ROW(11:11))), "")} | D14: {=IFERROR(INDEX('Bank Schedule'!D:D, SMALL(IF('Bank Schedule'!$K$2:$K$825="Vacant", ROW('Bank Schedule'!$K$2:$K$825)), ROW(11:11))), "")} | E14: {=IFERROR(INDEX('Bank Schedule'!E:E, SMALL(IF('Bank Schedule'!$K$2:$K$825="Vacant", ROW('Bank Schedule'!$K$2:$K$825)), ROW(11:11))), "")} | F14: {=IFERROR(INDEX('Bank Schedule'!F:F, SMALL(IF('Bank Schedule'!$K$2:$K$825="Vacant", ROW('Bank Schedule'!$K$2:$K$825)), ROW(11:11))), "")} | G14: {=IFERROR(INDEX('Bank Schedule'!G:G, SMALL(IF('Bank Schedule'!$K$2:$K$825="Vacant", ROW('Bank Schedule'!$K$2:$K$825)), ROW(11:11))), "")} | H14: {=IFERROR(INDEX('Bank Schedule'!H:H, SMALL(IF('Bank Schedule'!$K$2:$K$825="Vacant", ROW('Bank Schedule'!$K$2:$K$825)), ROW(11:11))), "")} | I14: {=IFERROR(INDEX('Bank Schedule'!I:I, SMALL(IF('Bank Schedule'!$K$2:$K$825="Vacant", ROW('Bank Schedule'!$K$2:$K$825)), ROW(11:11))), "")} | J14: {=IFERROR(INDEX('Bank Schedule'!J:J, SMALL(IF('Bank Schedule'!$K$2:$K$825="Vacant", ROW('Bank Schedule'!$K$2:$K$825)), ROW(11:11))), "")} | K14: {=IFERROR(INDEX('Bank Schedule'!K:K, SMALL(IF('Bank Schedule'!$K$2:$K$825="Vacant", ROW('Bank Schedule'!$K$2:$K$825)), ROW(11:11))), "")} | L14: {=IFERROR(INDEX('Bank Schedule'!L:L, SMALL(IF('Bank Schedule'!$K$2:$K$825="Vacant", ROW('Bank Schedule'!$K$2:$K$825)), ROW(11:11))), "")} | M14: {=IFERROR(INDEX('Bank Schedule'!M:M, SMALL(IF('Bank Schedule'!$K$2:$K$825="Vacant", ROW('Bank Schedule'!$K$2:$K$825)), ROW(11:11))), "")} | N14: {=IFERROR(INDEX('Bank Schedule'!N:N, SMALL(IF('Bank Schedule'!$K$2:$K$825="Vacant", ROW('Bank Schedule'!$K$2:$K$825)), ROW(11:11))), "")} | O14: {=IFERROR(INDEX('Bank Schedule'!O:O, SMALL(IF('Bank Schedule'!$K$2:$K$825="Vacant", ROW('Bank Schedule'!$K$2:$K$825)), ROW(11:11))), "")} | P14: {=IFERROR(INDEX('Bank Schedule'!P:P, SMALL(IF('Bank Schedule'!$K$2:$K$825="Vacant", ROW('Bank Schedule'!$K$2:$K$825)), ROW(11:11))), "")} | Q14: {=IFERROR(INDEX('Bank Schedule'!Q:Q, SMALL(IF('Bank Schedule'!$K$2:$K$825="Vacant", ROW('Bank Schedule'!$K$2:$K$825)), ROW(11:11))), "")} | R14: {=IFERROR(INDEX('Bank Schedule'!R:R, SMALL(IF('Bank Schedule'!$K$2:$K$825="Vacant", ROW('Bank Schedule'!$K$2:$K$825)), ROW(11:11))), "")} | S14: {=IFERROR(INDEX('Bank Schedule'!S:S, SMALL(IF('Bank Schedule'!$K$2:$K$825="Vacant", ROW('Bank Schedule'!$K$2:$K$825)), ROW(11:11))), "")} | T14: {=IFERROR(INDEX('Bank Schedule'!T:T, SMALL(IF('Bank Schedule'!$K$2:$K$825="Vacant", ROW('Bank Schedule'!$K$2:$K$825)), ROW(11:11))), "")} | U14: {=IFERROR(INDEX('Bank Schedule'!U:U, SMALL(IF('Bank Schedule'!$K$2:$K$825="Vacant", ROW('Bank Schedule'!$K$2:$K$825)), ROW(11:11))), "")} | V14: {=IFERROR(INDEX('Bank Schedule'!V:V, SMALL(IF('Bank Schedule'!$K$2:$K$825="Vacant", ROW('Bank Schedule'!$K$2:$K$825)), ROW(11:11))), "")} | W14: {=IFERROR(INDEX('Bank Schedule'!W:W, SMALL(IF('Bank Schedule'!$K$2:$K$825="Vacant", ROW('Bank Schedule'!$K$2:$K$825)), ROW(11:11))), "")} | X14: {=IFERROR(INDEX('Bank Schedule'!X:X, SMALL(IF('Bank Schedule'!$K$2:$K$825="Vacant", ROW('Bank Schedule'!$K$2:$K$825)), ROW(11:11))), "")} | Y14: {=IFERROR(INDEX('Bank Schedule'!Y:Y, SMALL(IF('Bank Schedule'!$K$2:$K$825="Vacant", ROW('Bank Schedule'!$K$2:$K$825)), ROW(11:11))), "")} | Z14: {=IFERROR(INDEX('Bank Schedule'!Z:Z, SMALL(IF('Bank Schedule'!$K$2:$K$825="Vacant", ROW('Bank Schedule'!$K$2:$K$825)), ROW(11:11))), "")} | AA14: {=IFERROR(INDEX('Bank Schedule'!AA:AA, SMALL(IF('Bank Schedule'!$K$2:$K$825="Vacant", ROW('Bank Schedule'!$K$2:$K$825)), ROW(11:11))), "")} | AB14: {=IFERROR(INDEX('Bank Schedule'!AB:AB, SMALL(IF('Bank Schedule'!$K$2:$K$825="Vacant", ROW('Bank Schedule'!$K$2:$K$825)), ROW(11:11))), "")} | AC14: {=IFERROR(INDEX('Bank Schedule'!AC:AC, SMALL(IF('Bank Schedule'!$K$2:$K$825="Vacant", ROW('Bank Schedule'!$K$2:$K$825)), ROW(11:11))), "")} | AD14: {=IFERROR(INDEX('Bank Schedule'!AD:AD, SMALL(IF('Bank Schedule'!$K$2:$K$825="Vacant", ROW('Bank Schedule'!$K$2:$K$825)), ROW(11:11))), "")} | AE14: {=IFERROR(INDEX('Bank Schedule'!AE:AE, SMALL(IF('Bank Schedule'!$K$2:$K$825="Vacant", ROW('Bank Schedule'!$K$2:$K$825)), ROW(11:11))), "")} | AF14: {=IFERROR(INDEX('Bank Schedule'!AF:AF, SMALL(IF('Bank Schedule'!$K$2:$K$825="Vacant", ROW('Bank Schedule'!$K$2:$K$825)), ROW(11:11))), "")} | AG14: {=IFERROR(INDEX('Bank Schedule'!AG:AG, SMALL(IF('Bank Schedule'!$K$2:$K$825="Vacant", ROW('Bank Schedule'!$K$2:$K$825)), ROW(11:11))), "")} | AH14: {=IFERROR(INDEX('Bank Schedule'!AH:AH, SMALL(IF('Bank Schedule'!$K$2:$K$825="Vacant", ROW('Bank Schedule'!$K$2:$K$825)), ROW(11:11))), "")}
A15: {=IFERROR(INDEX('Bank Schedule'!A:A, SMALL(IF('Bank Schedule'!$K$2:$K$825="Vacant", ROW('Bank Schedule'!$K$2:$K$825)), ROW(12:12))), "")} | B15: {=IFERROR(INDEX('Bank Schedule'!B:B, SMALL(IF('Bank Schedule'!$K$2:$K$825="Vacant", ROW('Bank Schedule'!$K$2:$K$825)), ROW(12:12))), "")} | C15: {=IFERROR(INDEX('Bank Schedule'!C:C, SMALL(IF('Bank Schedule'!$K$2:$K$825="Vacant", ROW('Bank Schedule'!$K$2:$K$825)), ROW(12:12))), "")} | D15: {=IFERROR(INDEX('Bank Schedule'!D:D, SMALL(IF('Bank Schedule'!$K$2:$K$825="Vacant", ROW('Bank Schedule'!$K$2:$K$825)), ROW(12:12))), "")} | E15: {=IFERROR(INDEX('Bank Schedule'!E:E, SMALL(IF('Bank Schedule'!$K$2:$K$825="Vacant", ROW('Bank Schedule'!$K$2:$K$825)), ROW(12:12))), "")} | F15: {=IFERROR(INDEX('Bank Schedule'!F:F, SMALL(IF('Bank Schedule'!$K$2:$K$825="Vacant", ROW('Bank Schedule'!$K$2:$K$825)), ROW(12:12))), "")} | G15: {=IFERROR(INDEX('Bank Schedule'!G:G, SMALL(IF('Bank Schedule'!$K$2:$K$825="Vacant", ROW('Bank Schedule'!$K$2:$K$825)), ROW(12:12))), "")} | H15: {=IFERROR(INDEX('Bank Schedule'!H:H, SMALL(IF('Bank Schedule'!$K$2:$K$825="Vacant", ROW('Bank Schedule'!$K$2:$K$825)), ROW(12:12))), "")} | I15: {=IFERROR(INDEX('Bank Schedule'!I:I, SMALL(IF('Bank Schedule'!$K$2:$K$825="Vacant", ROW('Bank Schedule'!$K$2:$K$825)), ROW(12:12))), "")} | J15: {=IFERROR(INDEX('Bank Schedule'!J:J, SMALL(IF('Bank Schedule'!$K$2:$K$825="Vacant", ROW('Bank Schedule'!$K$2:$K$825)), ROW(12:12))), "")} | K15: {=IFERROR(INDEX('Bank Schedule'!K:K, SMALL(IF('Bank Schedule'!$K$2:$K$825="Vacant", ROW('Bank Schedule'!$K$2:$K$825)), ROW(12:12))), "")} | L15: {=IFERROR(INDEX('Bank Schedule'!L:L, SMALL(IF('Bank Schedule'!$K$2:$K$825="Vacant", ROW('Bank Schedule'!$K$2:$K$825)), ROW(12:12))), "")} | M15: {=IFERROR(INDEX('Bank Schedule'!M:M, SMALL(IF('Bank Schedule'!$K$2:$K$825="Vacant", ROW('Bank Schedule'!$K$2:$K$825)), ROW(12:12))), "")} | N15: {=IFERROR(INDEX('Bank Schedule'!N:N, SMALL(IF('Bank Schedule'!$K$2:$K$825="Vacant", ROW('Bank Schedule'!$K$2:$K$825)), ROW(12:12))), "")} | O15: {=IFERROR(INDEX('Bank Schedule'!O:O, SMALL(IF('Bank Schedule'!$K$2:$K$825="Vacant", ROW('Bank Schedule'!$K$2:$K$825)), ROW(12:12))), "")} | P15: {=IFERROR(INDEX('Bank Schedule'!P:P, SMALL(IF('Bank Schedule'!$K$2:$K$825="Vacant", ROW('Bank Schedule'!$K$2:$K$825)), ROW(12:12))), "")} | Q15: {=IFERROR(INDEX('Bank Schedule'!Q:Q, SMALL(IF('Bank Schedule'!$K$2:$K$825="Vacant", ROW('Bank Schedule'!$K$2:$K$825)), ROW(12:12))), "")} | R15: {=IFERROR(INDEX('Bank Schedule'!R:R, SMALL(IF('Bank Schedule'!$K$2:$K$825="Vacant", ROW('Bank Schedule'!$K$2:$K$825)), ROW(12:12))), "")} | S15: {=IFERROR(INDEX('Bank Schedule'!S:S, SMALL(IF('Bank Schedule'!$K$2:$K$825="Vacant", ROW('Bank Schedule'!$K$2:$K$825)), ROW(12:12))), "")} | T15: {=IFERROR(INDEX('Bank Schedule'!T:T, SMALL(IF('Bank Schedule'!$K$2:$K$825="Vacant", ROW('Bank Schedule'!$K$2:$K$825)), ROW(12:12))), "")} | U15: {=IFERROR(INDEX('Bank Schedule'!U:U, SMALL(IF('Bank Schedule'!$K$2:$K$825="Vacant", ROW('Bank Schedule'!$K$2:$K$825)), ROW(12:12))), "")} | V15: {=IFERROR(INDEX('Bank Schedule'!V:V, SMALL(IF('Bank Schedule'!$K$2:$K$825="Vacant", ROW('Bank Schedule'!$K$2:$K$825)), ROW(12:12))), "")} | W15: {=IFERROR(INDEX('Bank Schedule'!W:W, SMALL(IF('Bank Schedule'!$K$2:$K$825="Vacant", ROW('Bank Schedule'!$K$2:$K$825)), ROW(12:12))), "")} | X15: {=IFERROR(INDEX('Bank Schedule'!X:X, SMALL(IF('Bank Schedule'!$K$2:$K$825="Vacant", ROW('Bank Schedule'!$K$2:$K$825)), ROW(12:12))), "")} | Y15: {=IFERROR(INDEX('Bank Schedule'!Y:Y, SMALL(IF('Bank Schedule'!$K$2:$K$825="Vacant", ROW('Bank Schedule'!$K$2:$K$825)), ROW(12:12))), "")} | Z15: {=IFERROR(INDEX('Bank Schedule'!Z:Z, SMALL(IF('Bank Schedule'!$K$2:$K$825="Vacant", ROW('Bank Schedule'!$K$2:$K$825)), ROW(12:12))), "")} | AA15: {=IFERROR(INDEX('Bank Schedule'!AA:AA, SMALL(IF('Bank Schedule'!$K$2:$K$825="Vacant", ROW('Bank Schedule'!$K$2:$K$825)), ROW(12:12))), "")} | AB15: {=IFERROR(INDEX('Bank Schedule'!AB:AB, SMALL(IF('Bank Schedule'!$K$2:$K$825="Vacant", ROW('Bank Schedule'!$K$2:$K$825)), ROW(12:12))), "")} | AC15: {=IFERROR(INDEX('Bank Schedule'!AC:AC, SMALL(IF('Bank Schedule'!$K$2:$K$825="Vacant", ROW('Bank Schedule'!$K$2:$K$825)), ROW(12:12))), "")} | AD15: {=IFERROR(INDEX('Bank Schedule'!AD:AD, SMALL(IF('Bank Schedule'!$K$2:$K$825="Vacant", ROW('Bank Schedule'!$K$2:$K$825)), ROW(12:12))), "")} | AE15: {=IFERROR(INDEX('Bank Schedule'!AE:AE, SMALL(IF('Bank Schedule'!$K$2:$K$825="Vacant", ROW('Bank Schedule'!$K$2:$K$825)), ROW(12:12))), "")} | AF15: {=IFERROR(INDEX('Bank Schedule'!AF:AF, SMALL(IF('Bank Schedule'!$K$2:$K$825="Vacant", ROW('Bank Schedule'!$K$2:$K$825)), ROW(12:12))), "")} | AG15: {=IFERROR(INDEX('Bank Schedule'!AG:AG, SMALL(IF('Bank Schedule'!$K$2:$K$825="Vacant", ROW('Bank Schedule'!$K$2:$K$825)), ROW(12:12))), "")} | AH15: {=IFERROR(INDEX('Bank Schedule'!AH:AH, SMALL(IF('Bank Schedule'!$K$2:$K$825="Vacant", ROW('Bank Schedule'!$K$2:$K$825)), ROW(12:12))), "")}
A16: {=IFERROR(INDEX('Bank Schedule'!A:A, SMALL(IF('Bank Schedule'!$K$2:$K$825="Vacant", ROW('Bank Schedule'!$K$2:$K$825)), ROW(13:13))), "")} | B16: {=IFERROR(INDEX('Bank Schedule'!B:B, SMALL(IF('Bank Schedule'!$K$2:$K$825="Vacant", ROW('Bank Schedule'!$K$2:$K$825)), ROW(13:13))), "")} | C16: {=IFERROR(INDEX('Bank Schedule'!C:C, SMALL(IF('Bank Schedule'!$K$2:$K$825="Vacant", ROW('Bank Schedule'!$K$2:$K$825)), ROW(13:13))), "")} | D16: {=IFERROR(INDEX('Bank Schedule'!D:D, SMALL(IF('Bank Schedule'!$K$2:$K$825="Vacant", ROW('Bank Schedule'!$K$2:$K$825)), ROW(13:13))), "")} | E16: {=IFERROR(INDEX('Bank Schedule'!E:E, SMALL(IF('Bank Schedule'!$K$2:$K$825="Vacant", ROW('Bank Schedule'!$K$2:$K$825)), ROW(13:13))), "")} | F16: {=IFERROR(INDEX('Bank Schedule'!F:F, SMALL(IF('Bank Schedule'!$K$2:$K$825="Vacant", ROW('Bank Schedule'!$K$2:$K$825)), ROW(13:13))), "")} | G16: {=IFERROR(INDEX('Bank Schedule'!G:G, SMALL(IF('Bank Schedule'!$K$2:$K$825="Vacant", ROW('Bank Schedule'!$K$2:$K$825)), ROW(13:13))), "")} | H16: {=IFERROR(INDEX('Bank Schedule'!H:H, SMALL(IF('Bank Schedule'!$K$2:$K$825="Vacant", ROW('Bank Schedule'!$K$2:$K$825)), ROW(13:13))), "")} | I16: {=IFERROR(INDEX('Bank Schedule'!I:I, SMALL(IF('Bank Schedule'!$K$2:$K$825="Vacant", ROW('Bank Schedule'!$K$2:$K$825)), ROW(13:13))), "")} | J16: {=IFERROR(INDEX('Bank Schedule'!J:J, SMALL(IF('Bank Schedule'!$K$2:$K$825="Vacant", ROW('Bank Schedule'!$K$2:$K$825)), ROW(13:13))), "")} | K16: {=IFERROR(INDEX('Bank Schedule'!K:K, SMALL(IF('Bank Schedule'!$K$2:$K$825="Vacant", ROW('Bank Schedule'!$K$2:$K$825)), ROW(13:13))), "")} | L16: {=IFERROR(INDEX('Bank Schedule'!L:L, SMALL(IF('Bank Schedule'!$K$2:$K$825="Vacant", ROW('Bank Schedule'!$K$2:$K$825)), ROW(13:13))), "")} | M16: {=IFERROR(INDEX('Bank Schedule'!M:M, SMALL(IF('Bank Schedule'!$K$2:$K$825="Vacant", ROW('Bank Schedule'!$K$2:$K$825)), ROW(13:13))), "")} | N16: {=IFERROR(INDEX('Bank Schedule'!N:N, SMALL(IF('Bank Schedule'!$K$2:$K$825="Vacant", ROW('Bank Schedule'!$K$2:$K$825)), ROW(13:13))), "")} | O16: {=IFERROR(INDEX('Bank Schedule'!O:O, SMALL(IF('Bank Schedule'!$K$2:$K$825="Vacant", ROW('Bank Schedule'!$K$2:$K$825)), ROW(13:13))), "")} | P16: {=IFERROR(INDEX('Bank Schedule'!P:P, SMALL(IF('Bank Schedule'!$K$2:$K$825="Vacant", ROW('Bank Schedule'!$K$2:$K$825)), ROW(13:13))), "")} | Q16: {=IFERROR(INDEX('Bank Schedule'!Q:Q, SMALL(IF('Bank Schedule'!$K$2:$K$825="Vacant", ROW('Bank Schedule'!$K$2:$K$825)), ROW(13:13))), "")} | R16: {=IFERROR(INDEX('Bank Schedule'!R:R, SMALL(IF('Bank Schedule'!$K$2:$K$825="Vacant", ROW('Bank Schedule'!$K$2:$K$825)), ROW(13:13))), "")} | S16: {=IFERROR(INDEX('Bank Schedule'!S:S, SMALL(IF('Bank Schedule'!$K$2:$K$825="Vacant", ROW('Bank Schedule'!$K$2:$K$825)), ROW(13:13))), "")} | T16: {=IFERROR(INDEX('Bank Schedule'!T:T, SMALL(IF('Bank Schedule'!$K$2:$K$825="Vacant", ROW('Bank Schedule'!$K$2:$K$825)), ROW(13:13))), "")} | U16: {=IFERROR(INDEX('Bank Schedule'!U:U, SMALL(IF('Bank Schedule'!$K$2:$K$825="Vacant", ROW('Bank Schedule'!$K$2:$K$825)), ROW(13:13))), "")} | V16: {=IFERROR(INDEX('Bank Schedule'!V:V, SMALL(IF('Bank Schedule'!$K$2:$K$825="Vacant", ROW('Bank Schedule'!$K$2:$K$825)), ROW(13:13))), "")} | W16: {=IFERROR(INDEX('Bank Schedule'!W:W, SMALL(IF('Bank Schedule'!$K$2:$K$825="Vacant", ROW('Bank Schedule'!$K$2:$K$825)), ROW(13:13))), "")} | X16: {=IFERROR(INDEX('Bank Schedule'!X:X, SMALL(IF('Bank Schedule'!$K$2:$K$825="Vacant", ROW('Bank Schedule'!$K$2:$K$825)), ROW(13:13))), "")} | Y16: {=IFERROR(INDEX('Bank Schedule'!Y:Y, SMALL(IF('Bank Schedule'!$K$2:$K$825="Vacant", ROW('Bank Schedule'!$K$2:$K$825)), ROW(13:13))), "")} | Z16: {=IFERROR(INDEX('Bank Schedule'!Z:Z, SMALL(IF('Bank Schedule'!$K$2:$K$825="Vacant", ROW('Bank Schedule'!$K$2:$K$825)), ROW(13:13))), "")} | AA16: {=IFERROR(INDEX('Bank Schedule'!AA:AA, SMALL(IF('Bank Schedule'!$K$2:$K$825="Vacant", ROW('Bank Schedule'!$K$2:$K$825)), ROW(13:13))), "")} | AB16: {=IFERROR(INDEX('Bank Schedule'!AB:AB, SMALL(IF('Bank Schedule'!$K$2:$K$825="Vacant", ROW('Bank Schedule'!$K$2:$K$825)), ROW(13:13))), "")} | AC16: {=IFERROR(INDEX('Bank Schedule'!AC:AC, SMALL(IF('Bank Schedule'!$K$2:$K$825="Vacant", ROW('Bank Schedule'!$K$2:$K$825)), ROW(13:13))), "")} | AD16: {=IFERROR(INDEX('Bank Schedule'!AD:AD, SMALL(IF('Bank Schedule'!$K$2:$K$825="Vacant", ROW('Bank Schedule'!$K$2:$K$825)), ROW(13:13))), "")} | AE16: {=IFERROR(INDEX('Bank Schedule'!AE:AE, SMALL(IF('Bank Schedule'!$K$2:$K$825="Vacant", ROW('Bank Schedule'!$K$2:$K$825)), ROW(13:13))), "")} | AF16: {=IFERROR(INDEX('Bank Schedule'!AF:AF, SMALL(IF('Bank Schedule'!$K$2:$K$825="Vacant", ROW('Bank Schedule'!$K$2:$K$825)), ROW(13:13))), "")} | AG16: {=IFERROR(INDEX('Bank Schedule'!AG:AG, SMALL(IF('Bank Schedule'!$K$2:$K$825="Vacant", ROW('Bank Schedule'!$K$2:$K$825)), ROW(13:13))), "")} | AH16: {=IFERROR(INDEX('Bank Schedule'!AH:AH, SMALL(IF('Bank Schedule'!$K$2:$K$825="Vacant", ROW('Bank Schedule'!$K$2:$K$825)), ROW(13:13))), "")}
A17: {=IFERROR(INDEX('Bank Schedule'!A:A, SMALL(IF('Bank Schedule'!$K$2:$K$825="Vacant", ROW('Bank Schedule'!$K$2:$K$825)), ROW(14:14))), "")} | B17: {=IFERROR(INDEX('Bank Schedule'!B:B, SMALL(IF('Bank Schedule'!$K$2:$K$825="Vacant", ROW('Bank Schedule'!$K$2:$K$825)), ROW(14:14))), "")} | C17: {=IFERROR(INDEX('Bank Schedule'!C:C, SMALL(IF('Bank Schedule'!$K$2:$K$825="Vacant", ROW('Bank Schedule'!$K$2:$K$825)), ROW(14:14))), "")} | D17: {=IFERROR(INDEX('Bank Schedule'!D:D, SMALL(IF('Bank Schedule'!$K$2:$K$825="Vacant", ROW('Bank Schedule'!$K$2:$K$825)), ROW(14:14))), "")} | E17: {=IFERROR(INDEX('Bank Schedule'!E:E, SMALL(IF('Bank Schedule'!$K$2:$K$825="Vacant", ROW('Bank Schedule'!$K$2:$K$825)), ROW(14:14))), "")} | F17: {=IFERROR(INDEX('Bank Schedule'!F:F, SMALL(IF('Bank Schedule'!$K$2:$K$825="Vacant", ROW('Bank Schedule'!$K$2:$K$825)), ROW(14:14))), "")} | G17: {=IFERROR(INDEX('Bank Schedule'!G:G, SMALL(IF('Bank Schedule'!$K$2:$K$825="Vacant", ROW('Bank Schedule'!$K$2:$K$825)), ROW(14:14))), "")} | H17: {=IFERROR(INDEX('Bank Schedule'!H:H, SMALL(IF('Bank Schedule'!$K$2:$K$825="Vacant", ROW('Bank Schedule'!$K$2:$K$825)), ROW(14:14))), "")} | I17: {=IFERROR(INDEX('Bank Schedule'!I:I, SMALL(IF('Bank Schedule'!$K$2:$K$825="Vacant", ROW('Bank Schedule'!$K$2:$K$825)), ROW(14:14))), "")} | J17: {=IFERROR(INDEX('Bank Schedule'!J:J, SMALL(IF('Bank Schedule'!$K$2:$K$825="Vacant", ROW('Bank Schedule'!$K$2:$K$825)), ROW(14:14))), "")} | K17: {=IFERROR(INDEX('Bank Schedule'!K:K, SMALL(IF('Bank Schedule'!$K$2:$K$825="Vacant", ROW('Bank Schedule'!$K$2:$K$825)), ROW(14:14))), "")} | L17: {=IFERROR(INDEX('Bank Schedule'!L:L, SMALL(IF('Bank Schedule'!$K$2:$K$825="Vacant", ROW('Bank Schedule'!$K$2:$K$825)), ROW(14:14))), "")} | M17: {=IFERROR(INDEX('Bank Schedule'!M:M, SMALL(IF('Bank Schedule'!$K$2:$K$825="Vacant", ROW('Bank Schedule'!$K$2:$K$825)), ROW(14:14))), "")} | N17: {=IFERROR(INDEX('Bank Schedule'!N:N, SMALL(IF('Bank Schedule'!$K$2:$K$825="Vacant", ROW('Bank Schedule'!$K$2:$K$825)), ROW(14:14))), "")} | O17: {=IFERROR(INDEX('Bank Schedule'!O:O, SMALL(IF('Bank Schedule'!$K$2:$K$825="Vacant", ROW('Bank Schedule'!$K$2:$K$825)), ROW(14:14))), "")} | P17: {=IFERROR(INDEX('Bank Schedule'!P:P, SMALL(IF('Bank Schedule'!$K$2:$K$825="Vacant", ROW('Bank Schedule'!$K$2:$K$825)), ROW(14:14))), "")} | Q17: {=IFERROR(INDEX('Bank Schedule'!Q:Q, SMALL(IF('Bank Schedule'!$K$2:$K$825="Vacant", ROW('Bank Schedule'!$K$2:$K$825)), ROW(14:14))), "")} | R17: {=IFERROR(INDEX('Bank Schedule'!R:R, SMALL(IF('Bank Schedule'!$K$2:$K$825="Vacant", ROW('Bank Schedule'!$K$2:$K$825)), ROW(14:14))), "")} | S17: {=IFERROR(INDEX('Bank Schedule'!S:S, SMALL(IF('Bank Schedule'!$K$2:$K$825="Vacant", ROW('Bank Schedule'!$K$2:$K$825)), ROW(14:14))), "")} | T17: {=IFERROR(INDEX('Bank Schedule'!T:T, SMALL(IF('Bank Schedule'!$K$2:$K$825="Vacant", ROW('Bank Schedule'!$K$2:$K$825)), ROW(14:14))), "")} | U17: {=IFERROR(INDEX('Bank Schedule'!U:U, SMALL(IF('Bank Schedule'!$K$2:$K$825="Vacant", ROW('Bank Schedule'!$K$2:$K$825)), ROW(14:14))), "")} | V17: {=IFERROR(INDEX('Bank Schedule'!V:V, SMALL(IF('Bank Schedule'!$K$2:$K$825="Vacant", ROW('Bank Schedule'!$K$2:$K$825)), ROW(14:14))), "")} | W17: {=IFERROR(INDEX('Bank Schedule'!W:W, SMALL(IF('Bank Schedule'!$K$2:$K$825="Vacant", ROW('Bank Schedule'!$K$2:$K$825)), ROW(14:14))), "")} | X17: {=IFERROR(INDEX('Bank Schedule'!X:X, SMALL(IF('Bank Schedule'!$K$2:$K$825="Vacant", ROW('Bank Schedule'!$K$2:$K$825)), ROW(14:14))), "")} | Y17: {=IFERROR(INDEX('Bank Schedule'!Y:Y, SMALL(IF('Bank Schedule'!$K$2:$K$825="Vacant", ROW('Bank Schedule'!$K$2:$K$825)), ROW(14:14))), "")} | Z17: {=IFERROR(INDEX('Bank Schedule'!Z:Z, SMALL(IF('Bank Schedule'!$K$2:$K$825="Vacant", ROW('Bank Schedule'!$K$2:$K$825)), ROW(14:14))), "")} | AA17: {=IFERROR(INDEX('Bank Schedule'!AA:AA, SMALL(IF('Bank Schedule'!$K$2:$K$825="Vacant", ROW('Bank Schedule'!$K$2:$K$825)), ROW(14:14))), "")} | AB17: {=IFERROR(INDEX('Bank Schedule'!AB:AB, SMALL(IF('Bank Schedule'!$K$2:$K$825="Vacant", ROW('Bank Schedule'!$K$2:$K$825)), ROW(14:14))), "")} | AC17: {=IFERROR(INDEX('Bank Schedule'!AC:AC, SMALL(IF('Bank Schedule'!$K$2:$K$825="Vacant", ROW('Bank Schedule'!$K$2:$K$825)), ROW(14:14))), "")} | AD17: {=IFERROR(INDEX('Bank Schedule'!AD:AD, SMALL(IF('Bank Schedule'!$K$2:$K$825="Vacant", ROW('Bank Schedule'!$K$2:$K$825)), ROW(14:14))), "")} | AE17: {=IFERROR(INDEX('Bank Schedule'!AE:AE, SMALL(IF('Bank Schedule'!$K$2:$K$825="Vacant", ROW('Bank Schedule'!$K$2:$K$825)), ROW(14:14))), "")} | AF17: {=IFERROR(INDEX('Bank Schedule'!AF:AF, SMALL(IF('Bank Schedule'!$K$2:$K$825="Vacant", ROW('Bank Schedule'!$K$2:$K$825)), ROW(14:14))), "")} | AG17: {=IFERROR(INDEX('Bank Schedule'!AG:AG, SMALL(IF('Bank Schedule'!$K$2:$K$825="Vacant", ROW('Bank Schedule'!$K$2:$K$825)), ROW(14:14))), "")} | AH17: {=IFERROR(INDEX('Bank Schedule'!AH:AH, SMALL(IF('Bank Schedule'!$K$2:$K$825="Vacant", ROW('Bank Schedule'!$K$2:$K$825)), ROW(14:14))), "")}
A18: {=IFERROR(INDEX('Bank Schedule'!A:A, SMALL(IF('Bank Schedule'!$K$2:$K$825="Vacant", ROW('Bank Schedule'!$K$2:$K$825)), ROW(15:15))), "")} | B18: {=IFERROR(INDEX('Bank Schedule'!B:B, SMALL(IF('Bank Schedule'!$K$2:$K$825="Vacant", ROW('Bank Schedule'!$K$2:$K$825)), ROW(15:15))), "")} | C18: {=IFERROR(INDEX('Bank Schedule'!C:C, SMALL(IF('Bank Schedule'!$K$2:$K$825="Vacant", ROW('Bank Schedule'!$K$2:$K$825)), ROW(15:15))), "")} | D18: {=IFERROR(INDEX('Bank Schedule'!D:D, SMALL(IF('Bank Schedule'!$K$2:$K$825="Vacant", ROW('Bank Schedule'!$K$2:$K$825)), ROW(15:15))), "")} | E18: {=IFERROR(INDEX('Bank Schedule'!E:E, SMALL(IF('Bank Schedule'!$K$2:$K$825="Vacant", ROW('Bank Schedule'!$K$2:$K$825)), ROW(15:15))), "")} | F18: {=IFERROR(INDEX('Bank Schedule'!F:F, SMALL(IF('Bank Schedule'!$K$2:$K$825="Vacant", ROW('Bank Schedule'!$K$2:$K$825)), ROW(15:15))), "")} | G18: {=IFERROR(INDEX('Bank Schedule'!G:G, SMALL(IF('Bank Schedule'!$K$2:$K$825="Vacant", ROW('Bank Schedule'!$K$2:$K$825)), ROW(15:15))), "")} | H18: {=IFERROR(INDEX('Bank Schedule'!H:H, SMALL(IF('Bank Schedule'!$K$2:$K$825="Vacant", ROW('Bank Schedule'!$K$2:$K$825)), ROW(15:15))), "")} | I18: {=IFERROR(INDEX('Bank Schedule'!I:I, SMALL(IF('Bank Schedule'!$K$2:$K$825="Vacant", ROW('Bank Schedule'!$K$2:$K$825)), ROW(15:15))), "")} | J18: {=IFERROR(INDEX('Bank Schedule'!J:J, SMALL(IF('Bank Schedule'!$K$2:$K$825="Vacant", ROW('Bank Schedule'!$K$2:$K$825)), ROW(15:15))), "")} | K18: {=IFERROR(INDEX('Bank Schedule'!K:K, SMALL(IF('Bank Schedule'!$K$2:$K$825="Vacant", ROW('Bank Schedule'!$K$2:$K$825)), ROW(15:15))), "")} | L18: {=IFERROR(INDEX('Bank Schedule'!L:L, SMALL(IF('Bank Schedule'!$K$2:$K$825="Vacant", ROW('Bank Schedule'!$K$2:$K$825)), ROW(15:15))), "")} | M18: {=IFERROR(INDEX('Bank Schedule'!M:M, SMALL(IF('Bank Schedule'!$K$2:$K$825="Vacant", ROW('Bank Schedule'!$K$2:$K$825)), ROW(15:15))), "")} | N18: {=IFERROR(INDEX('Bank Schedule'!N:N, SMALL(IF('Bank Schedule'!$K$2:$K$825="Vacant", ROW('Bank Schedule'!$K$2:$K$825)), ROW(15:15))), "")} | O18: {=IFERROR(INDEX('Bank Schedule'!O:O, SMALL(IF('Bank Schedule'!$K$2:$K$825="Vacant", ROW('Bank Schedule'!$K$2:$K$825)), ROW(15:15))), "")} | P18: {=IFERROR(INDEX('Bank Schedule'!P:P, SMALL(IF('Bank Schedule'!$K$2:$K$825="Vacant", ROW('Bank Schedule'!$K$2:$K$825)), ROW(15:15))), "")} | Q18: {=IFERROR(INDEX('Bank Schedule'!Q:Q, SMALL(IF('Bank Schedule'!$K$2:$K$825="Vacant", ROW('Bank Schedule'!$K$2:$K$825)), ROW(15:15))), "")} | R18: {=IFERROR(INDEX('Bank Schedule'!R:R, SMALL(IF('Bank Schedule'!$K$2:$K$825="Vacant", ROW('Bank Schedule'!$K$2:$K$825)), ROW(15:15))), "")} | S18: {=IFERROR(INDEX('Bank Schedule'!S:S, SMALL(IF('Bank Schedule'!$K$2:$K$825="Vacant", ROW('Bank Schedule'!$K$2:$K$825)), ROW(15:15))), "")} | T18: {=IFERROR(INDEX('Bank Schedule'!T:T, SMALL(IF('Bank Schedule'!$K$2:$K$825="Vacant", ROW('Bank Schedule'!$K$2:$K$825)), ROW(15:15))), "")} | U18: {=IFERROR(INDEX('Bank Schedule'!U:U, SMALL(IF('Bank Schedule'!$K$2:$K$825="Vacant", ROW('Bank Schedule'!$K$2:$K$825)), ROW(15:15))), "")} | V18: {=IFERROR(INDEX('Bank Schedule'!V:V, SMALL(IF('Bank Schedule'!$K$2:$K$825="Vacant", ROW('Bank Schedule'!$K$2:$K$825)), ROW(15:15))), "")} | W18: {=IFERROR(INDEX('Bank Schedule'!W:W, SMALL(IF('Bank Schedule'!$K$2:$K$825="Vacant", ROW('Bank Schedule'!$K$2:$K$825)), ROW(15:15))), "")} | X18: {=IFERROR(INDEX('Bank Schedule'!X:X, SMALL(IF('Bank Schedule'!$K$2:$K$825="Vacant", ROW('Bank Schedule'!$K$2:$K$825)), ROW(15:15))), "")} | Y18: {=IFERROR(INDEX('Bank Schedule'!Y:Y, SMALL(IF('Bank Schedule'!$K$2:$K$825="Vacant", ROW('Bank Schedule'!$K$2:$K$825)), ROW(15:15))), "")} | Z18: {=IFERROR(INDEX('Bank Schedule'!Z:Z, SMALL(IF('Bank Schedule'!$K$2:$K$825="Vacant", ROW('Bank Schedule'!$K$2:$K$825)), ROW(15:15))), "")} | AA18: {=IFERROR(INDEX('Bank Schedule'!AA:AA, SMALL(IF('Bank Schedule'!$K$2:$K$825="Vacant", ROW('Bank Schedule'!$K$2:$K$825)), ROW(15:15))), "")} | AB18: {=IFERROR(INDEX('Bank Schedule'!AB:AB, SMALL(IF('Bank Schedule'!$K$2:$K$825="Vacant", ROW('Bank Schedule'!$K$2:$K$825)), ROW(15:15))), "")} | AC18: {=IFERROR(INDEX('Bank Schedule'!AC:AC, SMALL(IF('Bank Schedule'!$K$2:$K$825="Vacant", ROW('Bank Schedule'!$K$2:$K$825)), ROW(15:15))), "")} | AD18: {=IFERROR(INDEX('Bank Schedule'!AD:AD, SMALL(IF('Bank Schedule'!$K$2:$K$825="Vacant", ROW('Bank Schedule'!$K$2:$K$825)), ROW(15:15))), "")} | AE18: {=IFERROR(INDEX('Bank Schedule'!AE:AE, SMALL(IF('Bank Schedule'!$K$2:$K$825="Vacant", ROW('Bank Schedule'!$K$2:$K$825)), ROW(15:15))), "")} | AF18: {=IFERROR(INDEX('Bank Schedule'!AF:AF, SMALL(IF('Bank Schedule'!$K$2:$K$825="Vacant", ROW('Bank Schedule'!$K$2:$K$825)), ROW(15:15))), "")} | AG18: {=IFERROR(INDEX('Bank Schedule'!AG:AG, SMALL(IF('Bank Schedule'!$K$2:$K$825="Vacant", ROW('Bank Schedule'!$K$2:$K$825)), ROW(15:15))), "")} | AH18: {=IFERROR(INDEX('Bank Schedule'!AH:AH, SMALL(IF('Bank Schedule'!$K$2:$K$825="Vacant", ROW('Bank Schedule'!$K$2:$K$825)), ROW(15:15))), "")}
A19: {=IFERROR(INDEX('Bank Schedule'!A:A, SMALL(IF('Bank Schedule'!$K$2:$K$825="Vacant", ROW('Bank Schedule'!$K$2:$K$825)), ROW(16:16))), "")} | B19: {=IFERROR(INDEX('Bank Schedule'!B:B, SMALL(IF('Bank Schedule'!$K$2:$K$825="Vacant", ROW('Bank Schedule'!$K$2:$K$825)), ROW(16:16))), "")} | C19: {=IFERROR(INDEX('Bank Schedule'!C:C, SMALL(IF('Bank Schedule'!$K$2:$K$825="Vacant", ROW('Bank Schedule'!$K$2:$K$825)), ROW(16:16))), "")} | D19: {=IFERROR(INDEX('Bank Schedule'!D:D, SMALL(IF('Bank Schedule'!$K$2:$K$825="Vacant", ROW('Bank Schedule'!$K$2:$K$825)), ROW(16:16))), "")} | E19: {=IFERROR(INDEX('Bank Schedule'!E:E, SMALL(IF('Bank Schedule'!$K$2:$K$825="Vacant", ROW('Bank Schedule'!$K$2:$K$825)), ROW(16:16))), "")} | F19: {=IFERROR(INDEX('Bank Schedule'!F:F, SMALL(IF('Bank Schedule'!$K$2:$K$825="Vacant", ROW('Bank Schedule'!$K$2:$K$825)), ROW(16:16))), "")} | G19: {=IFERROR(INDEX('Bank Schedule'!G:G, SMALL(IF('Bank Schedule'!$K$2:$K$825="Vacant", ROW('Bank Schedule'!$K$2:$K$825)), ROW(16:16))), "")} | H19: {=IFERROR(INDEX('Bank Schedule'!H:H, SMALL(IF('Bank Schedule'!$K$2:$K$825="Vacant", ROW('Bank Schedule'!$K$2:$K$825)), ROW(16:16))), "")} | I19: {=IFERROR(INDEX('Bank Schedule'!I:I, SMALL(IF('Bank Schedule'!$K$2:$K$825="Vacant", ROW('Bank Schedule'!$K$2:$K$825)), ROW(16:16))), "")} | J19: {=IFERROR(INDEX('Bank Schedule'!J:J, SMALL(IF('Bank Schedule'!$K$2:$K$825="Vacant", ROW('Bank Schedule'!$K$2:$K$825)), ROW(16:16))), "")} | K19: {=IFERROR(INDEX('Bank Schedule'!K:K, SMALL(IF('Bank Schedule'!$K$2:$K$825="Vacant", ROW('Bank Schedule'!$K$2:$K$825)), ROW(16:16))), "")} | L19: {=IFERROR(INDEX('Bank Schedule'!L:L, SMALL(IF('Bank Schedule'!$K$2:$K$825="Vacant", ROW('Bank Schedule'!$K$2:$K$825)), ROW(16:16))), "")} | M19: {=IFERROR(INDEX('Bank Schedule'!M:M, SMALL(IF('Bank Schedule'!$K$2:$K$825="Vacant", ROW('Bank Schedule'!$K$2:$K$825)), ROW(16:16))), "")} | N19: {=IFERROR(INDEX('Bank Schedule'!N:N, SMALL(IF('Bank Schedule'!$K$2:$K$825="Vacant", ROW('Bank Schedule'!$K$2:$K$825)), ROW(16:16))), "")} | O19: {=IFERROR(INDEX('Bank Schedule'!O:O, SMALL(IF('Bank Schedule'!$K$2:$K$825="Vacant", ROW('Bank Schedule'!$K$2:$K$825)), ROW(16:16))), "")} | P19: {=IFERROR(INDEX('Bank Schedule'!P:P, SMALL(IF('Bank Schedule'!$K$2:$K$825="Vacant", ROW('Bank Schedule'!$K$2:$K$825)), ROW(16:16))), "")} | Q19: {=IFERROR(INDEX('Bank Schedule'!Q:Q, SMALL(IF('Bank Schedule'!$K$2:$K$825="Vacant", ROW('Bank Schedule'!$K$2:$K$825)), ROW(16:16))), "")} | R19: {=IFERROR(INDEX('Bank Schedule'!R:R, SMALL(IF('Bank Schedule'!$K$2:$K$825="Vacant", ROW('Bank Schedule'!$K$2:$K$825)), ROW(16:16))), "")} | S19: {=IFERROR(INDEX('Bank Schedule'!S:S, SMALL(IF('Bank Schedule'!$K$2:$K$825="Vacant", ROW('Bank Schedule'!$K$2:$K$825)), ROW(16:16))), "")} | T19: {=IFERROR(INDEX('Bank Schedule'!T:T, SMALL(IF('Bank Schedule'!$K$2:$K$825="Vacant", ROW('Bank Schedule'!$K$2:$K$825)), ROW(16:16))), "")} | U19: {=IFERROR(INDEX('Bank Schedule'!U:U, SMALL(IF('Bank Schedule'!$K$2:$K$825="Vacant", ROW('Bank Schedule'!$K$2:$K$825)), ROW(16:16))), "")} | V19: {=IFERROR(INDEX('Bank Schedule'!V:V, SMALL(IF('Bank Schedule'!$K$2:$K$825="Vacant", ROW('Bank Schedule'!$K$2:$K$825)), ROW(16:16))), "")} | W19: {=IFERROR(INDEX('Bank Schedule'!W:W, SMALL(IF('Bank Schedule'!$K$2:$K$825="Vacant", ROW('Bank Schedule'!$K$2:$K$825)), ROW(16:16))), "")} | X19: {=IFERROR(INDEX('Bank Schedule'!X:X, SMALL(IF('Bank Schedule'!$K$2:$K$825="Vacant", ROW('Bank Schedule'!$K$2:$K$825)), ROW(16:16))), "")} | Y19: {=IFERROR(INDEX('Bank Schedule'!Y:Y, SMALL(IF('Bank Schedule'!$K$2:$K$825="Vacant", ROW('Bank Schedule'!$K$2:$K$825)), ROW(16:16))), "")} | Z19: {=IFERROR(INDEX('Bank Schedule'!Z:Z, SMALL(IF('Bank Schedule'!$K$2:$K$825="Vacant", ROW('Bank Schedule'!$K$2:$K$825)), ROW(16:16))), "")} | AA19: {=IFERROR(INDEX('Bank Schedule'!AA:AA, SMALL(IF('Bank Schedule'!$K$2:$K$825="Vacant", ROW('Bank Schedule'!$K$2:$K$825)), ROW(16:16))), "")} | AB19: {=IFERROR(INDEX('Bank Schedule'!AB:AB, SMALL(IF('Bank Schedule'!$K$2:$K$825="Vacant", ROW('Bank Schedule'!$K$2:$K$825)), ROW(16:16))), "")} | AC19: {=IFERROR(INDEX('Bank Schedule'!AC:AC, SMALL(IF('Bank Schedule'!$K$2:$K$825="Vacant", ROW('Bank Schedule'!$K$2:$K$825)), ROW(16:16))), "")} | AD19: {=IFERROR(INDEX('Bank Schedule'!AD:AD, SMALL(IF('Bank Schedule'!$K$2:$K$825="Vacant", ROW('Bank Schedule'!$K$2:$K$825)), ROW(16:16))), "")} | AE19: {=IFERROR(INDEX('Bank Schedule'!AE:AE, SMALL(IF('Bank Schedule'!$K$2:$K$825="Vacant", ROW('Bank Schedule'!$K$2:$K$825)), ROW(16:16))), "")} | AF19: {=IFERROR(INDEX('Bank Schedule'!AF:AF, SMALL(IF('Bank Schedule'!$K$2:$K$825="Vacant", ROW('Bank Schedule'!$K$2:$K$825)), ROW(16:16))), "")} | AG19: {=IFERROR(INDEX('Bank Schedule'!AG:AG, SMALL(IF('Bank Schedule'!$K$2:$K$825="Vacant", ROW('Bank Schedule'!$K$2:$K$825)), ROW(16:16))), "")} | AH19: {=IFERROR(INDEX('Bank Schedule'!AH:AH, SMALL(IF('Bank Schedule'!$K$2:$K$825="Vacant", ROW('Bank Schedule'!$K$2:$K$825)), ROW(16:16))), "")}
A20: {=IFERROR(INDEX('Bank Schedule'!A:A, SMALL(IF('Bank Schedule'!$K$2:$K$825="Vacant", ROW('Bank Schedule'!$K$2:$K$825)), ROW(17:17))), "")} | B20: {=IFERROR(INDEX('Bank Schedule'!B:B, SMALL(IF('Bank Schedule'!$K$2:$K$825="Vacant", ROW('Bank Schedule'!$K$2:$K$825)), ROW(17:17))), "")} | C20: {=IFERROR(INDEX('Bank Schedule'!C:C, SMALL(IF('Bank Schedule'!$K$2:$K$825="Vacant", ROW('Bank Schedule'!$K$2:$K$825)), ROW(17:17))), "")} | D20: {=IFERROR(INDEX('Bank Schedule'!D:D, SMALL(IF('Bank Schedule'!$K$2:$K$825="Vacant", ROW('Bank Schedule'!$K$2:$K$825)), ROW(17:17))), "")} | E20: {=IFERROR(INDEX('Bank Schedule'!E:E, SMALL(IF('Bank Schedule'!$K$2:$K$825="Vacant", ROW('Bank Schedule'!$K$2:$K$825)), ROW(17:17))), "")} | F20: {=IFERROR(INDEX('Bank Schedule'!F:F, SMALL(IF('Bank Schedule'!$K$2:$K$825="Vacant", ROW('Bank Schedule'!$K$2:$K$825)), ROW(17:17))), "")} | G20: {=IFERROR(INDEX('Bank Schedule'!G:G, SMALL(IF('Bank Schedule'!$K$2:$K$825="Vacant", ROW('Bank Schedule'!$K$2:$K$825)), ROW(17:17))), "")} | H20: {=IFERROR(INDEX('Bank Schedule'!H:H, SMALL(IF('Bank Schedule'!$K$2:$K$825="Vacant", ROW('Bank Schedule'!$K$2:$K$825)), ROW(17:17))), "")} | I20: {=IFERROR(INDEX('Bank Schedule'!I:I, SMALL(IF('Bank Schedule'!$K$2:$K$825="Vacant", ROW('Bank Schedule'!$K$2:$K$825)), ROW(17:17))), "")} | J20: {=IFERROR(INDEX('Bank Schedule'!J:J, SMALL(IF('Bank Schedule'!$K$2:$K$825="Vacant", ROW('Bank Schedule'!$K$2:$K$825)), ROW(17:17))), "")} | K20: {=IFERROR(INDEX('Bank Schedule'!K:K, SMALL(IF('Bank Schedule'!$K$2:$K$825="Vacant", ROW('Bank Schedule'!$K$2:$K$825)), ROW(17:17))), "")} | L20: {=IFERROR(INDEX('Bank Schedule'!L:L, SMALL(IF('Bank Schedule'!$K$2:$K$825="Vacant", ROW('Bank Schedule'!$K$2:$K$825)), ROW(17:17))), "")} | M20: {=IFERROR(INDEX('Bank Schedule'!M:M, SMALL(IF('Bank Schedule'!$K$2:$K$825="Vacant", ROW('Bank Schedule'!$K$2:$K$825)), ROW(17:17))), "")} | N20: {=IFERROR(INDEX('Bank Schedule'!N:N, SMALL(IF('Bank Schedule'!$K$2:$K$825="Vacant", ROW('Bank Schedule'!$K$2:$K$825)), ROW(17:17))), "")} | O20: {=IFERROR(INDEX('Bank Schedule'!O:O, SMALL(IF('Bank Schedule'!$K$2:$K$825="Vacant", ROW('Bank Schedule'!$K$2:$K$825)), ROW(17:17))), "")} | P20: {=IFERROR(INDEX('Bank Schedule'!P:P, SMALL(IF('Bank Schedule'!$K$2:$K$825="Vacant", ROW('Bank Schedule'!$K$2:$K$825)), ROW(17:17))), "")} | Q20: {=IFERROR(INDEX('Bank Schedule'!Q:Q, SMALL(IF('Bank Schedule'!$K$2:$K$825="Vacant", ROW('Bank Schedule'!$K$2:$K$825)), ROW(17:17))), "")} | R20: {=IFERROR(INDEX('Bank Schedule'!R:R, SMALL(IF('Bank Schedule'!$K$2:$K$825="Vacant", ROW('Bank Schedule'!$K$2:$K$825)), ROW(17:17))), "")} | S20: {=IFERROR(INDEX('Bank Schedule'!S:S, SMALL(IF('Bank Schedule'!$K$2:$K$825="Vacant", ROW('Bank Schedule'!$K$2:$K$825)), ROW(17:17))), "")} | T20: {=IFERROR(INDEX('Bank Schedule'!T:T, SMALL(IF('Bank Schedule'!$K$2:$K$825="Vacant", ROW('Bank Schedule'!$K$2:$K$825)), ROW(17:17))), "")} | U20: {=IFERROR(INDEX('Bank Schedule'!U:U, SMALL(IF('Bank Schedule'!$K$2:$K$825="Vacant", ROW('Bank Schedule'!$K$2:$K$825)), ROW(17:17))), "")} | V20: {=IFERROR(INDEX('Bank Schedule'!V:V, SMALL(IF('Bank Schedule'!$K$2:$K$825="Vacant", ROW('Bank Schedule'!$K$2:$K$825)), ROW(17:17))), "")} | W20: {=IFERROR(INDEX('Bank Schedule'!W:W, SMALL(IF('Bank Schedule'!$K$2:$K$825="Vacant", ROW('Bank Schedule'!$K$2:$K$825)), ROW(17:17))), "")} | X20: {=IFERROR(INDEX('Bank Schedule'!X:X, SMALL(IF('Bank Schedule'!$K$2:$K$825="Vacant", ROW('Bank Schedule'!$K$2:$K$825)), ROW(17:17))), "")} | Y20: {=IFERROR(INDEX('Bank Schedule'!Y:Y, SMALL(IF('Bank Schedule'!$K$2:$K$825="Vacant", ROW('Bank Schedule'!$K$2:$K$825)), ROW(17:17))), "")} | Z20: {=IFERROR(INDEX('Bank Schedule'!Z:Z, SMALL(IF('Bank Schedule'!$K$2:$K$825="Vacant", ROW('Bank Schedule'!$K$2:$K$825)), ROW(17:17))), "")} | AA20: {=IFERROR(INDEX('Bank Schedule'!AA:AA, SMALL(IF('Bank Schedule'!$K$2:$K$825="Vacant", ROW('Bank Schedule'!$K$2:$K$825)), ROW(17:17))), "")} | AB20: {=IFERROR(INDEX('Bank Schedule'!AB:AB, SMALL(IF('Bank Schedule'!$K$2:$K$825="Vacant", ROW('Bank Schedule'!$K$2:$K$825)), ROW(17:17))), "")} | AC20: {=IFERROR(INDEX('Bank Schedule'!AC:AC, SMALL(IF('Bank Schedule'!$K$2:$K$825="Vacant", ROW('Bank Schedule'!$K$2:$K$825)), ROW(17:17))), "")} | AD20: {=IFERROR(INDEX('Bank Schedule'!AD:AD, SMALL(IF('Bank Schedule'!$K$2:$K$825="Vacant", ROW('Bank Schedule'!$K$2:$K$825)), ROW(17:17))), "")} | AE20: {=IFERROR(INDEX('Bank Schedule'!AE:AE, SMALL(IF('Bank Schedule'!$K$2:$K$825="Vacant", ROW('Bank Schedule'!$K$2:$K$825)), ROW(17:17))), "")} | AF20: {=IFERROR(INDEX('Bank Schedule'!AF:AF, SMALL(IF('Bank Schedule'!$K$2:$K$825="Vacant", ROW('Bank Schedule'!$K$2:$K$825)), ROW(17:17))), "")} | AG20: {=IFERROR(INDEX('Bank Schedule'!AG:AG, SMALL(IF('Bank Schedule'!$K$2:$K$825="Vacant", ROW('Bank Schedule'!$K$2:$K$825)), ROW(17:17))), "")} | AH20: {=IFERROR(INDEX('Bank Schedule'!AH:AH, SMALL(IF('Bank Schedule'!$K$2:$K$825="Vacant", ROW('Bank Schedule'!$K$2:$K$825)), ROW(17:17))), "")}
A21: {=IFERROR(INDEX('Bank Schedule'!A:A, SMALL(IF('Bank Schedule'!$K$2:$K$825="Vacant", ROW('Bank Schedule'!$K$2:$K$825)), ROW(18:18))), "")} | B21: {=IFERROR(INDEX('Bank Schedule'!B:B, SMALL(IF('Bank Schedule'!$K$2:$K$825="Vacant", ROW('Bank Schedule'!$K$2:$K$825)), ROW(18:18))), "")} | C21: {=IFERROR(INDEX('Bank Schedule'!C:C, SMALL(IF('Bank Schedule'!$K$2:$K$825="Vacant", ROW('Bank Schedule'!$K$2:$K$825)), ROW(18:18))), "")} | D21: {=IFERROR(INDEX('Bank Schedule'!D:D, SMALL(IF('Bank Schedule'!$K$2:$K$825="Vacant", ROW('Bank Schedule'!$K$2:$K$825)), ROW(18:18))), "")} | E21: {=IFERROR(INDEX('Bank Schedule'!E:E, SMALL(IF('Bank Schedule'!$K$2:$K$825="Vacant", ROW('Bank Schedule'!$K$2:$K$825)), ROW(18:18))), "")} | F21: {=IFERROR(INDEX('Bank Schedule'!F:F, SMALL(IF('Bank Schedule'!$K$2:$K$825="Vacant", ROW('Bank Schedule'!$K$2:$K$825)), ROW(18:18))), "")} | G21: {=IFERROR(INDEX('Bank Schedule'!G:G, SMALL(IF('Bank Schedule'!$K$2:$K$825="Vacant", ROW('Bank Schedule'!$K$2:$K$825)), ROW(18:18))), "")} | H21: {=IFERROR(INDEX('Bank Schedule'!H:H, SMALL(IF('Bank Schedule'!$K$2:$K$825="Vacant", ROW('Bank Schedule'!$K$2:$K$825)), ROW(18:18))), "")} | I21: {=IFERROR(INDEX('Bank Schedule'!I:I, SMALL(IF('Bank Schedule'!$K$2:$K$825="Vacant", ROW('Bank Schedule'!$K$2:$K$825)), ROW(18:18))), "")} | J21: {=IFERROR(INDEX('Bank Schedule'!J:J, SMALL(IF('Bank Schedule'!$K$2:$K$825="Vacant", ROW('Bank Schedule'!$K$2:$K$825)), ROW(18:18))), "")} | K21: {=IFERROR(INDEX('Bank Schedule'!K:K, SMALL(IF('Bank Schedule'!$K$2:$K$825="Vacant", ROW('Bank Schedule'!$K$2:$K$825)), ROW(18:18))), "")} | L21: {=IFERROR(INDEX('Bank Schedule'!L:L, SMALL(IF('Bank Schedule'!$K$2:$K$825="Vacant", ROW('Bank Schedule'!$K$2:$K$825)), ROW(18:18))), "")} | M21: {=IFERROR(INDEX('Bank Schedule'!M:M, SMALL(IF('Bank Schedule'!$K$2:$K$825="Vacant", ROW('Bank Schedule'!$K$2:$K$825)), ROW(18:18))), "")} | N21: {=IFERROR(INDEX('Bank Schedule'!N:N, SMALL(IF('Bank Schedule'!$K$2:$K$825="Vacant", ROW('Bank Schedule'!$K$2:$K$825)), ROW(18:18))), "")} | O21: {=IFERROR(INDEX('Bank Schedule'!O:O, SMALL(IF('Bank Schedule'!$K$2:$K$825="Vacant", ROW('Bank Schedule'!$K$2:$K$825)), ROW(18:18))), "")} | P21: {=IFERROR(INDEX('Bank Schedule'!P:P, SMALL(IF('Bank Schedule'!$K$2:$K$825="Vacant", ROW('Bank Schedule'!$K$2:$K$825)), ROW(18:18))), "")} | Q21: {=IFERROR(INDEX('Bank Schedule'!Q:Q, SMALL(IF('Bank Schedule'!$K$2:$K$825="Vacant", ROW('Bank Schedule'!$K$2:$K$825)), ROW(18:18))), "")} | R21: {=IFERROR(INDEX('Bank Schedule'!R:R, SMALL(IF('Bank Schedule'!$K$2:$K$825="Vacant", ROW('Bank Schedule'!$K$2:$K$825)), ROW(18:18))), "")} | S21: {=IFERROR(INDEX('Bank Schedule'!S:S, SMALL(IF('Bank Schedule'!$K$2:$K$825="Vacant", ROW('Bank Schedule'!$K$2:$K$825)), ROW(18:18))), "")} | T21: {=IFERROR(INDEX('Bank Schedule'!T:T, SMALL(IF('Bank Schedule'!$K$2:$K$825="Vacant", ROW('Bank Schedule'!$K$2:$K$825)), ROW(18:18))), "")} | U21: {=IFERROR(INDEX('Bank Schedule'!U:U, SMALL(IF('Bank Schedule'!$K$2:$K$825="Vacant", ROW('Bank Schedule'!$K$2:$K$825)), ROW(18:18))), "")} | V21: {=IFERROR(INDEX('Bank Schedule'!V:V, SMALL(IF('Bank Schedule'!$K$2:$K$825="Vacant", ROW('Bank Schedule'!$K$2:$K$825)), ROW(18:18))), "")} | W21: {=IFERROR(INDEX('Bank Schedule'!W:W, SMALL(IF('Bank Schedule'!$K$2:$K$825="Vacant", ROW('Bank Schedule'!$K$2:$K$825)), ROW(18:18))), "")} | X21: {=IFERROR(INDEX('Bank Schedule'!X:X, SMALL(IF('Bank Schedule'!$K$2:$K$825="Vacant", ROW('Bank Schedule'!$K$2:$K$825)), ROW(18:18))), "")} | Y21: {=IFERROR(INDEX('Bank Schedule'!Y:Y, SMALL(IF('Bank Schedule'!$K$2:$K$825="Vacant", ROW('Bank Schedule'!$K$2:$K$825)), ROW(18:18))), "")} | Z21: {=IFERROR(INDEX('Bank Schedule'!Z:Z, SMALL(IF('Bank Schedule'!$K$2:$K$825="Vacant", ROW('Bank Schedule'!$K$2:$K$825)), ROW(18:18))), "")} | AA21: {=IFERROR(INDEX('Bank Schedule'!AA:AA, SMALL(IF('Bank Schedule'!$K$2:$K$825="Vacant", ROW('Bank Schedule'!$K$2:$K$825)), ROW(18:18))), "")} | AB21: {=IFERROR(INDEX('Bank Schedule'!AB:AB, SMALL(IF('Bank Schedule'!$K$2:$K$825="Vacant", ROW('Bank Schedule'!$K$2:$K$825)), ROW(18:18))), "")} | AC21: {=IFERROR(INDEX('Bank Schedule'!AC:AC, SMALL(IF('Bank Schedule'!$K$2:$K$825="Vacant", ROW('Bank Schedule'!$K$2:$K$825)), ROW(18:18))), "")} | AD21: {=IFERROR(INDEX('Bank Schedule'!AD:AD, SMALL(IF('Bank Schedule'!$K$2:$K$825="Vacant", ROW('Bank Schedule'!$K$2:$K$825)), ROW(18:18))), "")} | AE21: {=IFERROR(INDEX('Bank Schedule'!AE:AE, SMALL(IF('Bank Schedule'!$K$2:$K$825="Vacant", ROW('Bank Schedule'!$K$2:$K$825)), ROW(18:18))), "")} | AF21: {=IFERROR(INDEX('Bank Schedule'!AF:AF, SMALL(IF('Bank Schedule'!$K$2:$K$825="Vacant", ROW('Bank Schedule'!$K$2:$K$825)), ROW(18:18))), "")} | AG21: {=IFERROR(INDEX('Bank Schedule'!AG:AG, SMALL(IF('Bank Schedule'!$K$2:$K$825="Vacant", ROW('Bank Schedule'!$K$2:$K$825)), ROW(18:18))), "")} | AH21: {=IFERROR(INDEX('Bank Schedule'!AH:AH, SMALL(IF('Bank Schedule'!$K$2:$K$825="Vacant", ROW('Bank Schedule'!$K$2:$K$825)), ROW(18:18))), "")}
A22: {=IFERROR(INDEX('Bank Schedule'!A:A, SMALL(IF('Bank Schedule'!$K$2:$K$825="Vacant", ROW('Bank Schedule'!$K$2:$K$825)), ROW(19:19))), "")} | B22: {=IFERROR(INDEX('Bank Schedule'!B:B, SMALL(IF('Bank Schedule'!$K$2:$K$825="Vacant", ROW('Bank Schedule'!$K$2:$K$825)), ROW(19:19))), "")} | C22: {=IFERROR(INDEX('Bank Schedule'!C:C, SMALL(IF('Bank Schedule'!$K$2:$K$825="Vacant", ROW('Bank Schedule'!$K$2:$K$825)), ROW(19:19))), "")} | D22: {=IFERROR(INDEX('Bank Schedule'!D:D, SMALL(IF('Bank Schedule'!$K$2:$K$825="Vacant", ROW('Bank Schedule'!$K$2:$K$825)), ROW(19:19))), "")} | E22: {=IFERROR(INDEX('Bank Schedule'!E:E, SMALL(IF('Bank Schedule'!$K$2:$K$825="Vacant", ROW('Bank Schedule'!$K$2:$K$825)), ROW(19:19))), "")} | F22: {=IFERROR(INDEX('Bank Schedule'!F:F, SMALL(IF('Bank Schedule'!$K$2:$K$825="Vacant", ROW('Bank Schedule'!$K$2:$K$825)), ROW(19:19))), "")} | G22: {=IFERROR(INDEX('Bank Schedule'!G:G, SMALL(IF('Bank Schedule'!$K$2:$K$825="Vacant", ROW('Bank Schedule'!$K$2:$K$825)), ROW(19:19))), "")} | H22: {=IFERROR(INDEX('Bank Schedule'!H:H, SMALL(IF('Bank Schedule'!$K$2:$K$825="Vacant", ROW('Bank Schedule'!$K$2:$K$825)), ROW(19:19))), "")} | I22: {=IFERROR(INDEX('Bank Schedule'!I:I, SMALL(IF('Bank Schedule'!$K$2:$K$825="Vacant", ROW('Bank Schedule'!$K$2:$K$825)), ROW(19:19))), "")} | J22: {=IFERROR(INDEX('Bank Schedule'!J:J, SMALL(IF('Bank Schedule'!$K$2:$K$825="Vacant", ROW('Bank Schedule'!$K$2:$K$825)), ROW(19:19))), "")} | K22: {=IFERROR(INDEX('Bank Schedule'!K:K, SMALL(IF('Bank Schedule'!$K$2:$K$825="Vacant", ROW('Bank Schedule'!$K$2:$K$825)), ROW(19:19))), "")} | L22: {=IFERROR(INDEX('Bank Schedule'!L:L, SMALL(IF('Bank Schedule'!$K$2:$K$825="Vacant", ROW('Bank Schedule'!$K$2:$K$825)), ROW(19:19))), "")} | M22: {=IFERROR(INDEX('Bank Schedule'!M:M, SMALL(IF('Bank Schedule'!$K$2:$K$825="Vacant", ROW('Bank Schedule'!$K$2:$K$825)), ROW(19:19))), "")} | N22: {=IFERROR(INDEX('Bank Schedule'!N:N, SMALL(IF('Bank Schedule'!$K$2:$K$825="Vacant", ROW('Bank Schedule'!$K$2:$K$825)), ROW(19:19))), "")} | O22: {=IFERROR(INDEX('Bank Schedule'!O:O, SMALL(IF('Bank Schedule'!$K$2:$K$825="Vacant", ROW('Bank Schedule'!$K$2:$K$825)), ROW(19:19))), "")} | P22: {=IFERROR(INDEX('Bank Schedule'!P:P, SMALL(IF('Bank Schedule'!$K$2:$K$825="Vacant", ROW('Bank Schedule'!$K$2:$K$825)), ROW(19:19))), "")} | Q22: {=IFERROR(INDEX('Bank Schedule'!Q:Q, SMALL(IF('Bank Schedule'!$K$2:$K$825="Vacant", ROW('Bank Schedule'!$K$2:$K$825)), ROW(19:19))), "")} | R22: {=IFERROR(INDEX('Bank Schedule'!R:R, SMALL(IF('Bank Schedule'!$K$2:$K$825="Vacant", ROW('Bank Schedule'!$K$2:$K$825)), ROW(19:19))), "")} | S22: {=IFERROR(INDEX('Bank Schedule'!S:S, SMALL(IF('Bank Schedule'!$K$2:$K$825="Vacant", ROW('Bank Schedule'!$K$2:$K$825)), ROW(19:19))), "")} | T22: {=IFERROR(INDEX('Bank Schedule'!T:T, SMALL(IF('Bank Schedule'!$K$2:$K$825="Vacant", ROW('Bank Schedule'!$K$2:$K$825)), ROW(19:19))), "")} | U22: {=IFERROR(INDEX('Bank Schedule'!U:U, SMALL(IF('Bank Schedule'!$K$2:$K$825="Vacant", ROW('Bank Schedule'!$K$2:$K$825)), ROW(19:19))), "")} | V22: {=IFERROR(INDEX('Bank Schedule'!V:V, SMALL(IF('Bank Schedule'!$K$2:$K$825="Vacant", ROW('Bank Schedule'!$K$2:$K$825)), ROW(19:19))), "")} | W22: {=IFERROR(INDEX('Bank Schedule'!W:W, SMALL(IF('Bank Schedule'!$K$2:$K$825="Vacant", ROW('Bank Schedule'!$K$2:$K$825)), ROW(19:19))), "")} | X22: {=IFERROR(INDEX('Bank Schedule'!X:X, SMALL(IF('Bank Schedule'!$K$2:$K$825="Vacant", ROW('Bank Schedule'!$K$2:$K$825)), ROW(19:19))), "")} | Y22: {=IFERROR(INDEX('Bank Schedule'!Y:Y, SMALL(IF('Bank Schedule'!$K$2:$K$825="Vacant", ROW('Bank Schedule'!$K$2:$K$825)), ROW(19:19))), "")} | Z22: {=IFERROR(INDEX('Bank Schedule'!Z:Z, SMALL(IF('Bank Schedule'!$K$2:$K$825="Vacant", ROW('Bank Schedule'!$K$2:$K$825)), ROW(19:19))), "")} | AA22: {=IFERROR(INDEX('Bank Schedule'!AA:AA, SMALL(IF('Bank Schedule'!$K$2:$K$825="Vacant", ROW('Bank Schedule'!$K$2:$K$825)), ROW(19:19))), "")} | AB22: {=IFERROR(INDEX('Bank Schedule'!AB:AB, SMALL(IF('Bank Schedule'!$K$2:$K$825="Vacant", ROW('Bank Schedule'!$K$2:$K$825)), ROW(19:19))), "")} | AC22: {=IFERROR(INDEX('Bank Schedule'!AC:AC, SMALL(IF('Bank Schedule'!$K$2:$K$825="Vacant", ROW('Bank Schedule'!$K$2:$K$825)), ROW(19:19))), "")} | AD22: {=IFERROR(INDEX('Bank Schedule'!AD:AD, SMALL(IF('Bank Schedule'!$K$2:$K$825="Vacant", ROW('Bank Schedule'!$K$2:$K$825)), ROW(19:19))), "")} | AE22: {=IFERROR(INDEX('Bank Schedule'!AE:AE, SMALL(IF('Bank Schedule'!$K$2:$K$825="Vacant", ROW('Bank Schedule'!$K$2:$K$825)), ROW(19:19))), "")} | AF22: {=IFERROR(INDEX('Bank Schedule'!AF:AF, SMALL(IF('Bank Schedule'!$K$2:$K$825="Vacant", ROW('Bank Schedule'!$K$2:$K$825)), ROW(19:19))), "")} | AG22: {=IFERROR(INDEX('Bank Schedule'!AG:AG, SMALL(IF('Bank Schedule'!$K$2:$K$825="Vacant", ROW('Bank Schedule'!$K$2:$K$825)), ROW(19:19))), "")} | AH22: {=IFERROR(INDEX('Bank Schedule'!AH:AH, SMALL(IF('Bank Schedule'!$K$2:$K$825="Vacant", ROW('Bank Schedule'!$K$2:$K$825)), ROW(19:19))), "")}
A23: {=IFERROR(INDEX('Bank Schedule'!A:A, SMALL(IF('Bank Schedule'!$K$2:$K$825="Vacant", ROW('Bank Schedule'!$K$2:$K$825)), ROW(20:20))), "")} | B23: {=IFERROR(INDEX('Bank Schedule'!B:B, SMALL(IF('Bank Schedule'!$K$2:$K$825="Vacant", ROW('Bank Schedule'!$K$2:$K$825)), ROW(20:20))), "")} | C23: {=IFERROR(INDEX('Bank Schedule'!C:C, SMALL(IF('Bank Schedule'!$K$2:$K$825="Vacant", ROW('Bank Schedule'!$K$2:$K$825)), ROW(20:20))), "")} | D23: {=IFERROR(INDEX('Bank Schedule'!D:D, SMALL(IF('Bank Schedule'!$K$2:$K$825="Vacant", ROW('Bank Schedule'!$K$2:$K$825)), ROW(20:20))), "")} | E23: {=IFERROR(INDEX('Bank Schedule'!E:E, SMALL(IF('Bank Schedule'!$K$2:$K$825="Vacant", ROW('Bank Schedule'!$K$2:$K$825)), ROW(20:20))), "")} | F23: {=IFERROR(INDEX('Bank Schedule'!F:F, SMALL(IF('Bank Schedule'!$K$2:$K$825="Vacant", ROW('Bank Schedule'!$K$2:$K$825)), ROW(20:20))), "")} | G23: {=IFERROR(INDEX('Bank Schedule'!G:G, SMALL(IF('Bank Schedule'!$K$2:$K$825="Vacant", ROW('Bank Schedule'!$K$2:$K$825)), ROW(20:20))), "")} | H23: {=IFERROR(INDEX('Bank Schedule'!H:H, SMALL(IF('Bank Schedule'!$K$2:$K$825="Vacant", ROW('Bank Schedule'!$K$2:$K$825)), ROW(20:20))), "")} | I23: {=IFERROR(INDEX('Bank Schedule'!I:I, SMALL(IF('Bank Schedule'!$K$2:$K$825="Vacant", ROW('Bank Schedule'!$K$2:$K$825)), ROW(20:20))), "")} | J23: {=IFERROR(INDEX('Bank Schedule'!J:J, SMALL(IF('Bank Schedule'!$K$2:$K$825="Vacant", ROW('Bank Schedule'!$K$2:$K$825)), ROW(20:20))), "")} | K23: {=IFERROR(INDEX('Bank Schedule'!K:K, SMALL(IF('Bank Schedule'!$K$2:$K$825="Vacant", ROW('Bank Schedule'!$K$2:$K$825)), ROW(20:20))), "")} | L23: {=IFERROR(INDEX('Bank Schedule'!L:L, SMALL(IF('Bank Schedule'!$K$2:$K$825="Vacant", ROW('Bank Schedule'!$K$2:$K$825)), ROW(20:20))), "")} | M23: {=IFERROR(INDEX('Bank Schedule'!M:M, SMALL(IF('Bank Schedule'!$K$2:$K$825="Vacant", ROW('Bank Schedule'!$K$2:$K$825)), ROW(20:20))), "")} | N23: {=IFERROR(INDEX('Bank Schedule'!N:N, SMALL(IF('Bank Schedule'!$K$2:$K$825="Vacant", ROW('Bank Schedule'!$K$2:$K$825)), ROW(20:20))), "")} | O23: {=IFERROR(INDEX('Bank Schedule'!O:O, SMALL(IF('Bank Schedule'!$K$2:$K$825="Vacant", ROW('Bank Schedule'!$K$2:$K$825)), ROW(20:20))), "")} | P23: {=IFERROR(INDEX('Bank Schedule'!P:P, SMALL(IF('Bank Schedule'!$K$2:$K$825="Vacant", ROW('Bank Schedule'!$K$2:$K$825)), ROW(20:20))), "")} | Q23: {=IFERROR(INDEX('Bank Schedule'!Q:Q, SMALL(IF('Bank Schedule'!$K$2:$K$825="Vacant", ROW('Bank Schedule'!$K$2:$K$825)), ROW(20:20))), "")} | R23: {=IFERROR(INDEX('Bank Schedule'!R:R, SMALL(IF('Bank Schedule'!$K$2:$K$825="Vacant", ROW('Bank Schedule'!$K$2:$K$825)), ROW(20:20))), "")} | S23: {=IFERROR(INDEX('Bank Schedule'!S:S, SMALL(IF('Bank Schedule'!$K$2:$K$825="Vacant", ROW('Bank Schedule'!$K$2:$K$825)), ROW(20:20))), "")} | T23: {=IFERROR(INDEX('Bank Schedule'!T:T, SMALL(IF('Bank Schedule'!$K$2:$K$825="Vacant", ROW('Bank Schedule'!$K$2:$K$825)), ROW(20:20))), "")} | U23: {=IFERROR(INDEX('Bank Schedule'!U:U, SMALL(IF('Bank Schedule'!$K$2:$K$825="Vacant", ROW('Bank Schedule'!$K$2:$K$825)), ROW(20:20))), "")} | V23: {=IFERROR(INDEX('Bank Schedule'!V:V, SMALL(IF('Bank Schedule'!$K$2:$K$825="Vacant", ROW('Bank Schedule'!$K$2:$K$825)), ROW(20:20))), "")} | W23: {=IFERROR(INDEX('Bank Schedule'!W:W, SMALL(IF('Bank Schedule'!$K$2:$K$825="Vacant", ROW('Bank Schedule'!$K$2:$K$825)), ROW(20:20))), "")} | X23: {=IFERROR(INDEX('Bank Schedule'!X:X, SMALL(IF('Bank Schedule'!$K$2:$K$825="Vacant", ROW('Bank Schedule'!$K$2:$K$825)), ROW(20:20))), "")} | Y23: {=IFERROR(INDEX('Bank Schedule'!Y:Y, SMALL(IF('Bank Schedule'!$K$2:$K$825="Vacant", ROW('Bank Schedule'!$K$2:$K$825)), ROW(20:20))), "")} | Z23: {=IFERROR(INDEX('Bank Schedule'!Z:Z, SMALL(IF('Bank Schedule'!$K$2:$K$825="Vacant", ROW('Bank Schedule'!$K$2:$K$825)), ROW(20:20))), "")} | AA23: {=IFERROR(INDEX('Bank Schedule'!AA:AA, SMALL(IF('Bank Schedule'!$K$2:$K$825="Vacant", ROW('Bank Schedule'!$K$2:$K$825)), ROW(20:20))), "")} | AB23: {=IFERROR(INDEX('Bank Schedule'!AB:AB, SMALL(IF('Bank Schedule'!$K$2:$K$825="Vacant", ROW('Bank Schedule'!$K$2:$K$825)), ROW(20:20))), "")} | AC23: {=IFERROR(INDEX('Bank Schedule'!AC:AC, SMALL(IF('Bank Schedule'!$K$2:$K$825="Vacant", ROW('Bank Schedule'!$K$2:$K$825)), ROW(20:20))), "")} | AD23: {=IFERROR(INDEX('Bank Schedule'!AD:AD, SMALL(IF('Bank Schedule'!$K$2:$K$825="Vacant", ROW('Bank Schedule'!$K$2:$K$825)), ROW(20:20))), "")} | AE23: {=IFERROR(INDEX('Bank Schedule'!AE:AE, SMALL(IF('Bank Schedule'!$K$2:$K$825="Vacant", ROW('Bank Schedule'!$K$2:$K$825)), ROW(20:20))), "")} | AF23: {=IFERROR(INDEX('Bank Schedule'!AF:AF, SMALL(IF('Bank Schedule'!$K$2:$K$825="Vacant", ROW('Bank Schedule'!$K$2:$K$825)), ROW(20:20))), "")} | AG23: {=IFERROR(INDEX('Bank Schedule'!AG:AG, SMALL(IF('Bank Schedule'!$K$2:$K$825="Vacant", ROW('Bank Schedule'!$K$2:$K$825)), ROW(20:20))), "")} | AH23: {=IFERROR(INDEX('Bank Schedule'!AH:AH, SMALL(IF('Bank Schedule'!$K$2:$K$825="Vacant", ROW('Bank Schedule'!$K$2:$K$825)), ROW(20:20))), "")}
A24: {=IFERROR(INDEX('Bank Schedule'!A:A, SMALL(IF('Bank Schedule'!$K$2:$K$825="Vacant", ROW('Bank Schedule'!$K$2:$K$825)), ROW(21:21))), "")} | B24: {=IFERROR(INDEX('Bank Schedule'!B:B, SMALL(IF('Bank Schedule'!$K$2:$K$825="Vacant", ROW('Bank Schedule'!$K$2:$K$825)), ROW(21:21))), "")} | C24: {=IFERROR(INDEX('Bank Schedule'!C:C, SMALL(IF('Bank Schedule'!$K$2:$K$825="Vacant", ROW('Bank Schedule'!$K$2:$K$825)), ROW(21:21))), "")} | D24: {=IFERROR(INDEX('Bank Schedule'!D:D, SMALL(IF('Bank Schedule'!$K$2:$K$825="Vacant", ROW('Bank Schedule'!$K$2:$K$825)), ROW(21:21))), "")} | E24: {=IFERROR(INDEX('Bank Schedule'!E:E, SMALL(IF('Bank Schedule'!$K$2:$K$825="Vacant", ROW('Bank Schedule'!$K$2:$K$825)), ROW(21:21))), "")} | F24: {=IFERROR(INDEX('Bank Schedule'!F:F, SMALL(IF('Bank Schedule'!$K$2:$K$825="Vacant", ROW('Bank Schedule'!$K$2:$K$825)), ROW(21:21))), "")} | G24: {=IFERROR(INDEX('Bank Schedule'!G:G, SMALL(IF('Bank Schedule'!$K$2:$K$825="Vacant", ROW('Bank Schedule'!$K$2:$K$825)), ROW(21:21))), "")} | H24: {=IFERROR(INDEX('Bank Schedule'!H:H, SMALL(IF('Bank Schedule'!$K$2:$K$825="Vacant", ROW('Bank Schedule'!$K$2:$K$825)), ROW(21:21))), "")} | I24: {=IFERROR(INDEX('Bank Schedule'!I:I, SMALL(IF('Bank Schedule'!$K$2:$K$825="Vacant", ROW('Bank Schedule'!$K$2:$K$825)), ROW(21:21))), "")} | J24: {=IFERROR(INDEX('Bank Schedule'!J:J, SMALL(IF('Bank Schedule'!$K$2:$K$825="Vacant", ROW('Bank Schedule'!$K$2:$K$825)), ROW(21:21))), "")} | K24: {=IFERROR(INDEX('Bank Schedule'!K:K, SMALL(IF('Bank Schedule'!$K$2:$K$825="Vacant", ROW('Bank Schedule'!$K$2:$K$825)), ROW(21:21))), "")} | L24: {=IFERROR(INDEX('Bank Schedule'!L:L, SMALL(IF('Bank Schedule'!$K$2:$K$825="Vacant", ROW('Bank Schedule'!$K$2:$K$825)), ROW(21:21))), "")} | M24: {=IFERROR(INDEX('Bank Schedule'!M:M, SMALL(IF('Bank Schedule'!$K$2:$K$825="Vacant", ROW('Bank Schedule'!$K$2:$K$825)), ROW(21:21))), "")} | N24: {=IFERROR(INDEX('Bank Schedule'!N:N, SMALL(IF('Bank Schedule'!$K$2:$K$825="Vacant", ROW('Bank Schedule'!$K$2:$K$825)), ROW(21:21))), "")} | O24: {=IFERROR(INDEX('Bank Schedule'!O:O, SMALL(IF('Bank Schedule'!$K$2:$K$825="Vacant", ROW('Bank Schedule'!$K$2:$K$825)), ROW(21:21))), "")} | P24: {=IFERROR(INDEX('Bank Schedule'!P:P, SMALL(IF('Bank Schedule'!$K$2:$K$825="Vacant", ROW('Bank Schedule'!$K$2:$K$825)), ROW(21:21))), "")} | Q24: {=IFERROR(INDEX('Bank Schedule'!Q:Q, SMALL(IF('Bank Schedule'!$K$2:$K$825="Vacant", ROW('Bank Schedule'!$K$2:$K$825)), ROW(21:21))), "")} | R24: {=IFERROR(INDEX('Bank Schedule'!R:R, SMALL(IF('Bank Schedule'!$K$2:$K$825="Vacant", ROW('Bank Schedule'!$K$2:$K$825)), ROW(21:21))), "")} | S24: {=IFERROR(INDEX('Bank Schedule'!S:S, SMALL(IF('Bank Schedule'!$K$2:$K$825="Vacant", ROW('Bank Schedule'!$K$2:$K$825)), ROW(21:21))), "")} | T24: {=IFERROR(INDEX('Bank Schedule'!T:T, SMALL(IF('Bank Schedule'!$K$2:$K$825="Vacant", ROW('Bank Schedule'!$K$2:$K$825)), ROW(21:21))), "")} | U24: {=IFERROR(INDEX('Bank Schedule'!U:U, SMALL(IF('Bank Schedule'!$K$2:$K$825="Vacant", ROW('Bank Schedule'!$K$2:$K$825)), ROW(21:21))), "")} | V24: {=IFERROR(INDEX('Bank Schedule'!V:V, SMALL(IF('Bank Schedule'!$K$2:$K$825="Vacant", ROW('Bank Schedule'!$K$2:$K$825)), ROW(21:21))), "")} | W24: {=IFERROR(INDEX('Bank Schedule'!W:W, SMALL(IF('Bank Schedule'!$K$2:$K$825="Vacant", ROW('Bank Schedule'!$K$2:$K$825)), ROW(21:21))), "")} | X24: {=IFERROR(INDEX('Bank Schedule'!X:X, SMALL(IF('Bank Schedule'!$K$2:$K$825="Vacant", ROW('Bank Schedule'!$K$2:$K$825)), ROW(21:21))), "")} | Y24: {=IFERROR(INDEX('Bank Schedule'!Y:Y, SMALL(IF('Bank Schedule'!$K$2:$K$825="Vacant", ROW('Bank Schedule'!$K$2:$K$825)), ROW(21:21))), "")} | Z24: {=IFERROR(INDEX('Bank Schedule'!Z:Z, SMALL(IF('Bank Schedule'!$K$2:$K$825="Vacant", ROW('Bank Schedule'!$K$2:$K$825)), ROW(21:21))), "")} | AA24: {=IFERROR(INDEX('Bank Schedule'!AA:AA, SMALL(IF('Bank Schedule'!$K$2:$K$825="Vacant", ROW('Bank Schedule'!$K$2:$K$825)), ROW(21:21))), "")} | AB24: {=IFERROR(INDEX('Bank Schedule'!AB:AB, SMALL(IF('Bank Schedule'!$K$2:$K$825="Vacant", ROW('Bank Schedule'!$K$2:$K$825)), ROW(21:21))), "")} | AC24: {=IFERROR(INDEX('Bank Schedule'!AC:AC, SMALL(IF('Bank Schedule'!$K$2:$K$825="Vacant", ROW('Bank Schedule'!$K$2:$K$825)), ROW(21:21))), "")} | AD24: {=IFERROR(INDEX('Bank Schedule'!AD:AD, SMALL(IF('Bank Schedule'!$K$2:$K$825="Vacant", ROW('Bank Schedule'!$K$2:$K$825)), ROW(21:21))), "")} | AE24: {=IFERROR(INDEX('Bank Schedule'!AE:AE, SMALL(IF('Bank Schedule'!$K$2:$K$825="Vacant", ROW('Bank Schedule'!$K$2:$K$825)), ROW(21:21))), "")} | AF24: {=IFERROR(INDEX('Bank Schedule'!AF:AF, SMALL(IF('Bank Schedule'!$K$2:$K$825="Vacant", ROW('Bank Schedule'!$K$2:$K$825)), ROW(21:21))), "")} | AG24: {=IFERROR(INDEX('Bank Schedule'!AG:AG, SMALL(IF('Bank Schedule'!$K$2:$K$825="Vacant", ROW('Bank Schedule'!$K$2:$K$825)), ROW(21:21))), "")} | AH24: {=IFERROR(INDEX('Bank Schedule'!AH:AH, SMALL(IF('Bank Schedule'!$K$2:$K$825="Vacant", ROW('Bank Schedule'!$K$2:$K$825)), ROW(21:21))), "")}
A25: {=IFERROR(INDEX('Bank Schedule'!A:A, SMALL(IF('Bank Schedule'!$K$2:$K$825="Vacant", ROW('Bank Schedule'!$K$2:$K$825)), ROW(22:22))), "")} | B25: {=IFERROR(INDEX('Bank Schedule'!B:B, SMALL(IF('Bank Schedule'!$K$2:$K$825="Vacant", ROW('Bank Schedule'!$K$2:$K$825)), ROW(22:22))), "")} | C25: {=IFERROR(INDEX('Bank Schedule'!C:C, SMALL(IF('Bank Schedule'!$K$2:$K$825="Vacant", ROW('Bank Schedule'!$K$2:$K$825)), ROW(22:22))), "")} | D25: {=IFERROR(INDEX('Bank Schedule'!D:D, SMALL(IF('Bank Schedule'!$K$2:$K$825="Vacant", ROW('Bank Schedule'!$K$2:$K$825)), ROW(22:22))), "")} | E25: {=IFERROR(INDEX('Bank Schedule'!E:E, SMALL(IF('Bank Schedule'!$K$2:$K$825="Vacant", ROW('Bank Schedule'!$K$2:$K$825)), ROW(22:22))), "")} | F25: {=IFERROR(INDEX('Bank Schedule'!F:F, SMALL(IF('Bank Schedule'!$K$2:$K$825="Vacant", ROW('Bank Schedule'!$K$2:$K$825)), ROW(22:22))), "")} | G25: {=IFERROR(INDEX('Bank Schedule'!G:G, SMALL(IF('Bank Schedule'!$K$2:$K$825="Vacant", ROW('Bank Schedule'!$K$2:$K$825)), ROW(22:22))), "")} | H25: {=IFERROR(INDEX('Bank Schedule'!H:H, SMALL(IF('Bank Schedule'!$K$2:$K$825="Vacant", ROW('Bank Schedule'!$K$2:$K$825)), ROW(22:22))), "")} | I25: {=IFERROR(INDEX('Bank Schedule'!I:I, SMALL(IF('Bank Schedule'!$K$2:$K$825="Vacant", ROW('Bank Schedule'!$K$2:$K$825)), ROW(22:22))), "")} | J25: {=IFERROR(INDEX('Bank Schedule'!J:J, SMALL(IF('Bank Schedule'!$K$2:$K$825="Vacant", ROW('Bank Schedule'!$K$2:$K$825)), ROW(22:22))), "")} | K25: {=IFERROR(INDEX('Bank Schedule'!K:K, SMALL(IF('Bank Schedule'!$K$2:$K$825="Vacant", ROW('Bank Schedule'!$K$2:$K$825)), ROW(22:22))), "")} | L25: {=IFERROR(INDEX('Bank Schedule'!L:L, SMALL(IF('Bank Schedule'!$K$2:$K$825="Vacant", ROW('Bank Schedule'!$K$2:$K$825)), ROW(22:22))), "")} | M25: {=IFERROR(INDEX('Bank Schedule'!M:M, SMALL(IF('Bank Schedule'!$K$2:$K$825="Vacant", ROW('Bank Schedule'!$K$2:$K$825)), ROW(22:22))), "")} | N25: {=IFERROR(INDEX('Bank Schedule'!N:N, SMALL(IF('Bank Schedule'!$K$2:$K$825="Vacant", ROW('Bank Schedule'!$K$2:$K$825)), ROW(22:22))), "")} | O25: {=IFERROR(INDEX('Bank Schedule'!O:O, SMALL(IF('Bank Schedule'!$K$2:$K$825="Vacant", ROW('Bank Schedule'!$K$2:$K$825)), ROW(22:22))), "")} | P25: {=IFERROR(INDEX('Bank Schedule'!P:P, SMALL(IF('Bank Schedule'!$K$2:$K$825="Vacant", ROW('Bank Schedule'!$K$2:$K$825)), ROW(22:22))), "")} | Q25: {=IFERROR(INDEX('Bank Schedule'!Q:Q, SMALL(IF('Bank Schedule'!$K$2:$K$825="Vacant", ROW('Bank Schedule'!$K$2:$K$825)), ROW(22:22))), "")} | R25: {=IFERROR(INDEX('Bank Schedule'!R:R, SMALL(IF('Bank Schedule'!$K$2:$K$825="Vacant", ROW('Bank Schedule'!$K$2:$K$825)), ROW(22:22))), "")} | S25: {=IFERROR(INDEX('Bank Schedule'!S:S, SMALL(IF('Bank Schedule'!$K$2:$K$825="Vacant", ROW('Bank Schedule'!$K$2:$K$825)), ROW(22:22))), "")} | T25: {=IFERROR(INDEX('Bank Schedule'!T:T, SMALL(IF('Bank Schedule'!$K$2:$K$825="Vacant", ROW('Bank Schedule'!$K$2:$K$825)), ROW(22:22))), "")} | U25: {=IFERROR(INDEX('Bank Schedule'!U:U, SMALL(IF('Bank Schedule'!$K$2:$K$825="Vacant", ROW('Bank Schedule'!$K$2:$K$825)), ROW(22:22))), "")} | V25: {=IFERROR(INDEX('Bank Schedule'!V:V, SMALL(IF('Bank Schedule'!$K$2:$K$825="Vacant", ROW('Bank Schedule'!$K$2:$K$825)), ROW(22:22))), "")} | W25: {=IFERROR(INDEX('Bank Schedule'!W:W, SMALL(IF('Bank Schedule'!$K$2:$K$825="Vacant", ROW('Bank Schedule'!$K$2:$K$825)), ROW(22:22))), "")} | X25: {=IFERROR(INDEX('Bank Schedule'!X:X, SMALL(IF('Bank Schedule'!$K$2:$K$825="Vacant", ROW('Bank Schedule'!$K$2:$K$825)), ROW(22:22))), "")} | Y25: {=IFERROR(INDEX('Bank Schedule'!Y:Y, SMALL(IF('Bank Schedule'!$K$2:$K$825="Vacant", ROW('Bank Schedule'!$K$2:$K$825)), ROW(22:22))), "")} | Z25: {=IFERROR(INDEX('Bank Schedule'!Z:Z, SMALL(IF('Bank Schedule'!$K$2:$K$825="Vacant", ROW('Bank Schedule'!$K$2:$K$825)), ROW(22:22))), "")} | AA25: {=IFERROR(INDEX('Bank Schedule'!AA:AA, SMALL(IF('Bank Schedule'!$K$2:$K$825="Vacant", ROW('Bank Schedule'!$K$2:$K$825)), ROW(22:22))), "")} | AB25: {=IFERROR(INDEX('Bank Schedule'!AB:AB, SMALL(IF('Bank Schedule'!$K$2:$K$825="Vacant", ROW('Bank Schedule'!$K$2:$K$825)), ROW(22:22))), "")} | AC25: {=IFERROR(INDEX('Bank Schedule'!AC:AC, SMALL(IF('Bank Schedule'!$K$2:$K$825="Vacant", ROW('Bank Schedule'!$K$2:$K$825)), ROW(22:22))), "")} | AD25: {=IFERROR(INDEX('Bank Schedule'!AD:AD, SMALL(IF('Bank Schedule'!$K$2:$K$825="Vacant", ROW('Bank Schedule'!$K$2:$K$825)), ROW(22:22))), "")} | AE25: {=IFERROR(INDEX('Bank Schedule'!AE:AE, SMALL(IF('Bank Schedule'!$K$2:$K$825="Vacant", ROW('Bank Schedule'!$K$2:$K$825)), ROW(22:22))), "")} | AF25: {=IFERROR(INDEX('Bank Schedule'!AF:AF, SMALL(IF('Bank Schedule'!$K$2:$K$825="Vacant", ROW('Bank Schedule'!$K$2:$K$825)), ROW(22:22))), "")} | AG25: {=IFERROR(INDEX('Bank Schedule'!AG:AG, SMALL(IF('Bank Schedule'!$K$2:$K$825="Vacant", ROW('Bank Schedule'!$K$2:$K$825)), ROW(22:22))), "")} | AH25: {=IFERROR(INDEX('Bank Schedule'!AH:AH, SMALL(IF('Bank Schedule'!$K$2:$K$825="Vacant", ROW('Bank Schedule'!$K$2:$K$825)), ROW(22:22))), "")}
A26: {=IFERROR(INDEX('Bank Schedule'!A:A, SMALL(IF('Bank Schedule'!$K$2:$K$825="Vacant", ROW('Bank Schedule'!$K$2:$K$825)), ROW(23:23))), "")} | B26: {=IFERROR(INDEX('Bank Schedule'!B:B, SMALL(IF('Bank Schedule'!$K$2:$K$825="Vacant", ROW('Bank Schedule'!$K$2:$K$825)), ROW(23:23))), "")} | C26: {=IFERROR(INDEX('Bank Schedule'!C:C, SMALL(IF('Bank Schedule'!$K$2:$K$825="Vacant", ROW('Bank Schedule'!$K$2:$K$825)), ROW(23:23))), "")} | D26: {=IFERROR(INDEX('Bank Schedule'!D:D, SMALL(IF('Bank Schedule'!$K$2:$K$825="Vacant", ROW('Bank Schedule'!$K$2:$K$825)), ROW(23:23))), "")} | E26: {=IFERROR(INDEX('Bank Schedule'!E:E, SMALL(IF('Bank Schedule'!$K$2:$K$825="Vacant", ROW('Bank Schedule'!$K$2:$K$825)), ROW(23:23))), "")} | F26: {=IFERROR(INDEX('Bank Schedule'!F:F, SMALL(IF('Bank Schedule'!$K$2:$K$825="Vacant", ROW('Bank Schedule'!$K$2:$K$825)), ROW(23:23))), "")} | G26: {=IFERROR(INDEX('Bank Schedule'!G:G, SMALL(IF('Bank Schedule'!$K$2:$K$825="Vacant", ROW('Bank Schedule'!$K$2:$K$825)), ROW(23:23))), "")} | H26: {=IFERROR(INDEX('Bank Schedule'!H:H, SMALL(IF('Bank Schedule'!$K$2:$K$825="Vacant", ROW('Bank Schedule'!$K$2:$K$825)), ROW(23:23))), "")} | I26: {=IFERROR(INDEX('Bank Schedule'!I:I, SMALL(IF('Bank Schedule'!$K$2:$K$825="Vacant", ROW('Bank Schedule'!$K$2:$K$825)), ROW(23:23))), "")} | J26: {=IFERROR(INDEX('Bank Schedule'!J:J, SMALL(IF('Bank Schedule'!$K$2:$K$825="Vacant", ROW('Bank Schedule'!$K$2:$K$825)), ROW(23:23))), "")} | K26: {=IFERROR(INDEX('Bank Schedule'!K:K, SMALL(IF('Bank Schedule'!$K$2:$K$825="Vacant", ROW('Bank Schedule'!$K$2:$K$825)), ROW(23:23))), "")} | L26: {=IFERROR(INDEX('Bank Schedule'!L:L, SMALL(IF('Bank Schedule'!$K$2:$K$825="Vacant", ROW('Bank Schedule'!$K$2:$K$825)), ROW(23:23))), "")} | M26: {=IFERROR(INDEX('Bank Schedule'!M:M, SMALL(IF('Bank Schedule'!$K$2:$K$825="Vacant", ROW('Bank Schedule'!$K$2:$K$825)), ROW(23:23))), "")} | N26: {=IFERROR(INDEX('Bank Schedule'!N:N, SMALL(IF('Bank Schedule'!$K$2:$K$825="Vacant", ROW('Bank Schedule'!$K$2:$K$825)), ROW(23:23))), "")} | O26: {=IFERROR(INDEX('Bank Schedule'!O:O, SMALL(IF('Bank Schedule'!$K$2:$K$825="Vacant", ROW('Bank Schedule'!$K$2:$K$825)), ROW(23:23))), "")} | P26: {=IFERROR(INDEX('Bank Schedule'!P:P, SMALL(IF('Bank Schedule'!$K$2:$K$825="Vacant", ROW('Bank Schedule'!$K$2:$K$825)), ROW(23:23))), "")} | Q26: {=IFERROR(INDEX('Bank Schedule'!Q:Q, SMALL(IF('Bank Schedule'!$K$2:$K$825="Vacant", ROW('Bank Schedule'!$K$2:$K$825)), ROW(23:23))), "")} | R26: {=IFERROR(INDEX('Bank Schedule'!R:R, SMALL(IF('Bank Schedule'!$K$2:$K$825="Vacant", ROW('Bank Schedule'!$K$2:$K$825)), ROW(23:23))), "")} | S26: {=IFERROR(INDEX('Bank Schedule'!S:S, SMALL(IF('Bank Schedule'!$K$2:$K$825="Vacant", ROW('Bank Schedule'!$K$2:$K$825)), ROW(23:23))), "")} | T26: {=IFERROR(INDEX('Bank Schedule'!T:T, SMALL(IF('Bank Schedule'!$K$2:$K$825="Vacant", ROW('Bank Schedule'!$K$2:$K$825)), ROW(23:23))), "")} | U26: {=IFERROR(INDEX('Bank Schedule'!U:U, SMALL(IF('Bank Schedule'!$K$2:$K$825="Vacant", ROW('Bank Schedule'!$K$2:$K$825)), ROW(23:23))), "")} | V26: {=IFERROR(INDEX('Bank Schedule'!V:V, SMALL(IF('Bank Schedule'!$K$2:$K$825="Vacant", ROW('Bank Schedule'!$K$2:$K$825)), ROW(23:23))), "")} | W26: {=IFERROR(INDEX('Bank Schedule'!W:W, SMALL(IF('Bank Schedule'!$K$2:$K$825="Vacant", ROW('Bank Schedule'!$K$2:$K$825)), ROW(23:23))), "")} | X26: {=IFERROR(INDEX('Bank Schedule'!X:X, SMALL(IF('Bank Schedule'!$K$2:$K$825="Vacant", ROW('Bank Schedule'!$K$2:$K$825)), ROW(23:23))), "")} | Y26: {=IFERROR(INDEX('Bank Schedule'!Y:Y, SMALL(IF('Bank Schedule'!$K$2:$K$825="Vacant", ROW('Bank Schedule'!$K$2:$K$825)), ROW(23:23))), "")} | Z26: {=IFERROR(INDEX('Bank Schedule'!Z:Z, SMALL(IF('Bank Schedule'!$K$2:$K$825="Vacant", ROW('Bank Schedule'!$K$2:$K$825)), ROW(23:23))), "")} | AA26: {=IFERROR(INDEX('Bank Schedule'!AA:AA, SMALL(IF('Bank Schedule'!$K$2:$K$825="Vacant", ROW('Bank Schedule'!$K$2:$K$825)), ROW(23:23))), "")} | AB26: {=IFERROR(INDEX('Bank Schedule'!AB:AB, SMALL(IF('Bank Schedule'!$K$2:$K$825="Vacant", ROW('Bank Schedule'!$K$2:$K$825)), ROW(23:23))), "")} | AC26: {=IFERROR(INDEX('Bank Schedule'!AC:AC, SMALL(IF('Bank Schedule'!$K$2:$K$825="Vacant", ROW('Bank Schedule'!$K$2:$K$825)), ROW(23:23))), "")} | AD26: {=IFERROR(INDEX('Bank Schedule'!AD:AD, SMALL(IF('Bank Schedule'!$K$2:$K$825="Vacant", ROW('Bank Schedule'!$K$2:$K$825)), ROW(23:23))), "")} | AE26: {=IFERROR(INDEX('Bank Schedule'!AE:AE, SMALL(IF('Bank Schedule'!$K$2:$K$825="Vacant", ROW('Bank Schedule'!$K$2:$K$825)), ROW(23:23))), "")} | AF26: {=IFERROR(INDEX('Bank Schedule'!AF:AF, SMALL(IF('Bank Schedule'!$K$2:$K$825="Vacant", ROW('Bank Schedule'!$K$2:$K$825)), ROW(23:23))), "")} | AG26: {=IFERROR(INDEX('Bank Schedule'!AG:AG, SMALL(IF('Bank Schedule'!$K$2:$K$825="Vacant", ROW('Bank Schedule'!$K$2:$K$825)), ROW(23:23))), "")} | AH26: {=IFERROR(INDEX('Bank Schedule'!AH:AH, SMALL(IF('Bank Schedule'!$K$2:$K$825="Vacant", ROW('Bank Schedule'!$K$2:$K$825)), ROW(23:23))), "")}
A27: {=IFERROR(INDEX('Bank Schedule'!A:A, SMALL(IF('Bank Schedule'!$K$2:$K$825="Vacant", ROW('Bank Schedule'!$K$2:$K$825)), ROW(24:24))), "")} | B27: {=IFERROR(INDEX('Bank Schedule'!B:B, SMALL(IF('Bank Schedule'!$K$2:$K$825="Vacant", ROW('Bank Schedule'!$K$2:$K$825)), ROW(24:24))), "")} | C27: {=IFERROR(INDEX('Bank Schedule'!C:C, SMALL(IF('Bank Schedule'!$K$2:$K$825="Vacant", ROW('Bank Schedule'!$K$2:$K$825)), ROW(24:24))), "")} | D27: {=IFERROR(INDEX('Bank Schedule'!D:D, SMALL(IF('Bank Schedule'!$K$2:$K$825="Vacant", ROW('Bank Schedule'!$K$2:$K$825)), ROW(24:24))), "")} | E27: {=IFERROR(INDEX('Bank Schedule'!E:E, SMALL(IF('Bank Schedule'!$K$2:$K$825="Vacant", ROW('Bank Schedule'!$K$2:$K$825)), ROW(24:24))), "")} | F27: {=IFERROR(INDEX('Bank Schedule'!F:F, SMALL(IF('Bank Schedule'!$K$2:$K$825="Vacant", ROW('Bank Schedule'!$K$2:$K$825)), ROW(24:24))), "")} | G27: {=IFERROR(INDEX('Bank Schedule'!G:G, SMALL(IF('Bank Schedule'!$K$2:$K$825="Vacant", ROW('Bank Schedule'!$K$2:$K$825)), ROW(24:24))), "")} | H27: {=IFERROR(INDEX('Bank Schedule'!H:H, SMALL(IF('Bank Schedule'!$K$2:$K$825="Vacant", ROW('Bank Schedule'!$K$2:$K$825)), ROW(24:24))), "")} | I27: {=IFERROR(INDEX('Bank Schedule'!I:I, SMALL(IF('Bank Schedule'!$K$2:$K$825="Vacant", ROW('Bank Schedule'!$K$2:$K$825)), ROW(24:24))), "")} | J27: {=IFERROR(INDEX('Bank Schedule'!J:J, SMALL(IF('Bank Schedule'!$K$2:$K$825="Vacant", ROW('Bank Schedule'!$K$2:$K$825)), ROW(24:24))), "")} | K27: {=IFERROR(INDEX('Bank Schedule'!K:K, SMALL(IF('Bank Schedule'!$K$2:$K$825="Vacant", ROW('Bank Schedule'!$K$2:$K$825)), ROW(24:24))), "")} | L27: {=IFERROR(INDEX('Bank Schedule'!L:L, SMALL(IF('Bank Schedule'!$K$2:$K$825="Vacant", ROW('Bank Schedule'!$K$2:$K$825)), ROW(24:24))), "")} | M27: {=IFERROR(INDEX('Bank Schedule'!M:M, SMALL(IF('Bank Schedule'!$K$2:$K$825="Vacant", ROW('Bank Schedule'!$K$2:$K$825)), ROW(24:24))), "")} | N27: {=IFERROR(INDEX('Bank Schedule'!N:N, SMALL(IF('Bank Schedule'!$K$2:$K$825="Vacant", ROW('Bank Schedule'!$K$2:$K$825)), ROW(24:24))), "")} | O27: {=IFERROR(INDEX('Bank Schedule'!O:O, SMALL(IF('Bank Schedule'!$K$2:$K$825="Vacant", ROW('Bank Schedule'!$K$2:$K$825)), ROW(24:24))), "")} | P27: {=IFERROR(INDEX('Bank Schedule'!P:P, SMALL(IF('Bank Schedule'!$K$2:$K$825="Vacant", ROW('Bank Schedule'!$K$2:$K$825)), ROW(24:24))), "")} | Q27: {=IFERROR(INDEX('Bank Schedule'!Q:Q, SMALL(IF('Bank Schedule'!$K$2:$K$825="Vacant", ROW('Bank Schedule'!$K$2:$K$825)), ROW(24:24))), "")} | R27: {=IFERROR(INDEX('Bank Schedule'!R:R, SMALL(IF('Bank Schedule'!$K$2:$K$825="Vacant", ROW('Bank Schedule'!$K$2:$K$825)), ROW(24:24))), "")} | S27: {=IFERROR(INDEX('Bank Schedule'!S:S, SMALL(IF('Bank Schedule'!$K$2:$K$825="Vacant", ROW('Bank Schedule'!$K$2:$K$825)), ROW(24:24))), "")} | T27: {=IFERROR(INDEX('Bank Schedule'!T:T, SMALL(IF('Bank Schedule'!$K$2:$K$825="Vacant", ROW('Bank Schedule'!$K$2:$K$825)), ROW(24:24))), "")} | U27: {=IFERROR(INDEX('Bank Schedule'!U:U, SMALL(IF('Bank Schedule'!$K$2:$K$825="Vacant", ROW('Bank Schedule'!$K$2:$K$825)), ROW(24:24))), "")} | V27: {=IFERROR(INDEX('Bank Schedule'!V:V, SMALL(IF('Bank Schedule'!$K$2:$K$825="Vacant", ROW('Bank Schedule'!$K$2:$K$825)), ROW(24:24))), "")} | W27: {=IFERROR(INDEX('Bank Schedule'!W:W, SMALL(IF('Bank Schedule'!$K$2:$K$825="Vacant", ROW('Bank Schedule'!$K$2:$K$825)), ROW(24:24))), "")} | X27: {=IFERROR(INDEX('Bank Schedule'!X:X, SMALL(IF('Bank Schedule'!$K$2:$K$825="Vacant", ROW('Bank Schedule'!$K$2:$K$825)), ROW(24:24))), "")} | Y27: {=IFERROR(INDEX('Bank Schedule'!Y:Y, SMALL(IF('Bank Schedule'!$K$2:$K$825="Vacant", ROW('Bank Schedule'!$K$2:$K$825)), ROW(24:24))), "")} | Z27: {=IFERROR(INDEX('Bank Schedule'!Z:Z, SMALL(IF('Bank Schedule'!$K$2:$K$825="Vacant", ROW('Bank Schedule'!$K$2:$K$825)), ROW(24:24))), "")} | AA27: {=IFERROR(INDEX('Bank Schedule'!AA:AA, SMALL(IF('Bank Schedule'!$K$2:$K$825="Vacant", ROW('Bank Schedule'!$K$2:$K$825)), ROW(24:24))), "")} | AB27: {=IFERROR(INDEX('Bank Schedule'!AB:AB, SMALL(IF('Bank Schedule'!$K$2:$K$825="Vacant", ROW('Bank Schedule'!$K$2:$K$825)), ROW(24:24))), "")} | AC27: {=IFERROR(INDEX('Bank Schedule'!AC:AC, SMALL(IF('Bank Schedule'!$K$2:$K$825="Vacant", ROW('Bank Schedule'!$K$2:$K$825)), ROW(24:24))), "")} | AD27: {=IFERROR(INDEX('Bank Schedule'!AD:AD, SMALL(IF('Bank Schedule'!$K$2:$K$825="Vacant", ROW('Bank Schedule'!$K$2:$K$825)), ROW(24:24))), "")} | AE27: {=IFERROR(INDEX('Bank Schedule'!AE:AE, SMALL(IF('Bank Schedule'!$K$2:$K$825="Vacant", ROW('Bank Schedule'!$K$2:$K$825)), ROW(24:24))), "")} | AF27: {=IFERROR(INDEX('Bank Schedule'!AF:AF, SMALL(IF('Bank Schedule'!$K$2:$K$825="Vacant", ROW('Bank Schedule'!$K$2:$K$825)), ROW(24:24))), "")} | AG27: {=IFERROR(INDEX('Bank Schedule'!AG:AG, SMALL(IF('Bank Schedule'!$K$2:$K$825="Vacant", ROW('Bank Schedule'!$K$2:$K$825)), ROW(24:24))), "")} | AH27: {=IFERROR(INDEX('Bank Schedule'!AH:AH, SMALL(IF('Bank Schedule'!$K$2:$K$825="Vacant", ROW('Bank Schedule'!$K$2:$K$825)), ROW(24:24))), "")}
A28: {=IFERROR(INDEX('Bank Schedule'!A:A, SMALL(IF('Bank Schedule'!$K$2:$K$825="Vacant", ROW('Bank Schedule'!$K$2:$K$825)), ROW(25:25))), "")} | B28: {=IFERROR(INDEX('Bank Schedule'!B:B, SMALL(IF('Bank Schedule'!$K$2:$K$825="Vacant", ROW('Bank Schedule'!$K$2:$K$825)), ROW(25:25))), "")} | C28: {=IFERROR(INDEX('Bank Schedule'!C:C, SMALL(IF('Bank Schedule'!$K$2:$K$825="Vacant", ROW('Bank Schedule'!$K$2:$K$825)), ROW(25:25))), "")} | D28: {=IFERROR(INDEX('Bank Schedule'!D:D, SMALL(IF('Bank Schedule'!$K$2:$K$825="Vacant", ROW('Bank Schedule'!$K$2:$K$825)), ROW(25:25))), "")} | E28: {=IFERROR(INDEX('Bank Schedule'!E:E, SMALL(IF('Bank Schedule'!$K$2:$K$825="Vacant", ROW('Bank Schedule'!$K$2:$K$825)), ROW(25:25))), "")} | F28: {=IFERROR(INDEX('Bank Schedule'!F:F, SMALL(IF('Bank Schedule'!$K$2:$K$825="Vacant", ROW('Bank Schedule'!$K$2:$K$825)), ROW(25:25))), "")} | G28: {=IFERROR(INDEX('Bank Schedule'!G:G, SMALL(IF('Bank Schedule'!$K$2:$K$825="Vacant", ROW('Bank Schedule'!$K$2:$K$825)), ROW(25:25))), "")} | H28: {=IFERROR(INDEX('Bank Schedule'!H:H, SMALL(IF('Bank Schedule'!$K$2:$K$825="Vacant", ROW('Bank Schedule'!$K$2:$K$825)), ROW(25:25))), "")} | I28: {=IFERROR(INDEX('Bank Schedule'!I:I, SMALL(IF('Bank Schedule'!$K$2:$K$825="Vacant", ROW('Bank Schedule'!$K$2:$K$825)), ROW(25:25))), "")} | J28: {=IFERROR(INDEX('Bank Schedule'!J:J, SMALL(IF('Bank Schedule'!$K$2:$K$825="Vacant", ROW('Bank Schedule'!$K$2:$K$825)), ROW(25:25))), "")} | K28: {=IFERROR(INDEX('Bank Schedule'!K:K, SMALL(IF('Bank Schedule'!$K$2:$K$825="Vacant", ROW('Bank Schedule'!$K$2:$K$825)), ROW(25:25))), "")} | L28: {=IFERROR(INDEX('Bank Schedule'!L:L, SMALL(IF('Bank Schedule'!$K$2:$K$825="Vacant", ROW('Bank Schedule'!$K$2:$K$825)), ROW(25:25))), "")} | M28: {=IFERROR(INDEX('Bank Schedule'!M:M, SMALL(IF('Bank Schedule'!$K$2:$K$825="Vacant", ROW('Bank Schedule'!$K$2:$K$825)), ROW(25:25))), "")} | N28: {=IFERROR(INDEX('Bank Schedule'!N:N, SMALL(IF('Bank Schedule'!$K$2:$K$825="Vacant", ROW('Bank Schedule'!$K$2:$K$825)), ROW(25:25))), "")} | O28: {=IFERROR(INDEX('Bank Schedule'!O:O, SMALL(IF('Bank Schedule'!$K$2:$K$825="Vacant", ROW('Bank Schedule'!$K$2:$K$825)), ROW(25:25))), "")} | P28: {=IFERROR(INDEX('Bank Schedule'!P:P, SMALL(IF('Bank Schedule'!$K$2:$K$825="Vacant", ROW('Bank Schedule'!$K$2:$K$825)), ROW(25:25))), "")} | Q28: {=IFERROR(INDEX('Bank Schedule'!Q:Q, SMALL(IF('Bank Schedule'!$K$2:$K$825="Vacant", ROW('Bank Schedule'!$K$2:$K$825)), ROW(25:25))), "")} | R28: {=IFERROR(INDEX('Bank Schedule'!R:R, SMALL(IF('Bank Schedule'!$K$2:$K$825="Vacant", ROW('Bank Schedule'!$K$2:$K$825)), ROW(25:25))), "")} | S28: {=IFERROR(INDEX('Bank Schedule'!S:S, SMALL(IF('Bank Schedule'!$K$2:$K$825="Vacant", ROW('Bank Schedule'!$K$2:$K$825)), ROW(25:25))), "")} | T28: {=IFERROR(INDEX('Bank Schedule'!T:T, SMALL(IF('Bank Schedule'!$K$2:$K$825="Vacant", ROW('Bank Schedule'!$K$2:$K$825)), ROW(25:25))), "")} | U28: {=IFERROR(INDEX('Bank Schedule'!U:U, SMALL(IF('Bank Schedule'!$K$2:$K$825="Vacant", ROW('Bank Schedule'!$K$2:$K$825)), ROW(25:25))), "")} | V28: {=IFERROR(INDEX('Bank Schedule'!V:V, SMALL(IF('Bank Schedule'!$K$2:$K$825="Vacant", ROW('Bank Schedule'!$K$2:$K$825)), ROW(25:25))), "")} | W28: {=IFERROR(INDEX('Bank Schedule'!W:W, SMALL(IF('Bank Schedule'!$K$2:$K$825="Vacant", ROW('Bank Schedule'!$K$2:$K$825)), ROW(25:25))), "")} | X28: {=IFERROR(INDEX('Bank Schedule'!X:X, SMALL(IF('Bank Schedule'!$K$2:$K$825="Vacant", ROW('Bank Schedule'!$K$2:$K$825)), ROW(25:25))), "")} | Y28: {=IFERROR(INDEX('Bank Schedule'!Y:Y, SMALL(IF('Bank Schedule'!$K$2:$K$825="Vacant", ROW('Bank Schedule'!$K$2:$K$825)), ROW(25:25))), "")} | Z28: {=IFERROR(INDEX('Bank Schedule'!Z:Z, SMALL(IF('Bank Schedule'!$K$2:$K$825="Vacant", ROW('Bank Schedule'!$K$2:$K$825)), ROW(25:25))), "")} | AA28: {=IFERROR(INDEX('Bank Schedule'!AA:AA, SMALL(IF('Bank Schedule'!$K$2:$K$825="Vacant", ROW('Bank Schedule'!$K$2:$K$825)), ROW(25:25))), "")} | AB28: {=IFERROR(INDEX('Bank Schedule'!AB:AB, SMALL(IF('Bank Schedule'!$K$2:$K$825="Vacant", ROW('Bank Schedule'!$K$2:$K$825)), ROW(25:25))), "")} | AC28: {=IFERROR(INDEX('Bank Schedule'!AC:AC, SMALL(IF('Bank Schedule'!$K$2:$K$825="Vacant", ROW('Bank Schedule'!$K$2:$K$825)), ROW(25:25))), "")} | AD28: {=IFERROR(INDEX('Bank Schedule'!AD:AD, SMALL(IF('Bank Schedule'!$K$2:$K$825="Vacant", ROW('Bank Schedule'!$K$2:$K$825)), ROW(25:25))), "")} | AE28: {=IFERROR(INDEX('Bank Schedule'!AE:AE, SMALL(IF('Bank Schedule'!$K$2:$K$825="Vacant", ROW('Bank Schedule'!$K$2:$K$825)), ROW(25:25))), "")} | AF28: {=IFERROR(INDEX('Bank Schedule'!AF:AF, SMALL(IF('Bank Schedule'!$K$2:$K$825="Vacant", ROW('Bank Schedule'!$K$2:$K$825)), ROW(25:25))), "")} | AG28: {=IFERROR(INDEX('Bank Schedule'!AG:AG, SMALL(IF('Bank Schedule'!$K$2:$K$825="Vacant", ROW('Bank Schedule'!$K$2:$K$825)), ROW(25:25))), "")} | AH28: {=IFERROR(INDEX('Bank Schedule'!AH:AH, SMALL(IF('Bank Schedule'!$K$2:$K$825="Vacant", ROW('Bank Schedule'!$K$2:$K$825)), ROW(25:25))), "")}
A29: {=IFERROR(INDEX('Bank Schedule'!A:A, SMALL(IF('Bank Schedule'!$K$2:$K$825="Vacant", ROW('Bank Schedule'!$K$2:$K$825)), ROW(26:26))), "")} | B29: {=IFERROR(INDEX('Bank Schedule'!B:B, SMALL(IF('Bank Schedule'!$K$2:$K$825="Vacant", ROW('Bank Schedule'!$K$2:$K$825)), ROW(26:26))), "")} | C29: {=IFERROR(INDEX('Bank Schedule'!C:C, SMALL(IF('Bank Schedule'!$K$2:$K$825="Vacant", ROW('Bank Schedule'!$K$2:$K$825)), ROW(26:26))), "")} | D29: {=IFERROR(INDEX('Bank Schedule'!D:D, SMALL(IF('Bank Schedule'!$K$2:$K$825="Vacant", ROW('Bank Schedule'!$K$2:$K$825)), ROW(26:26))), "")} | E29: {=IFERROR(INDEX('Bank Schedule'!E:E, SMALL(IF('Bank Schedule'!$K$2:$K$825="Vacant", ROW('Bank Schedule'!$K$2:$K$825)), ROW(26:26))), "")} | F29: {=IFERROR(INDEX('Bank Schedule'!F:F, SMALL(IF('Bank Schedule'!$K$2:$K$825="Vacant", ROW('Bank Schedule'!$K$2:$K$825)), ROW(26:26))), "")} | G29: {=IFERROR(INDEX('Bank Schedule'!G:G, SMALL(IF('Bank Schedule'!$K$2:$K$825="Vacant", ROW('Bank Schedule'!$K$2:$K$825)), ROW(26:26))), "")} | H29: {=IFERROR(INDEX('Bank Schedule'!H:H, SMALL(IF('Bank Schedule'!$K$2:$K$825="Vacant", ROW('Bank Schedule'!$K$2:$K$825)), ROW(26:26))), "")} | I29: {=IFERROR(INDEX('Bank Schedule'!I:I, SMALL(IF('Bank Schedule'!$K$2:$K$825="Vacant", ROW('Bank Schedule'!$K$2:$K$825)), ROW(26:26))), "")} | J29: {=IFERROR(INDEX('Bank Schedule'!J:J, SMALL(IF('Bank Schedule'!$K$2:$K$825="Vacant", ROW('Bank Schedule'!$K$2:$K$825)), ROW(26:26))), "")} | K29: {=IFERROR(INDEX('Bank Schedule'!K:K, SMALL(IF('Bank Schedule'!$K$2:$K$825="Vacant", ROW('Bank Schedule'!$K$2:$K$825)), ROW(26:26))), "")} | L29: {=IFERROR(INDEX('Bank Schedule'!L:L, SMALL(IF('Bank Schedule'!$K$2:$K$825="Vacant", ROW('Bank Schedule'!$K$2:$K$825)), ROW(26:26))), "")} | M29: {=IFERROR(INDEX('Bank Schedule'!M:M, SMALL(IF('Bank Schedule'!$K$2:$K$825="Vacant", ROW('Bank Schedule'!$K$2:$K$825)), ROW(26:26))), "")} | N29: {=IFERROR(INDEX('Bank Schedule'!N:N, SMALL(IF('Bank Schedule'!$K$2:$K$825="Vacant", ROW('Bank Schedule'!$K$2:$K$825)), ROW(26:26))), "")} | O29: {=IFERROR(INDEX('Bank Schedule'!O:O, SMALL(IF('Bank Schedule'!$K$2:$K$825="Vacant", ROW('Bank Schedule'!$K$2:$K$825)), ROW(26:26))), "")} | P29: {=IFERROR(INDEX('Bank Schedule'!P:P, SMALL(IF('Bank Schedule'!$K$2:$K$825="Vacant", ROW('Bank Schedule'!$K$2:$K$825)), ROW(26:26))), "")} | Q29: {=IFERROR(INDEX('Bank Schedule'!Q:Q, SMALL(IF('Bank Schedule'!$K$2:$K$825="Vacant", ROW('Bank Schedule'!$K$2:$K$825)), ROW(26:26))), "")} | R29: {=IFERROR(INDEX('Bank Schedule'!R:R, SMALL(IF('Bank Schedule'!$K$2:$K$825="Vacant", ROW('Bank Schedule'!$K$2:$K$825)), ROW(26:26))), "")} | S29: {=IFERROR(INDEX('Bank Schedule'!S:S, SMALL(IF('Bank Schedule'!$K$2:$K$825="Vacant", ROW('Bank Schedule'!$K$2:$K$825)), ROW(26:26))), "")} | T29: {=IFERROR(INDEX('Bank Schedule'!T:T, SMALL(IF('Bank Schedule'!$K$2:$K$825="Vacant", ROW('Bank Schedule'!$K$2:$K$825)), ROW(26:26))), "")} | U29: {=IFERROR(INDEX('Bank Schedule'!U:U, SMALL(IF('Bank Schedule'!$K$2:$K$825="Vacant", ROW('Bank Schedule'!$K$2:$K$825)), ROW(26:26))), "")} | V29: {=IFERROR(INDEX('Bank Schedule'!V:V, SMALL(IF('Bank Schedule'!$K$2:$K$825="Vacant", ROW('Bank Schedule'!$K$2:$K$825)), ROW(26:26))), "")} | W29: {=IFERROR(INDEX('Bank Schedule'!W:W, SMALL(IF('Bank Schedule'!$K$2:$K$825="Vacant", ROW('Bank Schedule'!$K$2:$K$825)), ROW(26:26))), "")} | X29: {=IFERROR(INDEX('Bank Schedule'!X:X, SMALL(IF('Bank Schedule'!$K$2:$K$825="Vacant", ROW('Bank Schedule'!$K$2:$K$825)), ROW(26:26))), "")} | Y29: {=IFERROR(INDEX('Bank Schedule'!Y:Y, SMALL(IF('Bank Schedule'!$K$2:$K$825="Vacant", ROW('Bank Schedule'!$K$2:$K$825)), ROW(26:26))), "")} | Z29: {=IFERROR(INDEX('Bank Schedule'!Z:Z, SMALL(IF('Bank Schedule'!$K$2:$K$825="Vacant", ROW('Bank Schedule'!$K$2:$K$825)), ROW(26:26))), "")} | AA29: {=IFERROR(INDEX('Bank Schedule'!AA:AA, SMALL(IF('Bank Schedule'!$K$2:$K$825="Vacant", ROW('Bank Schedule'!$K$2:$K$825)), ROW(26:26))), "")} | AB29: {=IFERROR(INDEX('Bank Schedule'!AB:AB, SMALL(IF('Bank Schedule'!$K$2:$K$825="Vacant", ROW('Bank Schedule'!$K$2:$K$825)), ROW(26:26))), "")} | AC29: {=IFERROR(INDEX('Bank Schedule'!AC:AC, SMALL(IF('Bank Schedule'!$K$2:$K$825="Vacant", ROW('Bank Schedule'!$K$2:$K$825)), ROW(26:26))), "")} | AD29: {=IFERROR(INDEX('Bank Schedule'!AD:AD, SMALL(IF('Bank Schedule'!$K$2:$K$825="Vacant", ROW('Bank Schedule'!$K$2:$K$825)), ROW(26:26))), "")} | AE29: {=IFERROR(INDEX('Bank Schedule'!AE:AE, SMALL(IF('Bank Schedule'!$K$2:$K$825="Vacant", ROW('Bank Schedule'!$K$2:$K$825)), ROW(26:26))), "")} | AF29: {=IFERROR(INDEX('Bank Schedule'!AF:AF, SMALL(IF('Bank Schedule'!$K$2:$K$825="Vacant", ROW('Bank Schedule'!$K$2:$K$825)), ROW(26:26))), "")} | AG29: {=IFERROR(INDEX('Bank Schedule'!AG:AG, SMALL(IF('Bank Schedule'!$K$2:$K$825="Vacant", ROW('Bank Schedule'!$K$2:$K$825)), ROW(26:26))), "")} | AH29: {=IFERROR(INDEX('Bank Schedule'!AH:AH, SMALL(IF('Bank Schedule'!$K$2:$K$825="Vacant", ROW('Bank Schedule'!$K$2:$K$825)), ROW(26:26))), "")}
A30: {=IFERROR(INDEX('Bank Schedule'!A:A, SMALL(IF('Bank Schedule'!$K$2:$K$825="Vacant", ROW('Bank Schedule'!$K$2:$K$825)), ROW(27:27))), "")} | B30: {=IFERROR(INDEX('Bank Schedule'!B:B, SMALL(IF('Bank Schedule'!$K$2:$K$825="Vacant", ROW('Bank Schedule'!$K$2:$K$825)), ROW(27:27))), "")} | C30: {=IFERROR(INDEX('Bank Schedule'!C:C, SMALL(IF('Bank Schedule'!$K$2:$K$825="Vacant", ROW('Bank Schedule'!$K$2:$K$825)), ROW(27:27))), "")} | D30: {=IFERROR(INDEX('Bank Schedule'!D:D, SMALL(IF('Bank Schedule'!$K$2:$K$825="Vacant", ROW('Bank Schedule'!$K$2:$K$825)), ROW(27:27))), "")} | E30: {=IFERROR(INDEX('Bank Schedule'!E:E, SMALL(IF('Bank Schedule'!$K$2:$K$825="Vacant", ROW('Bank Schedule'!$K$2:$K$825)), ROW(27:27))), "")} | F30: {=IFERROR(INDEX('Bank Schedule'!F:F, SMALL(IF('Bank Schedule'!$K$2:$K$825="Vacant", ROW('Bank Schedule'!$K$2:$K$825)), ROW(27:27))), "")} | G30: {=IFERROR(INDEX('Bank Schedule'!G:G, SMALL(IF('Bank Schedule'!$K$2:$K$825="Vacant", ROW('Bank Schedule'!$K$2:$K$825)), ROW(27:27))), "")} | H30: {=IFERROR(INDEX('Bank Schedule'!H:H, SMALL(IF('Bank Schedule'!$K$2:$K$825="Vacant", ROW('Bank Schedule'!$K$2:$K$825)), ROW(27:27))), "")} | I30: {=IFERROR(INDEX('Bank Schedule'!I:I, SMALL(IF('Bank Schedule'!$K$2:$K$825="Vacant", ROW('Bank Schedule'!$K$2:$K$825)), ROW(27:27))), "")} | J30: {=IFERROR(INDEX('Bank Schedule'!J:J, SMALL(IF('Bank Schedule'!$K$2:$K$825="Vacant", ROW('Bank Schedule'!$K$2:$K$825)), ROW(27:27))), "")} | K30: {=IFERROR(INDEX('Bank Schedule'!K:K, SMALL(IF('Bank Schedule'!$K$2:$K$825="Vacant", ROW('Bank Schedule'!$K$2:$K$825)), ROW(27:27))), "")} | L30: {=IFERROR(INDEX('Bank Schedule'!L:L, SMALL(IF('Bank Schedule'!$K$2:$K$825="Vacant", ROW('Bank Schedule'!$K$2:$K$825)), ROW(27:27))), "")} | M30: {=IFERROR(INDEX('Bank Schedule'!M:M, SMALL(IF('Bank Schedule'!$K$2:$K$825="Vacant", ROW('Bank Schedule'!$K$2:$K$825)), ROW(27:27))), "")} | N30: {=IFERROR(INDEX('Bank Schedule'!N:N, SMALL(IF('Bank Schedule'!$K$2:$K$825="Vacant", ROW('Bank Schedule'!$K$2:$K$825)), ROW(27:27))), "")} | O30: {=IFERROR(INDEX('Bank Schedule'!O:O, SMALL(IF('Bank Schedule'!$K$2:$K$825="Vacant", ROW('Bank Schedule'!$K$2:$K$825)), ROW(27:27))), "")} | P30: {=IFERROR(INDEX('Bank Schedule'!P:P, SMALL(IF('Bank Schedule'!$K$2:$K$825="Vacant", ROW('Bank Schedule'!$K$2:$K$825)), ROW(27:27))), "")} | Q30: {=IFERROR(INDEX('Bank Schedule'!Q:Q, SMALL(IF('Bank Schedule'!$K$2:$K$825="Vacant", ROW('Bank Schedule'!$K$2:$K$825)), ROW(27:27))), "")} | R30: {=IFERROR(INDEX('Bank Schedule'!R:R, SMALL(IF('Bank Schedule'!$K$2:$K$825="Vacant", ROW('Bank Schedule'!$K$2:$K$825)), ROW(27:27))), "")} | S30: {=IFERROR(INDEX('Bank Schedule'!S:S, SMALL(IF('Bank Schedule'!$K$2:$K$825="Vacant", ROW('Bank Schedule'!$K$2:$K$825)), ROW(27:27))), "")} | T30: {=IFERROR(INDEX('Bank Schedule'!T:T, SMALL(IF('Bank Schedule'!$K$2:$K$825="Vacant", ROW('Bank Schedule'!$K$2:$K$825)), ROW(27:27))), "")} | U30: {=IFERROR(INDEX('Bank Schedule'!U:U, SMALL(IF('Bank Schedule'!$K$2:$K$825="Vacant", ROW('Bank Schedule'!$K$2:$K$825)), ROW(27:27))), "")} | V30: {=IFERROR(INDEX('Bank Schedule'!V:V, SMALL(IF('Bank Schedule'!$K$2:$K$825="Vacant", ROW('Bank Schedule'!$K$2:$K$825)), ROW(27:27))), "")} | W30: {=IFERROR(INDEX('Bank Schedule'!W:W, SMALL(IF('Bank Schedule'!$K$2:$K$825="Vacant", ROW('Bank Schedule'!$K$2:$K$825)), ROW(27:27))), "")} | X30: {=IFERROR(INDEX('Bank Schedule'!X:X, SMALL(IF('Bank Schedule'!$K$2:$K$825="Vacant", ROW('Bank Schedule'!$K$2:$K$825)), ROW(27:27))), "")} | Y30: {=IFERROR(INDEX('Bank Schedule'!Y:Y, SMALL(IF('Bank Schedule'!$K$2:$K$825="Vacant", ROW('Bank Schedule'!$K$2:$K$825)), ROW(27:27))), "")} | Z30: {=IFERROR(INDEX('Bank Schedule'!Z:Z, SMALL(IF('Bank Schedule'!$K$2:$K$825="Vacant", ROW('Bank Schedule'!$K$2:$K$825)), ROW(27:27))), "")} | AA30: {=IFERROR(INDEX('Bank Schedule'!AA:AA, SMALL(IF('Bank Schedule'!$K$2:$K$825="Vacant", ROW('Bank Schedule'!$K$2:$K$825)), ROW(27:27))), "")} | AB30: {=IFERROR(INDEX('Bank Schedule'!AB:AB, SMALL(IF('Bank Schedule'!$K$2:$K$825="Vacant", ROW('Bank Schedule'!$K$2:$K$825)), ROW(27:27))), "")} | AC30: {=IFERROR(INDEX('Bank Schedule'!AC:AC, SMALL(IF('Bank Schedule'!$K$2:$K$825="Vacant", ROW('Bank Schedule'!$K$2:$K$825)), ROW(27:27))), "")} | AD30: {=IFERROR(INDEX('Bank Schedule'!AD:AD, SMALL(IF('Bank Schedule'!$K$2:$K$825="Vacant", ROW('Bank Schedule'!$K$2:$K$825)), ROW(27:27))), "")} | AE30: {=IFERROR(INDEX('Bank Schedule'!AE:AE, SMALL(IF('Bank Schedule'!$K$2:$K$825="Vacant", ROW('Bank Schedule'!$K$2:$K$825)), ROW(27:27))), "")} | AF30: {=IFERROR(INDEX('Bank Schedule'!AF:AF, SMALL(IF('Bank Schedule'!$K$2:$K$825="Vacant", ROW('Bank Schedule'!$K$2:$K$825)), ROW(27:27))), "")} | AG30: {=IFERROR(INDEX('Bank Schedule'!AG:AG, SMALL(IF('Bank Schedule'!$K$2:$K$825="Vacant", ROW('Bank Schedule'!$K$2:$K$825)), ROW(27:27))), "")} | AH30: {=IFERROR(INDEX('Bank Schedule'!AH:AH, SMALL(IF('Bank Schedule'!$K$2:$K$825="Vacant", ROW('Bank Schedule'!$K$2:$K$825)), ROW(27:27))), "")}
A31: {=IFERROR(INDEX('Bank Schedule'!A:A, SMALL(IF('Bank Schedule'!$K$2:$K$825="Vacant", ROW('Bank Schedule'!$K$2:$K$825)), ROW(28:28))), "")} | B31: {=IFERROR(INDEX('Bank Schedule'!B:B, SMALL(IF('Bank Schedule'!$K$2:$K$825="Vacant", ROW('Bank Schedule'!$K$2:$K$825)), ROW(28:28))), "")} | C31: {=IFERROR(INDEX('Bank Schedule'!C:C, SMALL(IF('Bank Schedule'!$K$2:$K$825="Vacant", ROW('Bank Schedule'!$K$2:$K$825)), ROW(28:28))), "")} | D31: {=IFERROR(INDEX('Bank Schedule'!D:D, SMALL(IF('Bank Schedule'!$K$2:$K$825="Vacant", ROW('Bank Schedule'!$K$2:$K$825)), ROW(28:28))), "")} | E31: {=IFERROR(INDEX('Bank Schedule'!E:E, SMALL(IF('Bank Schedule'!$K$2:$K$825="Vacant", ROW('Bank Schedule'!$K$2:$K$825)), ROW(28:28))), "")} | F31: {=IFERROR(INDEX('Bank Schedule'!F:F, SMALL(IF('Bank Schedule'!$K$2:$K$825="Vacant", ROW('Bank Schedule'!$K$2:$K$825)), ROW(28:28))), "")} | G31: {=IFERROR(INDEX('Bank Schedule'!G:G, SMALL(IF('Bank Schedule'!$K$2:$K$825="Vacant", ROW('Bank Schedule'!$K$2:$K$825)), ROW(28:28))), "")} | H31: {=IFERROR(INDEX('Bank Schedule'!H:H, SMALL(IF('Bank Schedule'!$K$2:$K$825="Vacant", ROW('Bank Schedule'!$K$2:$K$825)), ROW(28:28))), "")} | I31: {=IFERROR(INDEX('Bank Schedule'!I:I, SMALL(IF('Bank Schedule'!$K$2:$K$825="Vacant", ROW('Bank Schedule'!$K$2:$K$825)), ROW(28:28))), "")} | J31: {=IFERROR(INDEX('Bank Schedule'!J:J, SMALL(IF('Bank Schedule'!$K$2:$K$825="Vacant", ROW('Bank Schedule'!$K$2:$K$825)), ROW(28:28))), "")} | K31: {=IFERROR(INDEX('Bank Schedule'!K:K, SMALL(IF('Bank Schedule'!$K$2:$K$825="Vacant", ROW('Bank Schedule'!$K$2:$K$825)), ROW(28:28))), "")} | L31: {=IFERROR(INDEX('Bank Schedule'!L:L, SMALL(IF('Bank Schedule'!$K$2:$K$825="Vacant", ROW('Bank Schedule'!$K$2:$K$825)), ROW(28:28))), "")} | M31: {=IFERROR(INDEX('Bank Schedule'!M:M, SMALL(IF('Bank Schedule'!$K$2:$K$825="Vacant", ROW('Bank Schedule'!$K$2:$K$825)), ROW(28:28))), "")} | N31: {=IFERROR(INDEX('Bank Schedule'!N:N, SMALL(IF('Bank Schedule'!$K$2:$K$825="Vacant", ROW('Bank Schedule'!$K$2:$K$825)), ROW(28:28))), "")} | O31: {=IFERROR(INDEX('Bank Schedule'!O:O, SMALL(IF('Bank Schedule'!$K$2:$K$825="Vacant", ROW('Bank Schedule'!$K$2:$K$825)), ROW(28:28))), "")} | P31: {=IFERROR(INDEX('Bank Schedule'!P:P, SMALL(IF('Bank Schedule'!$K$2:$K$825="Vacant", ROW('Bank Schedule'!$K$2:$K$825)), ROW(28:28))), "")} | Q31: {=IFERROR(INDEX('Bank Schedule'!Q:Q, SMALL(IF('Bank Schedule'!$K$2:$K$825="Vacant", ROW('Bank Schedule'!$K$2:$K$825)), ROW(28:28))), "")} | R31: {=IFERROR(INDEX('Bank Schedule'!R:R, SMALL(IF('Bank Schedule'!$K$2:$K$825="Vacant", ROW('Bank Schedule'!$K$2:$K$825)), ROW(28:28))), "")} | S31: {=IFERROR(INDEX('Bank Schedule'!S:S, SMALL(IF('Bank Schedule'!$K$2:$K$825="Vacant", ROW('Bank Schedule'!$K$2:$K$825)), ROW(28:28))), "")} | T31: {=IFERROR(INDEX('Bank Schedule'!T:T, SMALL(IF('Bank Schedule'!$K$2:$K$825="Vacant", ROW('Bank Schedule'!$K$2:$K$825)), ROW(28:28))), "")} | U31: {=IFERROR(INDEX('Bank Schedule'!U:U, SMALL(IF('Bank Schedule'!$K$2:$K$825="Vacant", ROW('Bank Schedule'!$K$2:$K$825)), ROW(28:28))), "")} | V31: {=IFERROR(INDEX('Bank Schedule'!V:V, SMALL(IF('Bank Schedule'!$K$2:$K$825="Vacant", ROW('Bank Schedule'!$K$2:$K$825)), ROW(28:28))), "")} | W31: {=IFERROR(INDEX('Bank Schedule'!W:W, SMALL(IF('Bank Schedule'!$K$2:$K$825="Vacant", ROW('Bank Schedule'!$K$2:$K$825)), ROW(28:28))), "")} | X31: {=IFERROR(INDEX('Bank Schedule'!X:X, SMALL(IF('Bank Schedule'!$K$2:$K$825="Vacant", ROW('Bank Schedule'!$K$2:$K$825)), ROW(28:28))), "")} | Y31: {=IFERROR(INDEX('Bank Schedule'!Y:Y, SMALL(IF('Bank Schedule'!$K$2:$K$825="Vacant", ROW('Bank Schedule'!$K$2:$K$825)), ROW(28:28))), "")} | Z31: {=IFERROR(INDEX('Bank Schedule'!Z:Z, SMALL(IF('Bank Schedule'!$K$2:$K$825="Vacant", ROW('Bank Schedule'!$K$2:$K$825)), ROW(28:28))), "")} | AA31: {=IFERROR(INDEX('Bank Schedule'!AA:AA, SMALL(IF('Bank Schedule'!$K$2:$K$825="Vacant", ROW('Bank Schedule'!$K$2:$K$825)), ROW(28:28))), "")} | AB31: {=IFERROR(INDEX('Bank Schedule'!AB:AB, SMALL(IF('Bank Schedule'!$K$2:$K$825="Vacant", ROW('Bank Schedule'!$K$2:$K$825)), ROW(28:28))), "")} | AC31: {=IFERROR(INDEX('Bank Schedule'!AC:AC, SMALL(IF('Bank Schedule'!$K$2:$K$825="Vacant", ROW('Bank Schedule'!$K$2:$K$825)), ROW(28:28))), "")} | AD31: {=IFERROR(INDEX('Bank Schedule'!AD:AD, SMALL(IF('Bank Schedule'!$K$2:$K$825="Vacant", ROW('Bank Schedule'!$K$2:$K$825)), ROW(28:28))), "")} | AE31: {=IFERROR(INDEX('Bank Schedule'!AE:AE, SMALL(IF('Bank Schedule'!$K$2:$K$825="Vacant", ROW('Bank Schedule'!$K$2:$K$825)), ROW(28:28))), "")} | AF31: {=IFERROR(INDEX('Bank Schedule'!AF:AF, SMALL(IF('Bank Schedule'!$K$2:$K$825="Vacant", ROW('Bank Schedule'!$K$2:$K$825)), ROW(28:28))), "")} | AG31: {=IFERROR(INDEX('Bank Schedule'!AG:AG, SMALL(IF('Bank Schedule'!$K$2:$K$825="Vacant", ROW('Bank Schedule'!$K$2:$K$825)), ROW(28:28))), "")} | AH31: {=IFERROR(INDEX('Bank Schedule'!AH:AH, SMALL(IF('Bank Schedule'!$K$2:$K$825="Vacant", ROW('Bank Schedule'!$K$2:$K$825)), ROW(28:28))), "")}
A32: {=IFERROR(INDEX('Bank Schedule'!A:A, SMALL(IF('Bank Schedule'!$K$2:$K$825="Vacant", ROW('Bank Schedule'!$K$2:$K$825)), ROW(29:29))), "")} | B32: {=IFERROR(INDEX('Bank Schedule'!B:B, SMALL(IF('Bank Schedule'!$K$2:$K$825="Vacant", ROW('Bank Schedule'!$K$2:$K$825)), ROW(29:29))), "")} | C32: {=IFERROR(INDEX('Bank Schedule'!C:C, SMALL(IF('Bank Schedule'!$K$2:$K$825="Vacant", ROW('Bank Schedule'!$K$2:$K$825)), ROW(29:29))), "")} | D32: {=IFERROR(INDEX('Bank Schedule'!D:D, SMALL(IF('Bank Schedule'!$K$2:$K$825="Vacant", ROW('Bank Schedule'!$K$2:$K$825)), ROW(29:29))), "")} | E32: {=IFERROR(INDEX('Bank Schedule'!E:E, SMALL(IF('Bank Schedule'!$K$2:$K$825="Vacant", ROW('Bank Schedule'!$K$2:$K$825)), ROW(29:29))), "")} | F32: {=IFERROR(INDEX('Bank Schedule'!F:F, SMALL(IF('Bank Schedule'!$K$2:$K$825="Vacant", ROW('Bank Schedule'!$K$2:$K$825)), ROW(29:29))), "")} | G32: {=IFERROR(INDEX('Bank Schedule'!G:G, SMALL(IF('Bank Schedule'!$K$2:$K$825="Vacant", ROW('Bank Schedule'!$K$2:$K$825)), ROW(29:29))), "")} | H32: {=IFERROR(INDEX('Bank Schedule'!H:H, SMALL(IF('Bank Schedule'!$K$2:$K$825="Vacant", ROW('Bank Schedule'!$K$2:$K$825)), ROW(29:29))), "")} | I32: {=IFERROR(INDEX('Bank Schedule'!I:I, SMALL(IF('Bank Schedule'!$K$2:$K$825="Vacant", ROW('Bank Schedule'!$K$2:$K$825)), ROW(29:29))), "")} | J32: {=IFERROR(INDEX('Bank Schedule'!J:J, SMALL(IF('Bank Schedule'!$K$2:$K$825="Vacant", ROW('Bank Schedule'!$K$2:$K$825)), ROW(29:29))), "")} | K32: {=IFERROR(INDEX('Bank Schedule'!K:K, SMALL(IF('Bank Schedule'!$K$2:$K$825="Vacant", ROW('Bank Schedule'!$K$2:$K$825)), ROW(29:29))), "")} | L32: {=IFERROR(INDEX('Bank Schedule'!L:L, SMALL(IF('Bank Schedule'!$K$2:$K$825="Vacant", ROW('Bank Schedule'!$K$2:$K$825)), ROW(29:29))), "")} | M32: {=IFERROR(INDEX('Bank Schedule'!M:M, SMALL(IF('Bank Schedule'!$K$2:$K$825="Vacant", ROW('Bank Schedule'!$K$2:$K$825)), ROW(29:29))), "")} | N32: {=IFERROR(INDEX('Bank Schedule'!N:N, SMALL(IF('Bank Schedule'!$K$2:$K$825="Vacant", ROW('Bank Schedule'!$K$2:$K$825)), ROW(29:29))), "")} | O32: {=IFERROR(INDEX('Bank Schedule'!O:O, SMALL(IF('Bank Schedule'!$K$2:$K$825="Vacant", ROW('Bank Schedule'!$K$2:$K$825)), ROW(29:29))), "")} | P32: {=IFERROR(INDEX('Bank Schedule'!P:P, SMALL(IF('Bank Schedule'!$K$2:$K$825="Vacant", ROW('Bank Schedule'!$K$2:$K$825)), ROW(29:29))), "")} | Q32: {=IFERROR(INDEX('Bank Schedule'!Q:Q, SMALL(IF('Bank Schedule'!$K$2:$K$825="Vacant", ROW('Bank Schedule'!$K$2:$K$825)), ROW(29:29))), "")} | R32: {=IFERROR(INDEX('Bank Schedule'!R:R, SMALL(IF('Bank Schedule'!$K$2:$K$825="Vacant", ROW('Bank Schedule'!$K$2:$K$825)), ROW(29:29))), "")} | S32: {=IFERROR(INDEX('Bank Schedule'!S:S, SMALL(IF('Bank Schedule'!$K$2:$K$825="Vacant", ROW('Bank Schedule'!$K$2:$K$825)), ROW(29:29))), "")} | T32: {=IFERROR(INDEX('Bank Schedule'!T:T, SMALL(IF('Bank Schedule'!$K$2:$K$825="Vacant", ROW('Bank Schedule'!$K$2:$K$825)), ROW(29:29))), "")} | U32: {=IFERROR(INDEX('Bank Schedule'!U:U, SMALL(IF('Bank Schedule'!$K$2:$K$825="Vacant", ROW('Bank Schedule'!$K$2:$K$825)), ROW(29:29))), "")} | V32: {=IFERROR(INDEX('Bank Schedule'!V:V, SMALL(IF('Bank Schedule'!$K$2:$K$825="Vacant", ROW('Bank Schedule'!$K$2:$K$825)), ROW(29:29))), "")} | W32: {=IFERROR(INDEX('Bank Schedule'!W:W, SMALL(IF('Bank Schedule'!$K$2:$K$825="Vacant", ROW('Bank Schedule'!$K$2:$K$825)), ROW(29:29))), "")} | X32: {=IFERROR(INDEX('Bank Schedule'!X:X, SMALL(IF('Bank Schedule'!$K$2:$K$825="Vacant", ROW('Bank Schedule'!$K$2:$K$825)), ROW(29:29))), "")} | Y32: {=IFERROR(INDEX('Bank Schedule'!Y:Y, SMALL(IF('Bank Schedule'!$K$2:$K$825="Vacant", ROW('Bank Schedule'!$K$2:$K$825)), ROW(29:29))), "")} | Z32: {=IFERROR(INDEX('Bank Schedule'!Z:Z, SMALL(IF('Bank Schedule'!$K$2:$K$825="Vacant", ROW('Bank Schedule'!$K$2:$K$825)), ROW(29:29))), "")} | AA32: {=IFERROR(INDEX('Bank Schedule'!AA:AA, SMALL(IF('Bank Schedule'!$K$2:$K$825="Vacant", ROW('Bank Schedule'!$K$2:$K$825)), ROW(29:29))), "")} | AB32: {=IFERROR(INDEX('Bank Schedule'!AB:AB, SMALL(IF('Bank Schedule'!$K$2:$K$825="Vacant", ROW('Bank Schedule'!$K$2:$K$825)), ROW(29:29))), "")} | AC32: {=IFERROR(INDEX('Bank Schedule'!AC:AC, SMALL(IF('Bank Schedule'!$K$2:$K$825="Vacant", ROW('Bank Schedule'!$K$2:$K$825)), ROW(29:29))), "")} | AD32: {=IFERROR(INDEX('Bank Schedule'!AD:AD, SMALL(IF('Bank Schedule'!$K$2:$K$825="Vacant", ROW('Bank Schedule'!$K$2:$K$825)), ROW(29:29))), "")} | AE32: {=IFERROR(INDEX('Bank Schedule'!AE:AE, SMALL(IF('Bank Schedule'!$K$2:$K$825="Vacant", ROW('Bank Schedule'!$K$2:$K$825)), ROW(29:29))), "")} | AF32: {=IFERROR(INDEX('Bank Schedule'!AF:AF, SMALL(IF('Bank Schedule'!$K$2:$K$825="Vacant", ROW('Bank Schedule'!$K$2:$K$825)), ROW(29:29))), "")} | AG32: {=IFERROR(INDEX('Bank Schedule'!AG:AG, SMALL(IF('Bank Schedule'!$K$2:$K$825="Vacant", ROW('Bank Schedule'!$K$2:$K$825)), ROW(29:29))), "")} | AH32: {=IFERROR(INDEX('Bank Schedule'!AH:AH, SMALL(IF('Bank Schedule'!$K$2:$K$825="Vacant", ROW('Bank Schedule'!$K$2:$K$825)), ROW(29:29))), "")}
A33: {=IFERROR(INDEX('Bank Schedule'!A:A, SMALL(IF('Bank Schedule'!$K$2:$K$825="Vacant", ROW('Bank Schedule'!$K$2:$K$825)), ROW(30:30))), "")} | B33: {=IFERROR(INDEX('Bank Schedule'!B:B, SMALL(IF('Bank Schedule'!$K$2:$K$825="Vacant", ROW('Bank Schedule'!$K$2:$K$825)), ROW(30:30))), "")} | C33: {=IFERROR(INDEX('Bank Schedule'!C:C, SMALL(IF('Bank Schedule'!$K$2:$K$825="Vacant", ROW('Bank Schedule'!$K$2:$K$825)), ROW(30:30))), "")} | D33: {=IFERROR(INDEX('Bank Schedule'!D:D, SMALL(IF('Bank Schedule'!$K$2:$K$825="Vacant", ROW('Bank Schedule'!$K$2:$K$825)), ROW(30:30))), "")} | E33: {=IFERROR(INDEX('Bank Schedule'!E:E, SMALL(IF('Bank Schedule'!$K$2:$K$825="Vacant", ROW('Bank Schedule'!$K$2:$K$825)), ROW(30:30))), "")} | F33: {=IFERROR(INDEX('Bank Schedule'!F:F, SMALL(IF('Bank Schedule'!$K$2:$K$825="Vacant", ROW('Bank Schedule'!$K$2:$K$825)), ROW(30:30))), "")} | G33: {=IFERROR(INDEX('Bank Schedule'!G:G, SMALL(IF('Bank Schedule'!$K$2:$K$825="Vacant", ROW('Bank Schedule'!$K$2:$K$825)), ROW(30:30))), "")} | H33: {=IFERROR(INDEX('Bank Schedule'!H:H, SMALL(IF('Bank Schedule'!$K$2:$K$825="Vacant", ROW('Bank Schedule'!$K$2:$K$825)), ROW(30:30))), "")} | I33: {=IFERROR(INDEX('Bank Schedule'!I:I, SMALL(IF('Bank Schedule'!$K$2:$K$825="Vacant", ROW('Bank Schedule'!$K$2:$K$825)), ROW(30:30))), "")} | J33: {=IFERROR(INDEX('Bank Schedule'!J:J, SMALL(IF('Bank Schedule'!$K$2:$K$825="Vacant", ROW('Bank Schedule'!$K$2:$K$825)), ROW(30:30))), "")} | K33: {=IFERROR(INDEX('Bank Schedule'!K:K, SMALL(IF('Bank Schedule'!$K$2:$K$825="Vacant", ROW('Bank Schedule'!$K$2:$K$825)), ROW(30:30))), "")} | L33: {=IFERROR(INDEX('Bank Schedule'!L:L, SMALL(IF('Bank Schedule'!$K$2:$K$825="Vacant", ROW('Bank Schedule'!$K$2:$K$825)), ROW(30:30))), "")} | M33: {=IFERROR(INDEX('Bank Schedule'!M:M, SMALL(IF('Bank Schedule'!$K$2:$K$825="Vacant", ROW('Bank Schedule'!$K$2:$K$825)), ROW(30:30))), "")} | N33: {=IFERROR(INDEX('Bank Schedule'!N:N, SMALL(IF('Bank Schedule'!$K$2:$K$825="Vacant", ROW('Bank Schedule'!$K$2:$K$825)), ROW(30:30))), "")} | O33: {=IFERROR(INDEX('Bank Schedule'!O:O, SMALL(IF('Bank Schedule'!$K$2:$K$825="Vacant", ROW('Bank Schedule'!$K$2:$K$825)), ROW(30:30))), "")} | P33: {=IFERROR(INDEX('Bank Schedule'!P:P, SMALL(IF('Bank Schedule'!$K$2:$K$825="Vacant", ROW('Bank Schedule'!$K$2:$K$825)), ROW(30:30))), "")} | Q33: {=IFERROR(INDEX('Bank Schedule'!Q:Q, SMALL(IF('Bank Schedule'!$K$2:$K$825="Vacant", ROW('Bank Schedule'!$K$2:$K$825)), ROW(30:30))), "")} | R33: {=IFERROR(INDEX('Bank Schedule'!R:R, SMALL(IF('Bank Schedule'!$K$2:$K$825="Vacant", ROW('Bank Schedule'!$K$2:$K$825)), ROW(30:30))), "")} | S33: {=IFERROR(INDEX('Bank Schedule'!S:S, SMALL(IF('Bank Schedule'!$K$2:$K$825="Vacant", ROW('Bank Schedule'!$K$2:$K$825)), ROW(30:30))), "")} | T33: {=IFERROR(INDEX('Bank Schedule'!T:T, SMALL(IF('Bank Schedule'!$K$2:$K$825="Vacant", ROW('Bank Schedule'!$K$2:$K$825)), ROW(30:30))), "")} | U33: {=IFERROR(INDEX('Bank Schedule'!U:U, SMALL(IF('Bank Schedule'!$K$2:$K$825="Vacant", ROW('Bank Schedule'!$K$2:$K$825)), ROW(30:30))), "")} | V33: {=IFERROR(INDEX('Bank Schedule'!V:V, SMALL(IF('Bank Schedule'!$K$2:$K$825="Vacant", ROW('Bank Schedule'!$K$2:$K$825)), ROW(30:30))), "")} | W33: {=IFERROR(INDEX('Bank Schedule'!W:W, SMALL(IF('Bank Schedule'!$K$2:$K$825="Vacant", ROW('Bank Schedule'!$K$2:$K$825)), ROW(30:30))), "")} | X33: {=IFERROR(INDEX('Bank Schedule'!X:X, SMALL(IF('Bank Schedule'!$K$2:$K$825="Vacant", ROW('Bank Schedule'!$K$2:$K$825)), ROW(30:30))), "")} | Y33: {=IFERROR(INDEX('Bank Schedule'!Y:Y, SMALL(IF('Bank Schedule'!$K$2:$K$825="Vacant", ROW('Bank Schedule'!$K$2:$K$825)), ROW(30:30))), "")} | Z33: {=IFERROR(INDEX('Bank Schedule'!Z:Z, SMALL(IF('Bank Schedule'!$K$2:$K$825="Vacant", ROW('Bank Schedule'!$K$2:$K$825)), ROW(30:30))), "")} | AA33: {=IFERROR(INDEX('Bank Schedule'!AA:AA, SMALL(IF('Bank Schedule'!$K$2:$K$825="Vacant", ROW('Bank Schedule'!$K$2:$K$825)), ROW(30:30))), "")} | AB33: {=IFERROR(INDEX('Bank Schedule'!AB:AB, SMALL(IF('Bank Schedule'!$K$2:$K$825="Vacant", ROW('Bank Schedule'!$K$2:$K$825)), ROW(30:30))), "")} | AC33: {=IFERROR(INDEX('Bank Schedule'!AC:AC, SMALL(IF('Bank Schedule'!$K$2:$K$825="Vacant", ROW('Bank Schedule'!$K$2:$K$825)), ROW(30:30))), "")} | AD33: {=IFERROR(INDEX('Bank Schedule'!AD:AD, SMALL(IF('Bank Schedule'!$K$2:$K$825="Vacant", ROW('Bank Schedule'!$K$2:$K$825)), ROW(30:30))), "")} | AE33: {=IFERROR(INDEX('Bank Schedule'!AE:AE, SMALL(IF('Bank Schedule'!$K$2:$K$825="Vacant", ROW('Bank Schedule'!$K$2:$K$825)), ROW(30:30))), "")} | AF33: {=IFERROR(INDEX('Bank Schedule'!AF:AF, SMALL(IF('Bank Schedule'!$K$2:$K$825="Vacant", ROW('Bank Schedule'!$K$2:$K$825)), ROW(30:30))), "")} | AG33: {=IFERROR(INDEX('Bank Schedule'!AG:AG, SMALL(IF('Bank Schedule'!$K$2:$K$825="Vacant", ROW('Bank Schedule'!$K$2:$K$825)), ROW(30:30))), "")} | AH33: {=IFERROR(INDEX('Bank Schedule'!AH:AH, SMALL(IF('Bank Schedule'!$K$2:$K$825="Vacant", ROW('Bank Schedule'!$K$2:$K$825)), ROW(30:30))), "")}
A34: {=IFERROR(INDEX('Bank Schedule'!A:A, SMALL(IF('Bank Schedule'!$K$2:$K$825="Vacant", ROW('Bank Schedule'!$K$2:$K$825)), ROW(31:31))), "")} | B34: {=IFERROR(INDEX('Bank Schedule'!B:B, SMALL(IF('Bank Schedule'!$K$2:$K$825="Vacant", ROW('Bank Schedule'!$K$2:$K$825)), ROW(31:31))), "")} | C34: {=IFERROR(INDEX('Bank Schedule'!C:C, SMALL(IF('Bank Schedule'!$K$2:$K$825="Vacant", ROW('Bank Schedule'!$K$2:$K$825)), ROW(31:31))), "")} | D34: {=IFERROR(INDEX('Bank Schedule'!D:D, SMALL(IF('Bank Schedule'!$K$2:$K$825="Vacant", ROW('Bank Schedule'!$K$2:$K$825)), ROW(31:31))), "")} | E34: {=IFERROR(INDEX('Bank Schedule'!E:E, SMALL(IF('Bank Schedule'!$K$2:$K$825="Vacant", ROW('Bank Schedule'!$K$2:$K$825)), ROW(31:31))), "")} | F34: {=IFERROR(INDEX('Bank Schedule'!F:F, SMALL(IF('Bank Schedule'!$K$2:$K$825="Vacant", ROW('Bank Schedule'!$K$2:$K$825)), ROW(31:31))), "")} | G34: {=IFERROR(INDEX('Bank Schedule'!G:G, SMALL(IF('Bank Schedule'!$K$2:$K$825="Vacant", ROW('Bank Schedule'!$K$2:$K$825)), ROW(31:31))), "")} | H34: {=IFERROR(INDEX('Bank Schedule'!H:H, SMALL(IF('Bank Schedule'!$K$2:$K$825="Vacant", ROW('Bank Schedule'!$K$2:$K$825)), ROW(31:31))), "")} | I34: {=IFERROR(INDEX('Bank Schedule'!I:I, SMALL(IF('Bank Schedule'!$K$2:$K$825="Vacant", ROW('Bank Schedule'!$K$2:$K$825)), ROW(31:31))), "")} | J34: {=IFERROR(INDEX('Bank Schedule'!J:J, SMALL(IF('Bank Schedule'!$K$2:$K$825="Vacant", ROW('Bank Schedule'!$K$2:$K$825)), ROW(31:31))), "")} | K34: {=IFERROR(INDEX('Bank Schedule'!K:K, SMALL(IF('Bank Schedule'!$K$2:$K$825="Vacant", ROW('Bank Schedule'!$K$2:$K$825)), ROW(31:31))), "")} | L34: {=IFERROR(INDEX('Bank Schedule'!L:L, SMALL(IF('Bank Schedule'!$K$2:$K$825="Vacant", ROW('Bank Schedule'!$K$2:$K$825)), ROW(31:31))), "")} | M34: {=IFERROR(INDEX('Bank Schedule'!M:M, SMALL(IF('Bank Schedule'!$K$2:$K$825="Vacant", ROW('Bank Schedule'!$K$2:$K$825)), ROW(31:31))), "")} | N34: {=IFERROR(INDEX('Bank Schedule'!N:N, SMALL(IF('Bank Schedule'!$K$2:$K$825="Vacant", ROW('Bank Schedule'!$K$2:$K$825)), ROW(31:31))), "")} | O34: {=IFERROR(INDEX('Bank Schedule'!O:O, SMALL(IF('Bank Schedule'!$K$2:$K$825="Vacant", ROW('Bank Schedule'!$K$2:$K$825)), ROW(31:31))), "")} | P34: {=IFERROR(INDEX('Bank Schedule'!P:P, SMALL(IF('Bank Schedule'!$K$2:$K$825="Vacant", ROW('Bank Schedule'!$K$2:$K$825)), ROW(31:31))), "")} | Q34: {=IFERROR(INDEX('Bank Schedule'!Q:Q, SMALL(IF('Bank Schedule'!$K$2:$K$825="Vacant", ROW('Bank Schedule'!$K$2:$K$825)), ROW(31:31))), "")} | R34: {=IFERROR(INDEX('Bank Schedule'!R:R, SMALL(IF('Bank Schedule'!$K$2:$K$825="Vacant", ROW('Bank Schedule'!$K$2:$K$825)), ROW(31:31))), "")} | S34: {=IFERROR(INDEX('Bank Schedule'!S:S, SMALL(IF('Bank Schedule'!$K$2:$K$825="Vacant", ROW('Bank Schedule'!$K$2:$K$825)), ROW(31:31))), "")} | T34: {=IFERROR(INDEX('Bank Schedule'!T:T, SMALL(IF('Bank Schedule'!$K$2:$K$825="Vacant", ROW('Bank Schedule'!$K$2:$K$825)), ROW(31:31))), "")} | U34: {=IFERROR(INDEX('Bank Schedule'!U:U, SMALL(IF('Bank Schedule'!$K$2:$K$825="Vacant", ROW('Bank Schedule'!$K$2:$K$825)), ROW(31:31))), "")} | V34: {=IFERROR(INDEX('Bank Schedule'!V:V, SMALL(IF('Bank Schedule'!$K$2:$K$825="Vacant", ROW('Bank Schedule'!$K$2:$K$825)), ROW(31:31))), "")} | W34: {=IFERROR(INDEX('Bank Schedule'!W:W, SMALL(IF('Bank Schedule'!$K$2:$K$825="Vacant", ROW('Bank Schedule'!$K$2:$K$825)), ROW(31:31))), "")} | X34: {=IFERROR(INDEX('Bank Schedule'!X:X, SMALL(IF('Bank Schedule'!$K$2:$K$825="Vacant", ROW('Bank Schedule'!$K$2:$K$825)), ROW(31:31))), "")} | Y34: {=IFERROR(INDEX('Bank Schedule'!Y:Y, SMALL(IF('Bank Schedule'!$K$2:$K$825="Vacant", ROW('Bank Schedule'!$K$2:$K$825)), ROW(31:31))), "")} | Z34: {=IFERROR(INDEX('Bank Schedule'!Z:Z, SMALL(IF('Bank Schedule'!$K$2:$K$825="Vacant", ROW('Bank Schedule'!$K$2:$K$825)), ROW(31:31))), "")} | AA34: {=IFERROR(INDEX('Bank Schedule'!AA:AA, SMALL(IF('Bank Schedule'!$K$2:$K$825="Vacant", ROW('Bank Schedule'!$K$2:$K$825)), ROW(31:31))), "")} | AB34: {=IFERROR(INDEX('Bank Schedule'!AB:AB, SMALL(IF('Bank Schedule'!$K$2:$K$825="Vacant", ROW('Bank Schedule'!$K$2:$K$825)), ROW(31:31))), "")} | AC34: {=IFERROR(INDEX('Bank Schedule'!AC:AC, SMALL(IF('Bank Schedule'!$K$2:$K$825="Vacant", ROW('Bank Schedule'!$K$2:$K$825)), ROW(31:31))), "")} | AD34: {=IFERROR(INDEX('Bank Schedule'!AD:AD, SMALL(IF('Bank Schedule'!$K$2:$K$825="Vacant", ROW('Bank Schedule'!$K$2:$K$825)), ROW(31:31))), "")} | AE34: {=IFERROR(INDEX('Bank Schedule'!AE:AE, SMALL(IF('Bank Schedule'!$K$2:$K$825="Vacant", ROW('Bank Schedule'!$K$2:$K$825)), ROW(31:31))), "")} | AF34: {=IFERROR(INDEX('Bank Schedule'!AF:AF, SMALL(IF('Bank Schedule'!$K$2:$K$825="Vacant", ROW('Bank Schedule'!$K$2:$K$825)), ROW(31:31))), "")} | AG34: {=IFERROR(INDEX('Bank Schedule'!AG:AG, SMALL(IF('Bank Schedule'!$K$2:$K$825="Vacant", ROW('Bank Schedule'!$K$2:$K$825)), ROW(31:31))), "")} | AH34: {=IFERROR(INDEX('Bank Schedule'!AH:AH, SMALL(IF('Bank Schedule'!$K$2:$K$825="Vacant", ROW('Bank Schedule'!$K$2:$K$825)), ROW(31:31))), "")}
A35: {=IFERROR(INDEX('Bank Schedule'!A:A, SMALL(IF('Bank Schedule'!$K$2:$K$825="Vacant", ROW('Bank Schedule'!$K$2:$K$825)), ROW(32:32))), "")} | B35: {=IFERROR(INDEX('Bank Schedule'!B:B, SMALL(IF('Bank Schedule'!$K$2:$K$825="Vacant", ROW('Bank Schedule'!$K$2:$K$825)), ROW(32:32))), "")} | C35: {=IFERROR(INDEX('Bank Schedule'!C:C, SMALL(IF('Bank Schedule'!$K$2:$K$825="Vacant", ROW('Bank Schedule'!$K$2:$K$825)), ROW(32:32))), "")} | D35: {=IFERROR(INDEX('Bank Schedule'!D:D, SMALL(IF('Bank Schedule'!$K$2:$K$825="Vacant", ROW('Bank Schedule'!$K$2:$K$825)), ROW(32:32))), "")} | E35: {=IFERROR(INDEX('Bank Schedule'!E:E, SMALL(IF('Bank Schedule'!$K$2:$K$825="Vacant", ROW('Bank Schedule'!$K$2:$K$825)), ROW(32:32))), "")} | F35: {=IFERROR(INDEX('Bank Schedule'!F:F, SMALL(IF('Bank Schedule'!$K$2:$K$825="Vacant", ROW('Bank Schedule'!$K$2:$K$825)), ROW(32:32))), "")} | G35: {=IFERROR(INDEX('Bank Schedule'!G:G, SMALL(IF('Bank Schedule'!$K$2:$K$825="Vacant", ROW('Bank Schedule'!$K$2:$K$825)), ROW(32:32))), "")} | H35: {=IFERROR(INDEX('Bank Schedule'!H:H, SMALL(IF('Bank Schedule'!$K$2:$K$825="Vacant", ROW('Bank Schedule'!$K$2:$K$825)), ROW(32:32))), "")} | I35: {=IFERROR(INDEX('Bank Schedule'!I:I, SMALL(IF('Bank Schedule'!$K$2:$K$825="Vacant", ROW('Bank Schedule'!$K$2:$K$825)), ROW(32:32))), "")} | J35: {=IFERROR(INDEX('Bank Schedule'!J:J, SMALL(IF('Bank Schedule'!$K$2:$K$825="Vacant", ROW('Bank Schedule'!$K$2:$K$825)), ROW(32:32))), "")} | K35: {=IFERROR(INDEX('Bank Schedule'!K:K, SMALL(IF('Bank Schedule'!$K$2:$K$825="Vacant", ROW('Bank Schedule'!$K$2:$K$825)), ROW(32:32))), "")} | L35: {=IFERROR(INDEX('Bank Schedule'!L:L, SMALL(IF('Bank Schedule'!$K$2:$K$825="Vacant", ROW('Bank Schedule'!$K$2:$K$825)), ROW(32:32))), "")} | M35: {=IFERROR(INDEX('Bank Schedule'!M:M, SMALL(IF('Bank Schedule'!$K$2:$K$825="Vacant", ROW('Bank Schedule'!$K$2:$K$825)), ROW(32:32))), "")} | N35: {=IFERROR(INDEX('Bank Schedule'!N:N, SMALL(IF('Bank Schedule'!$K$2:$K$825="Vacant", ROW('Bank Schedule'!$K$2:$K$825)), ROW(32:32))), "")} | O35: {=IFERROR(INDEX('Bank Schedule'!O:O, SMALL(IF('Bank Schedule'!$K$2:$K$825="Vacant", ROW('Bank Schedule'!$K$2:$K$825)), ROW(32:32))), "")} | P35: {=IFERROR(INDEX('Bank Schedule'!P:P, SMALL(IF('Bank Schedule'!$K$2:$K$825="Vacant", ROW('Bank Schedule'!$K$2:$K$825)), ROW(32:32))), "")} | Q35: {=IFERROR(INDEX('Bank Schedule'!Q:Q, SMALL(IF('Bank Schedule'!$K$2:$K$825="Vacant", ROW('Bank Schedule'!$K$2:$K$825)), ROW(32:32))), "")} | R35: {=IFERROR(INDEX('Bank Schedule'!R:R, SMALL(IF('Bank Schedule'!$K$2:$K$825="Vacant", ROW('Bank Schedule'!$K$2:$K$825)), ROW(32:32))), "")} | S35: {=IFERROR(INDEX('Bank Schedule'!S:S, SMALL(IF('Bank Schedule'!$K$2:$K$825="Vacant", ROW('Bank Schedule'!$K$2:$K$825)), ROW(32:32))), "")} | T35: {=IFERROR(INDEX('Bank Schedule'!T:T, SMALL(IF('Bank Schedule'!$K$2:$K$825="Vacant", ROW('Bank Schedule'!$K$2:$K$825)), ROW(32:32))), "")} | U35: {=IFERROR(INDEX('Bank Schedule'!U:U, SMALL(IF('Bank Schedule'!$K$2:$K$825="Vacant", ROW('Bank Schedule'!$K$2:$K$825)), ROW(32:32))), "")} | V35: {=IFERROR(INDEX('Bank Schedule'!V:V, SMALL(IF('Bank Schedule'!$K$2:$K$825="Vacant", ROW('Bank Schedule'!$K$2:$K$825)), ROW(32:32))), "")} | W35: {=IFERROR(INDEX('Bank Schedule'!W:W, SMALL(IF('Bank Schedule'!$K$2:$K$825="Vacant", ROW('Bank Schedule'!$K$2:$K$825)), ROW(32:32))), "")} | X35: {=IFERROR(INDEX('Bank Schedule'!X:X, SMALL(IF('Bank Schedule'!$K$2:$K$825="Vacant", ROW('Bank Schedule'!$K$2:$K$825)), ROW(32:32))), "")} | Y35: {=IFERROR(INDEX('Bank Schedule'!Y:Y, SMALL(IF('Bank Schedule'!$K$2:$K$825="Vacant", ROW('Bank Schedule'!$K$2:$K$825)), ROW(32:32))), "")} | Z35: {=IFERROR(INDEX('Bank Schedule'!Z:Z, SMALL(IF('Bank Schedule'!$K$2:$K$825="Vacant", ROW('Bank Schedule'!$K$2:$K$825)), ROW(32:32))), "")} | AA35: {=IFERROR(INDEX('Bank Schedule'!AA:AA, SMALL(IF('Bank Schedule'!$K$2:$K$825="Vacant", ROW('Bank Schedule'!$K$2:$K$825)), ROW(32:32))), "")} | AB35: {=IFERROR(INDEX('Bank Schedule'!AB:AB, SMALL(IF('Bank Schedule'!$K$2:$K$825="Vacant", ROW('Bank Schedule'!$K$2:$K$825)), ROW(32:32))), "")} | AC35: {=IFERROR(INDEX('Bank Schedule'!AC:AC, SMALL(IF('Bank Schedule'!$K$2:$K$825="Vacant", ROW('Bank Schedule'!$K$2:$K$825)), ROW(32:32))), "")} | AD35: {=IFERROR(INDEX('Bank Schedule'!AD:AD, SMALL(IF('Bank Schedule'!$K$2:$K$825="Vacant", ROW('Bank Schedule'!$K$2:$K$825)), ROW(32:32))), "")} | AE35: {=IFERROR(INDEX('Bank Schedule'!AE:AE, SMALL(IF('Bank Schedule'!$K$2:$K$825="Vacant", ROW('Bank Schedule'!$K$2:$K$825)), ROW(32:32))), "")} | AF35: {=IFERROR(INDEX('Bank Schedule'!AF:AF, SMALL(IF('Bank Schedule'!$K$2:$K$825="Vacant", ROW('Bank Schedule'!$K$2:$K$825)), ROW(32:32))), "")} | AG35: {=IFERROR(INDEX('Bank Schedule'!AG:AG, SMALL(IF('Bank Schedule'!$K$2:$K$825="Vacant", ROW('Bank Schedule'!$K$2:$K$825)), ROW(32:32))), "")} | AH35: {=IFERROR(INDEX('Bank Schedule'!AH:AH, SMALL(IF('Bank Schedule'!$K$2:$K$825="Vacant", ROW('Bank Schedule'!$K$2:$K$825)), ROW(32:32))), "")}
A36: {=IFERROR(INDEX('Bank Schedule'!A:A, SMALL(IF('Bank Schedule'!$K$2:$K$825="Vacant", ROW('Bank Schedule'!$K$2:$K$825)), ROW(33:33))), "")} | B36: {=IFERROR(INDEX('Bank Schedule'!B:B, SMALL(IF('Bank Schedule'!$K$2:$K$825="Vacant", ROW('Bank Schedule'!$K$2:$K$825)), ROW(33:33))), "")} | C36: {=IFERROR(INDEX('Bank Schedule'!C:C, SMALL(IF('Bank Schedule'!$K$2:$K$825="Vacant", ROW('Bank Schedule'!$K$2:$K$825)), ROW(33:33))), "")} | D36: {=IFERROR(INDEX('Bank Schedule'!D:D, SMALL(IF('Bank Schedule'!$K$2:$K$825="Vacant", ROW('Bank Schedule'!$K$2:$K$825)), ROW(33:33))), "")} | E36: {=IFERROR(INDEX('Bank Schedule'!E:E, SMALL(IF('Bank Schedule'!$K$2:$K$825="Vacant", ROW('Bank Schedule'!$K$2:$K$825)), ROW(33:33))), "")} | F36: {=IFERROR(INDEX('Bank Schedule'!F:F, SMALL(IF('Bank Schedule'!$K$2:$K$825="Vacant", ROW('Bank Schedule'!$K$2:$K$825)), ROW(33:33))), "")} | G36: {=IFERROR(INDEX('Bank Schedule'!G:G, SMALL(IF('Bank Schedule'!$K$2:$K$825="Vacant", ROW('Bank Schedule'!$K$2:$K$825)), ROW(33:33))), "")} | H36: {=IFERROR(INDEX('Bank Schedule'!H:H, SMALL(IF('Bank Schedule'!$K$2:$K$825="Vacant", ROW('Bank Schedule'!$K$2:$K$825)), ROW(33:33))), "")} | I36: {=IFERROR(INDEX('Bank Schedule'!I:I, SMALL(IF('Bank Schedule'!$K$2:$K$825="Vacant", ROW('Bank Schedule'!$K$2:$K$825)), ROW(33:33))), "")} | J36: {=IFERROR(INDEX('Bank Schedule'!J:J, SMALL(IF('Bank Schedule'!$K$2:$K$825="Vacant", ROW('Bank Schedule'!$K$2:$K$825)), ROW(33:33))), "")} | K36: {=IFERROR(INDEX('Bank Schedule'!K:K, SMALL(IF('Bank Schedule'!$K$2:$K$825="Vacant", ROW('Bank Schedule'!$K$2:$K$825)), ROW(33:33))), "")} | L36: {=IFERROR(INDEX('Bank Schedule'!L:L, SMALL(IF('Bank Schedule'!$K$2:$K$825="Vacant", ROW('Bank Schedule'!$K$2:$K$825)), ROW(33:33))), "")} | M36: {=IFERROR(INDEX('Bank Schedule'!M:M, SMALL(IF('Bank Schedule'!$K$2:$K$825="Vacant", ROW('Bank Schedule'!$K$2:$K$825)), ROW(33:33))), "")} | N36: {=IFERROR(INDEX('Bank Schedule'!N:N, SMALL(IF('Bank Schedule'!$K$2:$K$825="Vacant", ROW('Bank Schedule'!$K$2:$K$825)), ROW(33:33))), "")} | O36: {=IFERROR(INDEX('Bank Schedule'!O:O, SMALL(IF('Bank Schedule'!$K$2:$K$825="Vacant", ROW('Bank Schedule'!$K$2:$K$825)), ROW(33:33))), "")} | P36: {=IFERROR(INDEX('Bank Schedule'!P:P, SMALL(IF('Bank Schedule'!$K$2:$K$825="Vacant", ROW('Bank Schedule'!$K$2:$K$825)), ROW(33:33))), "")} | Q36: {=IFERROR(INDEX('Bank Schedule'!Q:Q, SMALL(IF('Bank Schedule'!$K$2:$K$825="Vacant", ROW('Bank Schedule'!$K$2:$K$825)), ROW(33:33))), "")} | R36: {=IFERROR(INDEX('Bank Schedule'!R:R, SMALL(IF('Bank Schedule'!$K$2:$K$825="Vacant", ROW('Bank Schedule'!$K$2:$K$825)), ROW(33:33))), "")} | S36: {=IFERROR(INDEX('Bank Schedule'!S:S, SMALL(IF('Bank Schedule'!$K$2:$K$825="Vacant", ROW('Bank Schedule'!$K$2:$K$825)), ROW(33:33))), "")} | T36: {=IFERROR(INDEX('Bank Schedule'!T:T, SMALL(IF('Bank Schedule'!$K$2:$K$825="Vacant", ROW('Bank Schedule'!$K$2:$K$825)), ROW(33:33))), "")} | U36: {=IFERROR(INDEX('Bank Schedule'!U:U, SMALL(IF('Bank Schedule'!$K$2:$K$825="Vacant", ROW('Bank Schedule'!$K$2:$K$825)), ROW(33:33))), "")} | V36: {=IFERROR(INDEX('Bank Schedule'!V:V, SMALL(IF('Bank Schedule'!$K$2:$K$825="Vacant", ROW('Bank Schedule'!$K$2:$K$825)), ROW(33:33))), "")} | W36: {=IFERROR(INDEX('Bank Schedule'!W:W, SMALL(IF('Bank Schedule'!$K$2:$K$825="Vacant", ROW('Bank Schedule'!$K$2:$K$825)), ROW(33:33))), "")} | X36: {=IFERROR(INDEX('Bank Schedule'!X:X, SMALL(IF('Bank Schedule'!$K$2:$K$825="Vacant", ROW('Bank Schedule'!$K$2:$K$825)), ROW(33:33))), "")} | Y36: {=IFERROR(INDEX('Bank Schedule'!Y:Y, SMALL(IF('Bank Schedule'!$K$2:$K$825="Vacant", ROW('Bank Schedule'!$K$2:$K$825)), ROW(33:33))), "")} | Z36: {=IFERROR(INDEX('Bank Schedule'!Z:Z, SMALL(IF('Bank Schedule'!$K$2:$K$825="Vacant", ROW('Bank Schedule'!$K$2:$K$825)), ROW(33:33))), "")} | AA36: {=IFERROR(INDEX('Bank Schedule'!AA:AA, SMALL(IF('Bank Schedule'!$K$2:$K$825="Vacant", ROW('Bank Schedule'!$K$2:$K$825)), ROW(33:33))), "")} | AB36: {=IFERROR(INDEX('Bank Schedule'!AB:AB, SMALL(IF('Bank Schedule'!$K$2:$K$825="Vacant", ROW('Bank Schedule'!$K$2:$K$825)), ROW(33:33))), "")} | AC36: {=IFERROR(INDEX('Bank Schedule'!AC:AC, SMALL(IF('Bank Schedule'!$K$2:$K$825="Vacant", ROW('Bank Schedule'!$K$2:$K$825)), ROW(33:33))), "")} | AD36: {=IFERROR(INDEX('Bank Schedule'!AD:AD, SMALL(IF('Bank Schedule'!$K$2:$K$825="Vacant", ROW('Bank Schedule'!$K$2:$K$825)), ROW(33:33))), "")} | AE36: {=IFERROR(INDEX('Bank Schedule'!AE:AE, SMALL(IF('Bank Schedule'!$K$2:$K$825="Vacant", ROW('Bank Schedule'!$K$2:$K$825)), ROW(33:33))), "")} | AF36: {=IFERROR(INDEX('Bank Schedule'!AF:AF, SMALL(IF('Bank Schedule'!$K$2:$K$825="Vacant", ROW('Bank Schedule'!$K$2:$K$825)), ROW(33:33))), "")} | AG36: {=IFERROR(INDEX('Bank Schedule'!AG:AG, SMALL(IF('Bank Schedule'!$K$2:$K$825="Vacant", ROW('Bank Schedule'!$K$2:$K$825)), ROW(33:33))), "")} | AH36: {=IFERROR(INDEX('Bank Schedule'!AH:AH, SMALL(IF('Bank Schedule'!$K$2:$K$825="Vacant", ROW('Bank Schedule'!$K$2:$K$825)), ROW(33:33))), "")}
A37: {=IFERROR(INDEX('Bank Schedule'!A:A, SMALL(IF('Bank Schedule'!$K$2:$K$825="Vacant", ROW('Bank Schedule'!$K$2:$K$825)), ROW(34:34))), "")} | B37: {=IFERROR(INDEX('Bank Schedule'!B:B, SMALL(IF('Bank Schedule'!$K$2:$K$825="Vacant", ROW('Bank Schedule'!$K$2:$K$825)), ROW(34:34))), "")} | C37: {=IFERROR(INDEX('Bank Schedule'!C:C, SMALL(IF('Bank Schedule'!$K$2:$K$825="Vacant", ROW('Bank Schedule'!$K$2:$K$825)), ROW(34:34))), "")} | D37: {=IFERROR(INDEX('Bank Schedule'!D:D, SMALL(IF('Bank Schedule'!$K$2:$K$825="Vacant", ROW('Bank Schedule'!$K$2:$K$825)), ROW(34:34))), "")} | E37: {=IFERROR(INDEX('Bank Schedule'!E:E, SMALL(IF('Bank Schedule'!$K$2:$K$825="Vacant", ROW('Bank Schedule'!$K$2:$K$825)), ROW(34:34))), "")} | F37: {=IFERROR(INDEX('Bank Schedule'!F:F, SMALL(IF('Bank Schedule'!$K$2:$K$825="Vacant", ROW('Bank Schedule'!$K$2:$K$825)), ROW(34:34))), "")} | G37: {=IFERROR(INDEX('Bank Schedule'!G:G, SMALL(IF('Bank Schedule'!$K$2:$K$825="Vacant", ROW('Bank Schedule'!$K$2:$K$825)), ROW(34:34))), "")} | H37: {=IFERROR(INDEX('Bank Schedule'!H:H, SMALL(IF('Bank Schedule'!$K$2:$K$825="Vacant", ROW('Bank Schedule'!$K$2:$K$825)), ROW(34:34))), "")} | I37: {=IFERROR(INDEX('Bank Schedule'!I:I, SMALL(IF('Bank Schedule'!$K$2:$K$825="Vacant", ROW('Bank Schedule'!$K$2:$K$825)), ROW(34:34))), "")} | J37: {=IFERROR(INDEX('Bank Schedule'!J:J, SMALL(IF('Bank Schedule'!$K$2:$K$825="Vacant", ROW('Bank Schedule'!$K$2:$K$825)), ROW(34:34))), "")} | K37: {=IFERROR(INDEX('Bank Schedule'!K:K, SMALL(IF('Bank Schedule'!$K$2:$K$825="Vacant", ROW('Bank Schedule'!$K$2:$K$825)), ROW(34:34))), "")} | L37: {=IFERROR(INDEX('Bank Schedule'!L:L, SMALL(IF('Bank Schedule'!$K$2:$K$825="Vacant", ROW('Bank Schedule'!$K$2:$K$825)), ROW(34:34))), "")} | M37: {=IFERROR(INDEX('Bank Schedule'!M:M, SMALL(IF('Bank Schedule'!$K$2:$K$825="Vacant", ROW('Bank Schedule'!$K$2:$K$825)), ROW(34:34))), "")} | N37: {=IFERROR(INDEX('Bank Schedule'!N:N, SMALL(IF('Bank Schedule'!$K$2:$K$825="Vacant", ROW('Bank Schedule'!$K$2:$K$825)), ROW(34:34))), "")} | O37: {=IFERROR(INDEX('Bank Schedule'!O:O, SMALL(IF('Bank Schedule'!$K$2:$K$825="Vacant", ROW('Bank Schedule'!$K$2:$K$825)), ROW(34:34))), "")} | P37: {=IFERROR(INDEX('Bank Schedule'!P:P, SMALL(IF('Bank Schedule'!$K$2:$K$825="Vacant", ROW('Bank Schedule'!$K$2:$K$825)), ROW(34:34))), "")} | Q37: {=IFERROR(INDEX('Bank Schedule'!Q:Q, SMALL(IF('Bank Schedule'!$K$2:$K$825="Vacant", ROW('Bank Schedule'!$K$2:$K$825)), ROW(34:34))), "")} | R37: {=IFERROR(INDEX('Bank Schedule'!R:R, SMALL(IF('Bank Schedule'!$K$2:$K$825="Vacant", ROW('Bank Schedule'!$K$2:$K$825)), ROW(34:34))), "")} | S37: {=IFERROR(INDEX('Bank Schedule'!S:S, SMALL(IF('Bank Schedule'!$K$2:$K$825="Vacant", ROW('Bank Schedule'!$K$2:$K$825)), ROW(34:34))), "")} | T37: {=IFERROR(INDEX('Bank Schedule'!T:T, SMALL(IF('Bank Schedule'!$K$2:$K$825="Vacant", ROW('Bank Schedule'!$K$2:$K$825)), ROW(34:34))), "")} | U37: {=IFERROR(INDEX('Bank Schedule'!U:U, SMALL(IF('Bank Schedule'!$K$2:$K$825="Vacant", ROW('Bank Schedule'!$K$2:$K$825)), ROW(34:34))), "")} | V37: {=IFERROR(INDEX('Bank Schedule'!V:V, SMALL(IF('Bank Schedule'!$K$2:$K$825="Vacant", ROW('Bank Schedule'!$K$2:$K$825)), ROW(34:34))), "")} | W37: {=IFERROR(INDEX('Bank Schedule'!W:W, SMALL(IF('Bank Schedule'!$K$2:$K$825="Vacant", ROW('Bank Schedule'!$K$2:$K$825)), ROW(34:34))), "")} | X37: {=IFERROR(INDEX('Bank Schedule'!X:X, SMALL(IF('Bank Schedule'!$K$2:$K$825="Vacant", ROW('Bank Schedule'!$K$2:$K$825)), ROW(34:34))), "")} | Y37: {=IFERROR(INDEX('Bank Schedule'!Y:Y, SMALL(IF('Bank Schedule'!$K$2:$K$825="Vacant", ROW('Bank Schedule'!$K$2:$K$825)), ROW(34:34))), "")} | Z37: {=IFERROR(INDEX('Bank Schedule'!Z:Z, SMALL(IF('Bank Schedule'!$K$2:$K$825="Vacant", ROW('Bank Schedule'!$K$2:$K$825)), ROW(34:34))), "")} | AA37: {=IFERROR(INDEX('Bank Schedule'!AA:AA, SMALL(IF('Bank Schedule'!$K$2:$K$825="Vacant", ROW('Bank Schedule'!$K$2:$K$825)), ROW(34:34))), "")} | AB37: {=IFERROR(INDEX('Bank Schedule'!AB:AB, SMALL(IF('Bank Schedule'!$K$2:$K$825="Vacant", ROW('Bank Schedule'!$K$2:$K$825)), ROW(34:34))), "")} | AC37: {=IFERROR(INDEX('Bank Schedule'!AC:AC, SMALL(IF('Bank Schedule'!$K$2:$K$825="Vacant", ROW('Bank Schedule'!$K$2:$K$825)), ROW(34:34))), "")} | AD37: {=IFERROR(INDEX('Bank Schedule'!AD:AD, SMALL(IF('Bank Schedule'!$K$2:$K$825="Vacant", ROW('Bank Schedule'!$K$2:$K$825)), ROW(34:34))), "")} | AE37: {=IFERROR(INDEX('Bank Schedule'!AE:AE, SMALL(IF('Bank Schedule'!$K$2:$K$825="Vacant", ROW('Bank Schedule'!$K$2:$K$825)), ROW(34:34))), "")} | AF37: {=IFERROR(INDEX('Bank Schedule'!AF:AF, SMALL(IF('Bank Schedule'!$K$2:$K$825="Vacant", ROW('Bank Schedule'!$K$2:$K$825)), ROW(34:34))), "")} | AG37: {=IFERROR(INDEX('Bank Schedule'!AG:AG, SMALL(IF('Bank Schedule'!$K$2:$K$825="Vacant", ROW('Bank Schedule'!$K$2:$K$825)), ROW(34:34))), "")} | AH37: {=IFERROR(INDEX('Bank Schedule'!AH:AH, SMALL(IF('Bank Schedule'!$K$2:$K$825="Vacant", ROW('Bank Schedule'!$K$2:$K$825)), ROW(34:34))), "")}
A38: {=IFERROR(INDEX('Bank Schedule'!A:A, SMALL(IF('Bank Schedule'!$K$2:$K$825="Vacant", ROW('Bank Schedule'!$K$2:$K$825)), ROW(35:35))), "")} | B38: {=IFERROR(INDEX('Bank Schedule'!B:B, SMALL(IF('Bank Schedule'!$K$2:$K$825="Vacant", ROW('Bank Schedule'!$K$2:$K$825)), ROW(35:35))), "")} | C38: {=IFERROR(INDEX('Bank Schedule'!C:C, SMALL(IF('Bank Schedule'!$K$2:$K$825="Vacant", ROW('Bank Schedule'!$K$2:$K$825)), ROW(35:35))), "")} | D38: {=IFERROR(INDEX('Bank Schedule'!D:D, SMALL(IF('Bank Schedule'!$K$2:$K$825="Vacant", ROW('Bank Schedule'!$K$2:$K$825)), ROW(35:35))), "")} | E38: {=IFERROR(INDEX('Bank Schedule'!E:E, SMALL(IF('Bank Schedule'!$K$2:$K$825="Vacant", ROW('Bank Schedule'!$K$2:$K$825)), ROW(35:35))), "")} | F38: {=IFERROR(INDEX('Bank Schedule'!F:F, SMALL(IF('Bank Schedule'!$K$2:$K$825="Vacant", ROW('Bank Schedule'!$K$2:$K$825)), ROW(35:35))), "")} | G38: {=IFERROR(INDEX('Bank Schedule'!G:G, SMALL(IF('Bank Schedule'!$K$2:$K$825="Vacant", ROW('Bank Schedule'!$K$2:$K$825)), ROW(35:35))), "")} | H38: {=IFERROR(INDEX('Bank Schedule'!H:H, SMALL(IF('Bank Schedule'!$K$2:$K$825="Vacant", ROW('Bank Schedule'!$K$2:$K$825)), ROW(35:35))), "")} | I38: {=IFERROR(INDEX('Bank Schedule'!I:I, SMALL(IF('Bank Schedule'!$K$2:$K$825="Vacant", ROW('Bank Schedule'!$K$2:$K$825)), ROW(35:35))), "")} | J38: {=IFERROR(INDEX('Bank Schedule'!J:J, SMALL(IF('Bank Schedule'!$K$2:$K$825="Vacant", ROW('Bank Schedule'!$K$2:$K$825)), ROW(35:35))), "")} | K38: {=IFERROR(INDEX('Bank Schedule'!K:K, SMALL(IF('Bank Schedule'!$K$2:$K$825="Vacant", ROW('Bank Schedule'!$K$2:$K$825)), ROW(35:35))), "")} | L38: {=IFERROR(INDEX('Bank Schedule'!L:L, SMALL(IF('Bank Schedule'!$K$2:$K$825="Vacant", ROW('Bank Schedule'!$K$2:$K$825)), ROW(35:35))), "")} | M38: {=IFERROR(INDEX('Bank Schedule'!M:M, SMALL(IF('Bank Schedule'!$K$2:$K$825="Vacant", ROW('Bank Schedule'!$K$2:$K$825)), ROW(35:35))), "")} | N38: {=IFERROR(INDEX('Bank Schedule'!N:N, SMALL(IF('Bank Schedule'!$K$2:$K$825="Vacant", ROW('Bank Schedule'!$K$2:$K$825)), ROW(35:35))), "")} | O38: {=IFERROR(INDEX('Bank Schedule'!O:O, SMALL(IF('Bank Schedule'!$K$2:$K$825="Vacant", ROW('Bank Schedule'!$K$2:$K$825)), ROW(35:35))), "")} | P38: {=IFERROR(INDEX('Bank Schedule'!P:P, SMALL(IF('Bank Schedule'!$K$2:$K$825="Vacant", ROW('Bank Schedule'!$K$2:$K$825)), ROW(35:35))), "")} | Q38: {=IFERROR(INDEX('Bank Schedule'!Q:Q, SMALL(IF('Bank Schedule'!$K$2:$K$825="Vacant", ROW('Bank Schedule'!$K$2:$K$825)), ROW(35:35))), "")} | R38: {=IFERROR(INDEX('Bank Schedule'!R:R, SMALL(IF('Bank Schedule'!$K$2:$K$825="Vacant", ROW('Bank Schedule'!$K$2:$K$825)), ROW(35:35))), "")} | S38: {=IFERROR(INDEX('Bank Schedule'!S:S, SMALL(IF('Bank Schedule'!$K$2:$K$825="Vacant", ROW('Bank Schedule'!$K$2:$K$825)), ROW(35:35))), "")} | T38: {=IFERROR(INDEX('Bank Schedule'!T:T, SMALL(IF('Bank Schedule'!$K$2:$K$825="Vacant", ROW('Bank Schedule'!$K$2:$K$825)), ROW(35:35))), "")} | U38: {=IFERROR(INDEX('Bank Schedule'!U:U, SMALL(IF('Bank Schedule'!$K$2:$K$825="Vacant", ROW('Bank Schedule'!$K$2:$K$825)), ROW(35:35))), "")} | V38: {=IFERROR(INDEX('Bank Schedule'!V:V, SMALL(IF('Bank Schedule'!$K$2:$K$825="Vacant", ROW('Bank Schedule'!$K$2:$K$825)), ROW(35:35))), "")} | W38: {=IFERROR(INDEX('Bank Schedule'!W:W, SMALL(IF('Bank Schedule'!$K$2:$K$825="Vacant", ROW('Bank Schedule'!$K$2:$K$825)), ROW(35:35))), "")} | X38: {=IFERROR(INDEX('Bank Schedule'!X:X, SMALL(IF('Bank Schedule'!$K$2:$K$825="Vacant", ROW('Bank Schedule'!$K$2:$K$825)), ROW(35:35))), "")} | Y38: {=IFERROR(INDEX('Bank Schedule'!Y:Y, SMALL(IF('Bank Schedule'!$K$2:$K$825="Vacant", ROW('Bank Schedule'!$K$2:$K$825)), ROW(35:35))), "")} | Z38: {=IFERROR(INDEX('Bank Schedule'!Z:Z, SMALL(IF('Bank Schedule'!$K$2:$K$825="Vacant", ROW('Bank Schedule'!$K$2:$K$825)), ROW(35:35))), "")} | AA38: {=IFERROR(INDEX('Bank Schedule'!AA:AA, SMALL(IF('Bank Schedule'!$K$2:$K$825="Vacant", ROW('Bank Schedule'!$K$2:$K$825)), ROW(35:35))), "")} | AB38: {=IFERROR(INDEX('Bank Schedule'!AB:AB, SMALL(IF('Bank Schedule'!$K$2:$K$825="Vacant", ROW('Bank Schedule'!$K$2:$K$825)), ROW(35:35))), "")} | AC38: {=IFERROR(INDEX('Bank Schedule'!AC:AC, SMALL(IF('Bank Schedule'!$K$2:$K$825="Vacant", ROW('Bank Schedule'!$K$2:$K$825)), ROW(35:35))), "")} | AD38: {=IFERROR(INDEX('Bank Schedule'!AD:AD, SMALL(IF('Bank Schedule'!$K$2:$K$825="Vacant", ROW('Bank Schedule'!$K$2:$K$825)), ROW(35:35))), "")} | AE38: {=IFERROR(INDEX('Bank Schedule'!AE:AE, SMALL(IF('Bank Schedule'!$K$2:$K$825="Vacant", ROW('Bank Schedule'!$K$2:$K$825)), ROW(35:35))), "")} | AF38: {=IFERROR(INDEX('Bank Schedule'!AF:AF, SMALL(IF('Bank Schedule'!$K$2:$K$825="Vacant", ROW('Bank Schedule'!$K$2:$K$825)), ROW(35:35))), "")} | AG38: {=IFERROR(INDEX('Bank Schedule'!AG:AG, SMALL(IF('Bank Schedule'!$K$2:$K$825="Vacant", ROW('Bank Schedule'!$K$2:$K$825)), ROW(35:35))), "")} | AH38: {=IFERROR(INDEX('Bank Schedule'!AH:AH, SMALL(IF('Bank Schedule'!$K$2:$K$825="Vacant", ROW('Bank Schedule'!$K$2:$K$825)), ROW(35:35))), "")}
